Workbook

Sheet Лист1
A1: Олмазор тумани Тиббиёт Бирлашмаси томонидан 2018 йил ноябрь ойи иш хаки суммалари поликлиникалар кесимида
A2: Ташкилот номи | B2: Суммаси | C2: Санаси | D2: Кабул килди: ФИО | E2: Имзо
A3: 5-Детская стоматологическая поликлиника | B3: 10 182 556,00
A4: 4- Тери Таносил Касалликлар диспансери | B4: 28 122 959,00
A5: Противотуберкулезный диспансер №3 | B5: 32 529 279,00
A6: Олмазор туман Марказий куп тармокли поликлиника | B6: 86830534
A7: 14 Оилавий поликлиника | B7: 30 725 181,00
A8: 15 Семейная поликлиника | B8: 36 774 668,00
A9: 16 Оилавий поликлиника | B9: 51202266
A10: 17-Оилавий поликлиника | B10: 20 644 086,00
A11: 20-сон оилавий поликлиника | B11: 22 068 389,00
A12: 21 - семейная поликлиника | B12: 28 867 178,00
A13: Олмазор туман 18 оилавий поликлиника | B13: 26 166 414,00
A14: Олмазор тумани 19 Оилавий поликлиника | B14: 38 203 767,00
A15: Талабалар шахарчаси Марказий кўптармоқли поликлиника | B15: 24 516 602,00
A16: Жами | B16: 436833879
A18: Бош Хисобчи | B18: Рустамова Ш.С
A20: ТТБ бошлиги | B20: Миралимов М.М

Sheet 11,2018
A1: № | B1: НАИМЕНОВАНИЯ | C1: ИНПС | D1: ЕСП | E1: ПОД НАЛ | F1: ЕНП | G1: ОПЛАТА | H1: БАЛАНС | I1: ФИН РЕЗ | J1: ПЕНСИЯ
A2: 1 | B2: AVTOMOTOHAVASKOR TALABALAR , ИНН: 304651169 | K2: 36275148
A3: 2 | B3: "ASADTILLO BIZNES" ИНН : 304453422 | K3: 13540974 | L3: НДС
A4: 3 | B4: "INSHOOT MAXSUSMONTAJ QURILISH" ИНН : 301716199 | C4: картотека | K4: 33979629 | L4: НДС
A5: 4 | B5: "ЧП ENGLISH SERVICE" ИНН: 303256439 | K5: 72641824 | L5: НДС
A6: 5 | B6: "MUZAFFARXO`JA-HILOL" Х.Ф. ИНН: 206450634 | K6: 84564973 | L6: НДС
A7: 6 | B7: "STUDY GUIDE" ИНН: 303408381 | K7: 45313285
A8: 7 | B8: "ЧП INTER PROF EDUCATION" ИНН: 304107369 | K8: 88700206
A9: 8 | B9: "AVTOMOTOHAVASKORLAR YANGIOBOD" ИНН: 304632864 | K9: 86722119
A10: 9 | B10: "DILFUZAXON AVTO" ИНН: 304825630 | K10: 35324962
A11: 10 | B11: "GLOBALMED" , ИНН: 304979653 | K11: 100186 | L11: НДС
A12: 11 | B12: "УП CHORBOG` AVTOUSTOZ" ИНН: 305133922 | K12: 50995539
A13: 12 | B13: "C A WOLVES" , ИНН: 305713761 | C13: нет ещё | K13: 100186
A14: 13 | B14: "MUXLISA NUR FARM" ИНН: 303004885 | K14: 100186
A15: 14 | B15: "AKJ SEBZOR BO`LIMI" , ИНН: 305150198 | K15: 100186
A16: 15 | B16: ООО "MUBINA RAYONA BUSINESS" ИНН: 305023742 | C16: картотека | K16: 34406143
A17: 16 | B17: "RUSLAN GRAND "ИНН: 303451710 | K17: 23956654
A18: 17 | B18: "GULBAHOR BUSINESS" ИНН: 304737756 | C18: картотека | K18: 100186
A19: 18 | B19: ABSOLUTE STRENGTH NTM , ИНН: 303434754 | C19: картотека | K19: 100186
A20: 19 | B20: "FLY HIGH TICKET" ИНН: 305650493 | C20: картотека | K20: 100186
A21: 20 | B21: "SHINEART MCHJ" ИНН: 300821821 | C21: картотека | K21: 100186
A22: 21 | B22: ЯТТ 537852647 Акрамов | C22: керакмас | K22: 100186
A23: 22 | B23: "MCHJ "METCOM" VAKOLATXONASI" ИНН: 207285442, | K23: 100186

Sheet 01,2019
A1: № | B1: НАИМЕНОВАНИЯ | C1: ЕСП и Подоход и ИНПС | D1: 10604-2 вода | E1: 10201-9 прибыль | F1: 10401-6,7 Имущество | G1: 10507-1 Земля | H1: ЕНП, НДС | I1: ОПЛАТА | J1: БАЛАНС | K1: ФИН РЕЗ
A2: 1 | B2: AVTOMOTOHAVASKOR TALABALAR , ИНН: 304651169 | L2: 36275148
A3: 2 | B3: "ASADTILLO BIZNES" ИНН : 304453422 | L3: 13540974 | M3: НДС
A4: 3 | B4: "INSHOOT MAXSUSMONTAJ QURILISH" ИНН : 301716199 | L4: 33979629 | M4: НДС
A5: 4 | B5: "ЧП ENGLISH SERVICE" ИНН: 303256439 | L5: 72641824 | M5: НДС
A6: 5 | B6: "MUZAFFARXO`JA-HILOL" Х.Ф. ИНН: 206450634 | L6: 84564973 | M6: НДС
A7: 6 | B7: "STUDY GUIDE" ИНН: 303408381 | L7: 45313285
A8: 7 | B8: "ЧП INTER PROF EDUCATION" ИНН: 304107369 | L8: 88700206
A9: 8 | B9: "AVTOMOTOHAVASKORLAR YANGIOBOD" ИНН: 304632864 | L9: 86722119
A10: 9 | B10: "DILFUZAXON AVTO" ИНН: 304825630 | L10: 35324962
A11: 10 | B11: "GLOBALMED" , ИНН: 304979653 | L11: 100186 | M11: НДС
A12: 11 | B12: "MEDICOM" ИНН:305925047 | L12: 100186
A13: 12 | B13: "УП CHORBOG` AVTOUSTOZ" ИНН: 305133922 | L13: 50995539
A14: 13 | B14: "C A WOLVES" , ИНН: 305713761 | L14: 100186
A15: 14 | B15: "MUXLISA NUR FARM" ИНН: 303004885 | L15: 100186
A16: 15 | B16: "AKJ SEBZOR BO`LIMI" , ИНН: 305150198 | L16: 100186
A17: 16 | B17: ООО "MUBINA RAYONA BUSINESS" ИНН: 305023742 | L17: 34406143
A18: 17 | B18: "RUSLAN GRAND "ИНН: 303451710 | D18: суммали | F18: суммали | G18: суммали | L18: 23956654
A19: 18 | B19: ЯТТ 537852647 Акрамов | L19: 100186
A20: 19 | B20: "MCHJ "METCOM" VAKOLATXONASI" ИНН: 20728544 | L20: 100186
A21: 20 | B21: "ТСТ CLUSTER" 305904904 | L21: 100186
A22: 21 | B22: "WALL STREET ACADEMY" 306116238 | L22: 100186
A23: 22

Sheet 12,2018 
A1: № | B1: НАИМЕНОВАНИЯ | C1: ИНПС | D1: ЕСП | E1: 10604-2 вода | F1: 10201-9 прибыль | G1: 10401-6,7 Имущество | H1: 10507-1 Земля | I1: ПОД НАЛ | J1: ЕНП | K1: ОПЛАТА | L1: БАЛАНС | M1: ФИН РЕЗ
A2: 1 | B2: AVTOMOTOHAVASKOR TALABALAR , ИНН: 304651169 | N2: 36275148
A3: 2 | B3: "ASADTILLO BIZNES" ИНН : 304453422 | N3: 13540974 | O3: НДС
A4: 3 | B4: "INSHOOT MAXSUSMONTAJ QURILISH" ИНН : 301716199 | C4: картотека | N4: 33979629 | O4: НДС
A5: 4 | B5: "ЧП ENGLISH SERVICE" ИНН: 303256439 | N5: 72641824 | O5: НДС
A6: 5 | B6: "MUZAFFARXO`JA-HILOL" Х.Ф. ИНН: 206450634 | N6: 84564973 | O6: НДС
A7: 6 | B7: "STUDY GUIDE" ИНН: 303408381 | N7: 45313285
A8: 7 | B8: "ЧП INTER PROF EDUCATION" ИНН: 304107369 | N8: 88700206
A9: 8 | B9: "AVTOMOTOHAVASKORLAR YANGIOBOD" ИНН: 304632864 | N9: 86722119
A10: 9 | B10: "DILFUZAXON AVTO" ИНН: 304825630 | N10: 35324962
A11: 10 | B11: "GLOBALMED" , ИНН: 304979653 | N11: 100186 | O11: НДС
A12: 11 | B12: "УП CHORBOG` AVTOUSTOZ" ИНН: 305133922 | N12: 50995539
A13: 12 | B13: "C A WOLVES" , ИНН: 305713761 | C13: нет ещё | N13: 100186
A14: 13 | B14: "MUXLISA NUR FARM" ИНН: 303004885 | N14: 100186
A15: 14 | B15: "AKJ SEBZOR BO`LIMI" , ИНН: 305150198 | N15: 100186
A16: 15 | B16: ООО "MUBINA RAYONA BUSINESS" ИНН: 305023742 | C16: картотека | N16: 34406143
A17: 16 | B17: "RUSLAN GRAND "ИНН: 303451710 | E17: суммали | G17: суммали | H17: суммали | N17: 23956654
A18: 18 | B18: "MCHJ "METCOM" VAKOLATXONASI" ИНН: 20728544 | N18: 100186
A19: 19 | B19: "WALL STREET ACADEMY " 306116238
A20: 17 | B20: ЯТТ 537852647 Акрамов | C20: керакмас | N20: 100186

Sheet 25-29
B1: ЯНВАР | C1: ФЕВРАЛ | D1: МАРТ | E1: АПРЕЛЬ | F1: МАЙ | G1: ИЮНЬ | H1: ИЮЛЬ | I1: АВГУСТ | J1: СЕНТЯБРЬ | K1: ОКТЯБРЬ | L1: НОЯБРЬ | M1: ДЕКАБРЬ
A2: ПОДОХОД 25
A3: ПЕНСИЯ 25
A4: ПОДОХОД 29
A5: ПЕНСИЯ 29
A8: 100186

Sheet клиенты НДС
A1: № | B1: НАИМЕНОВАНИЯ | C1: ИНН | D1: эгаси | F1: сабаб
A2: 1 | B2: ЧП "MATYUSUF SALAEV" | C2: 206155668 | D2: Розия | F2: Охирги ўн икки ой ичида солиқ ҳисоботларини ўз вақтида тақдим этмаслик ҳолатлари мавжуд бўлганлиги
A3: 2 | B3: "MUZAFFARXO`JA-HILOL" Х.Ф. | C3: 206450634 | D3: Ёркиной
A4: 3 | B4: "SHIRIN LYUKS TAOM" 01.09.2021 | C4: 302813323 | D4: Ёркиной
A5: 4 | B5: "STUDY GUIDE" | C5: 303408381 | D5: Розия
A6: 5 | B6: "ЧП INTER PROF EDUCATION" | C6: 304107369 | D6: Розия
A7: 6 | B7: DORKOMPLEKTSNAB PLUS | C7: 304384359 | D7: Ёркиной | F7: Охирги ўн икки ой ичида солиқ ҳисоботларини ўз вақтида тақдим этмаслик ҳолатлари мавжуд бўлганлиги
A8: 7 | B8: MIRIRMONTAJ MCHJ | C8: 304459144 | D8: Ёркиной | F8: Охирги ўн икки ой ичида солиқ ҳисоботларини ўз вақтида тақдим этмаслик ҳолатлари мавжуд бўлганлиги
A9: 8 | B9: "AVTOMOTOHAVASKORLAR YANGIOBOD" | C9: 304632864 | D9: Розия | F9: Охирги ўн икки ой ичида солиқ ҳисоботларини ўз вақтида тақдим этмаслик ҳолатлари мавжуд бўлганлиги
A10: 9 | B10: "FLY TOURISM" | C10: 304801376 | D10: Розия
A11: 10 | B11: "DILFUZAXON AVTO" | C11: 304825630 | D11: Розия | F11: Охирги ўн икки ой ичида солиқ ҳисоботларини ўз вақтида тақдим этмаслик ҳолатлари мавжуд бўлганлиги
A12: 11 | B12: AVTOHAVASKOR CHORSU | C12: 305099119 | D12: Розия | F12: Охирги ўн икки ой ичида солиқ ҳисоботларини ўз вақтида тақдим этмаслик ҳолатлари мавжуд бўлганлиги
A13: 12 | B13: "УП CHORBOG` AVTOUSTOZ" | C13: 305133922 | D13: Розия | F13: Охирги ўн икки ой ичида солиқ ҳисоботларини ўз вақтида тақдим этмаслик ҳолатлари мавжуд бўлганлиги
A14: 13 | B14: "AKJ SEBZOR BO`LIMI" | C14: 305150198 | D14: Розия | F14: Охирги ўн икки ой ичида солиқ ҳисоботларини ўз вақтида тақдим этмаслик ҳолатлари мавжуд бўлганлиги
A15: 14 | B15: "TRANS SERVIS UK" YUNUSOBOD | C15: 305502390 | D15: Розия
A16: 15 | B16: "LANGUAGE ACADEMY" | C16: 305610162 | D16: Розия
A17: 16 | B17: ЧП "PREMIUM TRADING INVEST" | C17: 305630035 | D17: Ёркиной | F17: Охирги ўн икки ой ичида солиқ ҳисоботларини ўз вақтида тақдим этмаслик ҳолатлари мавжуд бўлганлиги
A18: 17 | B18: "C A WOLVES" | C18: 305713761 | D18: Розия | F18: Охирги ўн икки ой ичида солиқ ҳисоботларини ўз вақтида тақдим этмаслик ҳолатлари мавжуд бўлганлиги
A19: 18 | B19: "AVTO DRIVE AKJ" NTM QATORTOL | C19: 305804094 | D19: Розия
A20: 19 | B20: ЧП "MASHXUR TAOM BIZNES" | C20: 305883924 | D20: Ёркиной | F20: Уч ойдан ортиқ вақт давомида молия-хўжалик фаолияти амалга оширилмаганлиги
A21: 20 | B21: HILOL PHARM | C21: 305979201 | D21: Ёркиной | F21: Ходимлари ёки ёлланма ишчилари сони 4 кишидан кам бўлганлиги
A22: 21 | B22: "WALL STREET ACADEMY" | C22: 306116238 | D22: Розия
A23: 22 | B23: "TEACHER`S AUTO SCHOOL" | C23: 306166287 | D23: Розия
A24: 23 | B24: "AVTO SCHOOL" NTM QORAQAMISH | C24: 306214227 | D24: Розия
A25: 24 | B25: " SAM INC" | C25: 306349905 | D25: Ёркиной | F25: Ходимлари ёки ёлланма ишчилари сони 4 кишидан кам бўлганлиги
A26: 25 | B26: "AVTO BEST STUDY" NTM SERGELI | C26: 306372744 | D26: Розия
A27: 26 | B27: "AVTO DRIVE ELEGANT" NTM RISIVIY | C27: 306382810 | D27: Розия
A28: 27 | B28: "LIVING STONE" МЧЖ | C28: 306700191 | D28: Ёркиной | F28: Ходимлари ёки ёлланма ишчилари сони 4 кишидан кам бўлганлиги
A29: 28 | B29: ДОО "KIDS NUR CITY" | C29: 306774385 | D29: Розия
A30: 29 | B30: "AL-AZIZ ACADEMY" НОУ | C30: 306784151 | D30: Розия
A31: 30 | B31: "ZIP LINE" | C31: 306865683 | D31: Ёркиной | F31: Солиқ тўловчининг раҳбари бир вақтнинг ўзида бошқа солиқ тўловчида (юридик шахсда) раҳбар бўлиб, ушбу солиқ тўловчида солиқ қарзи мавжуд бўлганда ёхуд солиқ ҳисоботларини тақдим этилмаганлиги
A32: 31 | B32: ЧП "LIGHT-MED" | C32: 306911088 | D32: Ёркиной | F32: Ходимлари ёки ёлланма ишчилари сони 4 кишидан кам бўлганлиги
A33: 32 | B33: OOO "SS-MOBILE ELECTRONICS" | C33: 306924332 | D33: Ёркиной
A34: 33 | B34: DAMBO STORY MCHJ | C34: 307051200 | D34: Ёркиной | F34: Охирги ўн икки ой ичида солиқ ҳисоботларини ўз вақтида тақдим этмаслик ҳолатлари мавжуд бўлганлиги
A35: 34 | B35: ООО "INTEST MAX" | C35: 307058508 | D35: Розия | F35: Охирги ўн икки ой ичида солиқ ҳисоботларини ўз вақтида тақдим этмаслик ҳолатлари мавжуд бўлганлиги
A36: 35 | B36: "MOVAROUNNAHR BIZNES" INTEGRO | C36: 307101819 | D36: Розия
A37: 36 | B37: ООО "BASKETBALL ACADEMY" | C37: 307205799 | D37: Розия | F37: Ходимлари ёки ёлланма ишчилари сони 4 кишидан кам бўлганлиги
A38: 37 | B38: ООО "ZAMBAR-PLATINUM" | C38: 307209437 | D38: Ёркиной | F38: Ходимлари ёки ёлланма ишчилари сони 4 кишидан кам бўлганлиги
A39: 38 | B39: ООО "HIGH-TECH GROUP" | C39: 307446998 | D39: Ёркиной | F39: Ходимлари ёки ёлланма ишчилари сони 4 кишидан кам бўлганлиги
A40: 39 | B40: "AVIA GORODOK" | C40: 307688389 | D40: Ёркиной
A41: 40 | B41: "BLESSING INVEST OIL" MCHJ | C41: 307821555 | D41: Ёркиной | F41: Уч ойдан ортиқ вақт давомида молия-хўжалик фаолияти амалга оширилмаганлиги
A42: 41 | B42: "AKJ TUZEL BO`LIMI" | C42: 307829726 | D42: Розия | F42: Охирги ўн икки ой ичида солиқ ҳисоботларини ўз вақтида тақдим этмаслик ҳолатлари мавжуд бўлганлиги
A43: 42 | B43: "KESH LOGIST" | C43: 307947611 | D43: Ёркиной | F43: Ходимлари ёки ёлланма ишчилари сони 4 кишидан кам бўлганлиги
A44: 43 | B44: "AVTO SCHOOL ELEGANT" KADISHEVA | C44: 308041046 | D44: Розия
A45: 44 | B45: "МОЯ УДАЧА" | C45: 308113192 | D45: Розия | F45: Ходимлари ёки ёлланма ишчилари сони 4 кишидан кам бўлганлиги
A46: 45 | B46: "FINANCE SCHOOL" | C46: 308234589 | D46: Розия | F46: Охирги ўн икки ой ичида солиқ ҳисоботларини ўз вақтида тақдим этмаслик ҳолатлари мавжуд бўлганлиги
A47: 46 | B47: "MK OFFICE" OOO | C47: 308334321 | D47: Ёркиной | F47: Ходимлари ёки ёлланма ишчилари сони 4 кишидан кам бўлганлиги
A48: 47 | B48: "AVTO SCHOOL PARKENT" | C48: 308360630 | D48: Розия
A49: 48 | B49: "TOSHKENT SCHOOL" ANGREN | C49: 308383848 | D49: Розия | F49: Охирги ўн икки ой ичида солиқ ҳисоботларини ўз вақтида тақдим этмаслик ҳолатлари мавжуд бўлганлиги
A50: 49 | B50: "AVTO AKBAR DAIMLER" | C50: 308485585 | D50: Розия | F50: Ходимлари ёки ёлланма ишчилари сони 4 кишидан кам бўлганлиги
A51: 50 | B51: ООО "SHIRIN SUPER TAOM" | C51: 308543061 | D51: Ёркиной
A52: 51 | B52: NTM "AVTO 777" QO`YLIQ | C52: 308551052 | D52: Розия | F52: Охирги ўн икки ой ичида солиқ ҳисоботларини ўз вақтида тақдим этмаслик ҳолатлари мавжуд бўлганлиги
A53: 52 | B53: PRO TEACHER`S 14.07.2021 | C53: 308678384 | D53: Розия | F53: Ходимлари ёки ёлланма ишчилари сони 4 кишидан кам бўлганлиги
A54: 53 | B54: NOBEL EDU NTM 02.08.2021 | C54: 308746347 | D54: Розия
A55: 54 | B55: МEZON GRP OOO | C55: 308760584 | D55: Ёркиной
A56: 55 | B56: "SAPRAMTECH" OOO 29.08.2021 | C56: 308820248 | D56: Ёркиной
A57: 56 | B57: 7-NINE МЧЖ 28.09.2021 | C57: 308836242 | D57: Розия | F57: Раҳбарнинг ёки молиявий бошқарув вазифаларини амалга ошираётган шахснинг шахси “ЯММТ” ИДАК тизимида тасдиқланмаганлиги | G57: Ўз кўчмас мулкига эга бўлмай туриб ижарага олинган ёки текин фойдаланилаётган кўчмас мулки бўлмаганлиги
A58: 57 | B58: MED PHARM ZAMIRAXON МЧЖ 28.09.2021 | C58: 308898593 | D58: Ёркиной | F58: Раҳбарнинг ёки молиявий бошқарув вазифаларини амалга ошираётган шахснинг шахси “ЯММТ” ИДАК тизимида тасдиқланмаганлиги | G58: Ўз кўчмас мулкига эга бўлмай туриб ижарага олинган ёки текин фойдаланилаётган кўчмас мулки бўлмаганлиги
A59: 58 | B59: "AVTOMATLASHTIRILGAN ELEKTRIK YURITMA" | C59: 201250775 | D59: Розия
A60: 59 | B60: AVTOMOTOHAVASK.KONGILLI JAMIYA | C60: 207134036 | D60: Розия
A61: 60 | B61: OOO "MAGISTRAL TRANS QURILISH" | C61: 207189989 | D61: Ёркиной
A62: 61 | B62: "JS MUROTOV" АДВОКАТЛИК БЮРОСИ" | C62: 207314302 | D62: Ёркиной
A63: 62 | B63: VMM RELIABLE LEGAL PROTECTION | C63: 207324203 | D63: Ёркиной
A64: 63 | B64: "RUSLAN GRAND " | C64: 303451710 | D64: Ёркиной
A65: 64 | B65: "IDEAL SYSTEM MONTAJ" | C65: 306223936 | D65: Ёркиной
A66: 65 | B66: "ЧП "ROAD RIDERS" | C66: 306807944 | D66: Розия
A67: 66 | B67: ЧП "SEVEN`S UP" | C67: 306918663 | D67: Ёркиной
A68: 67 | B68: "KIDS LUNCH LADY" MChJ 01.09.2021 | C68: 307039973 | D68: Ёркиной
A69: 68 | B69: ООО "AVTO LUXUSARY TRADE" | C69: 307043621 | D69: Ёркиной
A70: 69 | B70: ООО "TEN BRANCHES" | C70: 307053253 | D70: Розия
... A97: 96 | B97: ЗИЯТОВА МУХАББАТ КАРИМБАЕВНА | C97: 601611170 | D97: Розия

Sheet bugalter oylik
A3: Названия строк | B3: Сумма по полю % бухгалтер
A4: Abrorbek | B4: 7040000
A5: Axmadjon | B5: 0
A6: Go'zaloy | B6: 8134000
A7: Maxmuda | B7: 7320000
A8: Mirabbos | B8: 5080000
A9: Muslimbek | B9: 9740000
A10: Sherzod | B10: 100000
A11: (пусто) | B11: 0
A12: Zamira | B12: 8280000
A13: Musobek | B13: 13210000
A14: Humora | B14: 7840000
A15: Ilhom | B15: 3000000
... A31: Общий итог | B31: 113674000

Sheet bank klient oylik
A3: Названия строк | B3: Сумма по полю % банк клиент
A4: Azizbek | B4: 8917500
A5: (пусто) | B5: 0
A6: Bekzod | B6: 2750000
A7: Ruslan | B7: 6257500
A8: Abdulaziz | B8: 2030000
A9: Общий итог | B9: 19955000

Sheet nazoratchi
A3: Названия строк | B3: Сумма по полю Назоратчи %
A4: Go'zaloy | B4: 19322500
A5: (пусто) | B5: 0
A6: Muslimbek | B6: 8068500
A7: Musobek | B7: 2400000
A8: Zamira | B8: 0
A9: Общий итог | B9: 29791000

Sheet Royxat
A2: № | B2: НАИМЕНОВАНИЯ | C2: ИНН | D2: НДС | E2: Бухгалтер | F2: bank klient | G2: Столбец7 | H2: Назоратчи | I2: Столбец10 | J2: % банк клиент | K2: % бухгалтер | L2: Ёркиной | M2: Назоратчи %
A3: 1 | B3: MONTAJ TEPLO ENERGO MCHJ | C3: 306033555 | D3: НДС | E3: Sevara | F3: Azizbek | G3: 500000 | H3: Zamira | I3: 20 | J3: =G3*5% -> 25000 | K3: =G3*I3% -> 100000 | L3: =G3*7% -> 35000 | M3: =G3*5% -> 25000
A4: 2 | B4: "FINANCE COUNCIL" MCHJ | C4: 302672452 | E4: Ruslan | F4: Ruslan | G4: 700000 | H4: Go'zaloy | I4: 20 | J4: =G4*5% -> 35000 | K4: =G4*I4% -> 140000 | L4: =G4*7% -> 49000 | M4: =G4*5% -> 35000
A5: 3 | B5: "ЧП "ROAD RIDERS" | C5: 306807944 | E5: Abrorbek | F5: Ruslan | G5: 700000 | H5: Go'zaloy | I5: 20 | J5: =G5*5% -> 35000 | K5: =G5*I5% -> 140000 | L5: =G5*7% -> 49000 | M5: =G5*5% -> 35000
A6: 4 | B6: ЧП "SEVEN`S UP" | C6: 306918663 | E6: Ruslan | F6: Ruslan | G6: 700000 | H6: Go'zaloy | I6: 20 | J6: =G6*5% -> 35000 | K6: =G6*I6% -> 140000 | L6: =G6*7% -> 49000 | M6: =G6*5% -> 35000
A7: 5 | B7: ООО "TEN BRANCHES" | C7: 307053253 | E7: Go'zaloy | G7: 0 | H7: Muslimbek | I7: 20 | J7: 0 | K7: =G7*I7% -> 0 | L7: =G7*7% -> 0 | M7: =G7*5% -> 0
A8: 6 | B8: СП "ZIL-BAX" | C8: 307972154 | E8: Mohirbek | F8: Ruslan | G8: 700000 | H8: Musobek | I8: 20 | J8: =G8*5% -> 35000 | K8: =G8*I8% -> 140000 | L8: =G8*7% -> 49000 | M8: =G8*5% -> 35000
A9: 7 | B9: OOO "SARDORBEK HOUSE" | C9: 308435425 | E9: Ruslan | F9: Ruslan | G9: 700000 | H9: Go'zaloy | I9: 20 | J9: =G9*5% -> 35000 | K9: =G9*I9% -> 140000 | L9: =G9*7% -> 49000 | M9: =G9*5% -> 35000
A10: 8 | B10: "DILFUZAXON AVTO" | C10: 304825630 | D10: НДС | E10: Abrorbek | F10: Ruslan | G10: 2000000 | H10: Go'zaloy | I10: 20 | J10: =G10*5% -> 100000 | K10: =G10*I10% -> 400000 | L10: =G10*7% -> 140000 | M10: =G10*5% -> 100000
A11: 9 | B11: "SOF MEDTEX" MCHJ | C11: 309899654 | E11: Maxmuda | F11: Azizbek | G11: 6000000 | H11: Go'zaloy | I11: 20 | J11: =G11*5% -> 300000 | K11: =G11*I11% -> 1200000 | L11: =G11*7% -> 420000 | M11: =G11*5% -> 300000
A12: 10 | B12: OOO "RONICS" | C12: 308023653 | D12: НДС | E12: Muslimbek | F12: Azizbek | G12: 2500000 | H12: Go'zaloy | I12: 20 | J12: =G12*5% -> 125000 | K12: =G12*I12% -> 500000 | L12: =G12*7% -> 175000 | M12: =G12*5% -> 125000
A13: 11 | B13: "SAPRAMTECH" OOO | C13: 308820248 | D13: НДС | E13: Muslimbek | F13: Azizbek | G13: 7000000 | H13: Go'zaloy | I13: 20 | J13: =G13*5% -> 350000 | K13: =G13*I13% -> 1400000 | L13: =G13*7% -> 490000 | M13: =G13*5% -> 350000
A14: 12 | B14: GELECTRONIC | C14: 310055812 | D14: НДС | E14: Mirabbos | F14: Ruslan | G14: 4000000 | H14: Muslimbek | I14: 20 | J14: =G14*5% -> 200000 | K14: =G14*I14% -> 800000 | L14: =G14*7% -> 280000 | M14: =G14*5% -> 200000
A15: 13 | B15: SHIRIN XK | C15: 202536307 | D15: НДС | E15: Go'zaloy | G15: 2000000 | H15: Muslimbek | I15: 25 | J15: 0 | K15: =G15*I15% -> 500000 | L15: =G15*7% -> 140000 | M15: =G15*5% -> 100000
A16: 14 | B16: MELIOMASH | C16: 304940229 | D16: НДС | E16: Go'zaloy | G16: 0 | H16: Muslimbek | I16: 20 | J16: 0 | K16: =G16*I16% -> 0 | L16: =G16*7% -> 0 | M16: =G16*5% -> 0
A17: 15 | B17: "C A WOLVES" | C17: 305713761 | D17: НДС | E17: Abdugani | F17: Azizbek | G17: 3000000 | H17: Muslimbek | I17: 20 | J17: =G17*5% -> 150000 | K17: =G17*I17% -> 600000 | L17: =G17*7% -> 210000 | M17: =G17*5% -> 150000
A18: 16 | B18: "AL-AZIZ ACADEMY" НОУ | C18: 306784151 | D18: НДС | E18: Musobek | F18: Azizbek | G18: 3500000 | H18: Go'zaloy | I18: 20 | J18: =G18*5% -> 175000 | K18: =G18*I18% -> 700000 | L18: =G18*7% -> 245000 | M18: =G18*5% -> 175000
A19: 17 | B19: ООО "INTEST MAX" | C19: 307058508 | D19: НДС | E19: Go'zaloy | F19: Azizbek | G19: 25000000 | H19: Muslimbek | I19: 20 | J19: =G19*5% -> 1250000 | K19: =G19*I19% -> 5000000 | L19: =G19*7% -> 1750000 | M19: =G19*5% -> 1250000
A20: 18 | B20: "AVIA GORODOK" | C20: 307688389 | D20: НДС | E20: Mohirbek | F20: Ruslan | G20: 1000000 | H20: Musobek | I20: 20 | J20: =G20*5% -> 50000 | K20: =G20*I20% -> 200000 | L20: =G20*7% -> 70000 | M20: =G20*5% -> 50000
A21: 19 | B21: "AVTOMATLASHTIRILGAN ELEKTRIK YURITMA" | C21: 201250775 | E21: Sevara | G21: 500000 | H21: Zamira | I21: 20 | J21: 0 | K21: =G21*I21% -> 100000 | L21: =G21*7% -> 35000 | M21: =G21*5% -> 25000
A22: 20 | B22: BM UNIT | E22: Humora | F22: Azizbek | G22: 1000000 | H22: Go'zaloy | I22: 20 | J22: =G22*5% -> 50000 | K22: =G22*I22% -> 200000 | L22: =G22*7% -> 70000 | M22: =G22*5% -> 50000
A23: 21 | B23: ООО "AVTO LUXUSARY TRADE" | C23: 307043621 | E23: Alisher | F23: Ruslan | G23: 1000000 | H23: Muslimbek | I23: 20 | J23: =G23*5% -> 50000 | K23: =G23*I23% -> 200000 | L23: =G23*7% -> 70000 | M23: =G23*5% -> 50000
A24: 22 | B24: KOLBERG PRODUCTION | G24: 50000000 | K24: =G24*I24% -> 0 | L24: =G24*5% -> 2500000 | M24: 0
A25: 23 | B25: "AKJ SEBZOR BO`LIMI" | C25: 305150198 | D25: НДС | E25: Sevara | F25: Ruslan | G25: 500000 | H25: Zamira | I25: 20 | J25: =G25*5% -> 25000 | K25: =G25*I25% -> 100000 | L25: =G25*7% -> 35000 | M25: =G25*5% -> 25000
A26: 24 | B26: "AKJ TUZEL BO`LIMI" | C26: 307829726 | D26: НДС | E26: Sevara | F26: Ruslan | G26: 500000 | H26: Zamira | I26: 20 | J26: =G26*5% -> 25000 | K26: =G26*I26% -> 100000 | L26: =G26*7% -> 35000 | M26: =G26*5% -> 25000
A27: 25 | B27: "WALL STREET ACADEMY" | C27: 306116238 | D27: НДС | E27: Maxmuda | F27: Ruslan | G27: 2300000 | H27: Go'zaloy | I27: 20 | J27: =G27*5% -> 115000 | K27: =G27*I27% -> 460000 | L27: =G27*7% -> 161000 | M27: =G27*5% -> 115000
A28: 27 | B28: LIDER ELITE | E28: Zamira | F28: Azizbek | G28: 2500000 | H28: Go'zaloy | I28: 20 | J28: =G28*5% -> 125000 | K28: =G28*I28% -> 500000 | L28: =G28*7% -> 175000 | M28: =G28*5% -> 125000
A29: 28 | B29: NATURE ECO WOOD MCHJ | C29: 309706846 | D29: НДС | E29: Mirabbos | H29: Muslimbek | I29: 20 | J29: 0 | K29: =G29*I29% -> 0 | L29: =G29*7% -> 0 | M29: =G29*5% -> 0
A30: 29 | B30: Wood city 1999 | E30: Mirabbos | H30: Muslimbek | I30: 20 | J30: 0 | K30: =G30*I30% -> 0 | L30: =G30*7% -> 0 | M30: =G30*5% -> 0
A31: 30 | B31: "G-R-A-N-D ELECTRONICS" | C31: 308038910 | E31: Mirabbos | F31: Azizbek | G31: 1000000 | H31: Muslimbek | I31: 20 | J31: =G31*5% -> 50000 | K31: =G31*I31% -> 200000 | L31: =G31*7% -> 70000 | M31: =G31*5% -> 50000
A32: 31 | B32: KIFTI OFTOB SARBONI | E32: Mirabbos | F32: Ruslan | G32: 2000000 | H32: Muslimbek | I32: 20 | J32: =G32*5% -> 100000 | K32: =G32*I32% -> 400000 | L32: =G32*7% -> 140000 | M32: 0
A33: 32 | B33: ЧП "MATYUSUF SALAEV" | C33: 206155668 | D33: НДС | E33: Humora | F33: Azizbek | G33: 0 | H33: Go'zaloy | I33: 20 | J33: =G33*3% -> 0 | K33: =G33*I33% -> 0 | L33: =G33*7% -> 0 | M33: =G33*5% -> 0
A34: 33 | B34: OOO "MAGISTRAL TRANS QURILISH" | C34: 207189989 | D34: НДС | E34: Humora | F34: Ruslan | G34: 3500000 | H34: Go'zaloy | I34: 20 | J34: =G34*5% -> 175000 | K34: =G34*I34% -> 700000 | L34: =G34*7% -> 245000 | M34: =G34*5% -> 175000
A35: 34 | B35: "SHIRIN LYUKS TAOM" 01.09.2021 | C35: 302813323 | D35: НДС | E35: Musobek | G35: 0 | H35: Go'zaloy | I35: 20 | J35: =G35*3% -> 0 | K35: =G35*I35% -> 0 | L35: =G35*7% -> 0 | M35: =G35*5% -> 0
A36: 35 | B36: BY ETIKETKA | E36: Abrorbek | F36: Azizbek | G36: 1500000 | H36: Go'zaloy | I36: 20 | J36: =G36*5% -> 75000 | K36: =G36*I36% -> 300000 | L36: =G36*7% -> 105000 | M36: =G36*5% -> 75000
A37: 36 | B37: IN VITRO PLANTS | E37: Mirabbos | F37: Azizbek | G37: 2000000 | H37: Muslimbek | I37: 20 | J37: =G37*5% -> 100000 | K37: =G37*I37% -> 400000 | L37: =G37*7% -> 140000 | M37: =G37*5% -> 100000
A38: 37 | B38: ООО "BASKETBALL ACADEMY" | C38: 307205799 | D38: НДС | E38: Otabek | F38: Ruslan | G38: 700000 | H38: Muslimbek | I38: 20 | J38: =G38*5% -> 35000 | K38: =G38*I38% -> 140000 | L38: =G38*7% -> 49000 | M38: =G38*5% -> 35000
A39: 38 | B39: "KESH LOGIST" | C39: 307947611 | D39: НДС | E39: Aziz shogird | F39: Ruslan | G39: 500000 | H39: Musobek | I39: 20 | J39: =G39*5% -> 25000 | K39: =G39*I39% -> 100000 | L39: =G39*7% -> 35000 | M39: =G39*5% -> 25000
A40: 39 | B40: "GITA DASTURCHILAR AKADEMIYASI" MCHJ | C40: 309238352 | E40: Dilhush | F40: Azizbek | G40: 1000000 | H40: Go'zaloy | I40: 20 | J40: =G40*5% -> 50000 | K40: =G40*I40% -> 200000 | L40: =G40*7% -> 70000 | M40: =G40*5% -> 50000
A41: 40 | B41: "JS MUROTOV" АДВОКАТЛИК БЮРОСИ" | C41: 207314302 | E41: Maxmuda | F41: Azizbek | G41: 800000 | H41: Go'zaloy | I41: 20 | J41: =G41*5% -> 40000 | K41: =G41*I41% -> 160000 | L41: =G41*7% -> 56000 | M41: =G41*5% -> 40000
A42: 41 | B42: VMM RELIABLE LEGAL PROTECTION | C42: 207324203 | E42: Maxmuda | F42: Azizbek | G42: 500000 | H42: Go'zaloy | I42: 20 | J42: =G42*5% -> 25000 | K42: =G42*I42% -> 100000 | L42: =G42*7% -> 35000 | M42: =G42*5% -> 25000
A43: 42 | B43: "RUSLAN GRAND " | C43: 303451710 | E43: Otabek | F43: Ruslan | G43: 1500000 | H43: Muslimbek | I43: 20 | J43: =G43*5% -> 75000 | K43: =G43*I43% -> 300000 | L43: =G43*7% -> 105000 | M43: =G43*5% -> 75000
A44: 43 | B44: ЧП "CHIRCHIQ SAHOVAT" | C44: 307077420 | E44: Ruslan | F44: Ruslan | G44: 400000 | H44: Go'zaloy | I44: 20 | J44: =G44*5% -> 20000 | K44: =G44*I44% -> 80000 | L44: =G44*7% -> 28000 | M44: =G44*5% -> 20000
A45: 44 | B45: "JT INVESTMENT HUB" | C45: 307159792 | E45: Maxmuda | F45: Azizbek | G45: 2000000 | H45: Go'zaloy | I45: 20 | J45: =G45*5% -> 100000 | K45: =G45*I45% -> 400000 | L45: =G45*7% -> 140000 | M45: =G45*5% -> 100000
A46: 45 | B46: "AMIRBEK-RUXSHONA PHARM" XK | C46: 303328933 | D46: НДС | E46: Zamira | G46: 4000000 | H46: Go'zaloy | I46: 20 | J46: 0 | K46: =G46*I46% -> 800000 | L46: =G46*7% -> 280000 | M46: =G46*5% -> 200000
A47: 46 | B47: "XASANOV SABIRJAN LASHOVICH" AB | C47: 309188899 | E47: Dilhush | F47: Azizbek | G47: 700000 | H47: Go'zaloy | I47: 20 | J47: =G47*5% -> 35000 | K47: =G47*I47% -> 140000 | L47: =G47*7% -> 49000 | M47: =G47*5% -> 35000
A48: 47 | B48: HAPPY CLEAN MChJ | C48: 309610674 | E48: Dilhush | F48: Azizbek | G48: 1000000 | H48: Go'zaloy | I48: 20 | J48: =G48*5% -> 50000 | K48: =G48*I48% -> 200000 | L48: =G48*7% -> 70000 | M48: =G48*5% -> 50000
A49: 48 | B49: ООО "HIGH-TECH GROUP" | C49: 307446998 | D49: НДС | E49: Maxmuda | G49: 3000000 | H49: Go'zaloy | I49: 20 | J49: 0 | K49: =G49*I49% -> 600000 | L49: =G49*7% -> 210000 | M49: =G49*5% -> 150000
A50: 49 | B50: XK UNIMEAL BUSINESS ENTITY | C50: 308763019 | E50: Humora | F50: Azizbek | G50: 1000000 | H50: Go'zaloy | I50: 20 | J50: =G50*5% -> 50000 | K50: =G50*I50% -> 200000 | L50: =G50*7% -> 70000 | M50: =G50*5% -> 50000
A51: 50 | B51: "ЧП INTER PROF EDUCATION" | C51: 304107369 | D51: НДС | E51: Humora | F51: Ruslan | G51: 2000000 | H51: Go'zaloy | I51: 20 | J51: =G51*5% -> 100000 | K51: =G51*I51% -> 400000 | L51: =G51*7% -> 140000 | M51: =G51*5% -> 100000
A52: 51 | B52: LANGUAGE ACADEMY" | C52: 305610162 | D52: НДС | E52: Abdugani | F52: Azizbek | G52: 2500000 | H52: Go'zaloy | I52: 20 | J52: =G52*5% -> 125000 | K52: =G52*I52% -> 500000 | L52: =G52*7% -> 175000 | M52: =G52*5% -> 125000
A53: 52 | B53: BEK AND COMPANY | E53: Mirabbos | F53: Azizbek | G53: 1000000 | H53: Muslimbek | I53: 20 | J53: =G53*5% -> 50000 | K53: =G53*I53% -> 200000 | L53: =G53*7% -> 70000 | M53: =G53*5% -> 50000
A54: 53 | B54: 7-NINE МЧЖ | C54: 308836242 | D54: НДС | E54: Musobek | F54: Azizbek | G54: 1500000 | H54: Go'zaloy | I54: 20 | J54: =G54*5% -> 75000 | K54: =G54*I54% -> 300000 | L54: =G54*7% -> 105000 | M54: =G54*5% -> 75000
A55: 54 | B55: BELLSTORE | E55: Go'zaloy | F55: Azizbek | G55: 1000000 | H55: Muslimbek | I55: 20 | J55: =G55*5% -> 50000 | K55: =G55*I55% -> 200000 | L55: =G55*7% -> 70000 | M55: =G55*5% -> 50000
A56: 55 | B56: TRUST MEDICAL LAB | C56: 307409092 | E56: Mirabbos | F56: Ruslan | G56: 1500000 | H56: Muslimbek | I56: 20 | J56: =G56*5% -> 75000 | K56: =G56*I56% -> 300000 | L56: =G56*7% -> 105000 | M56: =G56*5% -> 75000
A57: 56 | B57: "STUDY GUIDE" | C57: 303408381 | D57: НДС | E57: Abdugani | F57: Azizbek | G57: 4000000 | H57: Muslimbek | I57: 20 | J57: =G57*5% -> 200000 | K57: =G57*I57% -> 800000 | L57: =G57*7% -> 280000 | M57: =G57*5% -> 200000
A58: 57 | B58: HILOL PHARM | C58: 305979201 | D58: НДС | E58: Abdugani | F58: Azizbek | G58: 2500000 | H58: Go'zaloy | I58: 20 | J58: =G58*5% -> 125000 | K58: =G58*I58% -> 500000 | L58: =G58*7% -> 175000 | M58: =G58*5% -> 125000
A59: 58 | B59: "HI-TECH ORIENT MED-BUSINESS MCHJ | C59: 306672520 | D59: НДС | E59: Muslimbek | G59: 4000000 | H59: Go'zaloy | I59: 20 | J59: 0 | K59: =G59*I59% -> 800000 | L59: =G59*7% -> 280000 | M59: =G59*5% -> 200000
A60: 59 | B60: "FINANCE SCHOOL" | C60: 308234589 | D60: НДС | E60: Humora | F60: Ruslan | G60: 700000 | H60: Go'zaloy | I60: 20 | J60: =G60*5% -> 35000 | K60: =G60*I60% -> 140000 | L60: =G60*7% -> 49000 | M60: =G60*5% -> 35000
A61: 60 | B61: "KIDS NUR CITY" ООО | C61: 306774385 | D61: НДС | E61: Musobek | F61: Azizbek | G61: 4350000 | H61: Go'zaloy | I61: 20 | J61: =G61*5% -> 217500 | K61: =G61*I61% -> 870000 | L61: =G61*7% -> 304500 | M61: =G61*5% -> 217500
A62: 61 | B62: TAKSIM-KEBAB GROUP MCHJ | C62: 309695560 | E62: Abdugani | F62: Ruslan | G62: 0 | H62: Go'zaloy | I62: 20 | J62: =G62*5% -> 0 | K62: =G62*I62% -> 0 | L62: =G62*7% -> 0 | M62: =G62*5% -> 0
A63: 62 | B63: NIGINA FARM | D63: НДС | E63: Zamira | G63: 5000000 | H63: Go'zaloy | I63: 20 | J63: 0 | K63: =G63*I63% -> 1000000 | L63: =G63*7% -> 350000 | M63: =G63*5% -> 250000
A64: 63 | B64: DOUBLE X PRO | E64: Hasan | F64: Azizbek | G64: 1000000 | H64: Muslimbek | I64: 20 | J64: =G64*5% -> 50000 | K64: =G64*I64% -> 200000 | L64: =G64*7% -> 70000 | M64: =G64*5% -> 50000
A65: 64 | B65: "MUZAFFARXO`JA-HILOL" Х.Ф. | C65: 206450634 | D65: НДС | E65: Musobek | F65: Ruslan | G65: 2500000 | H65: Go'zaloy | I65: 20 | J65: =G65*5% -> 125000 | K65: =G65*I65% -> 500000 | L65: =G65*7% -> 175000 | M65: =G65*5% -> 125000
A66: 65 | B66: VIRTUS-SOCIUM МЧЖ | C66: 308241991 | D66: НДС | E66: Abrorbek | F66: Azizbek | G66: 0 | H66: Go'zaloy | J66: =G66*5% -> 0 | K66: =G66*I66% -> 0 | M66: =G66*5% -> 0
A67: 66 | B67: "PHARM SMART" MCHJ | C67: 309680747 | D67: НДС | E67: Otabek | F67: Azizbek | G67: 4000000 | H67: Muslimbek | I67: 20 | J67: =G67*5% -> 200000 | K67: =G67*I67% -> 800000 | L67: =G67*7% -> 280000 | M67: =G67*5% -> 200000
A68: 67 | B68: PHARZAM FARM | E68: Javohir | F68: Ruslan | G68: 3000000 | H68: Muslimbek | I68: 20 | J68: =G68*5% -> 150000 | K68: =G68*I68% -> 600000 | L68: =G68*7% -> 210000 | M68: =G68*5% -> 150000
A69: 68 | B69: MIRGAS OIL MCHJ | C69: 309291123 | D69: НДС | E69: Mirabbos | F69: Azizbek | G69: 1500000 | H69: Muslimbek | I69: 20 | J69: =G69*5% -> 75000 | K69: =G69*I69% -> 300000 | L69: =G69*7% -> 105000 | M69: =G69*5% -> 75000
A70: 69 | B70: TRINITY TECHNOLOGY MCHJ | C70: 305218618 | D70: НДС | G70: 20000000 | I70: 25 | J70: 0 | L70: =G70*7% -> 1400000
A71: 70 | B71: SOBIROV I YATT | E71: Abdugani | G71: 200000 | H71: Go'zaloy | I71: 20 | K71: =G71*I71% -> 40000 | L71: =G71*7% -> 14000 | M71: =G71*5% -> 10000
A72: 71 | B72: RIZO MULK MCHJ | C72: 309918004 | E72: Abrorbek | G72: 1000000 | H72: Go'zaloy | I72: 20 | J72: 0 | K72: =G72*I72% -> 200000 | L72: =G72*7% -> 70000 | M72: =G72*5% -> 50000
A73: 72 | B73: ENGLIFY | E73: Axmadjon | F73: Ruslan | G73: 11000000 | H73: Muslimbek | I73: 20 | J73: =4000000*5% -> 200000 | K73: 0 | L73: =G73*7% -> 770000 | M73: =G73*5% -> 550000
A74: 73 | B74: J-R GROUP | E74: Mirabbos | F74: Azizbek | G74: 1000000 | H74: Muslimbek | I74: 20 | J74: =G74*5% -> 50000 | K74: =G74*I74% -> 200000 | L74: =G74*7% -> 70000 | M74: =G74*5% -> 50000
A75: 74 | B75: BADEX LIFE | E75: Muslimbek | F75: Ruslan | G75: 2500000 | H75: Go'zaloy | I75: 20 | J75: =G75*5% -> 125000 | K75: =G75*I75% -> 500000 | L75: =G75*7% -> 175000 | M75: =G75*5% -> 125000
A76: 75 | B76: RONICS ENGINEERING TEAM | C76: 310310683 | E76: Muslimbek | F76: Azizbek | G76: 700000 | H76: Go'zaloy | I76: 20 | J76: =G76*5% -> 35000 | K76: =G76*I76% -> 140000 | L76: =G76*7% -> 49000 | M76: =G76*5% -> 35000
A77: 76 | B77: Raximjonova Dilnoza YATT | E77: Go'zaloy | G77: 170000 | H77: Muslimbek | I77: 20 | K77: =G77*I77% -> 34000 | L77: =G77*7% -> 11900 | M77: =G77*5% -> 8500
A78: 77 | B78: HI UNIT | E78: Humora | F78: Azizbek | G78: 1000000 | H78: Go'zaloy | I78: 20 | J78: =G78*5% -> 50000 | K78: =G78*I78% -> 200000 | L78: =G78*7% -> 70000 | M78: =G78*5% -> 50000
A79: 78 | B79: BRAND NEW HOUSES | E79: Humora | G79: 10000000 | H79: Go'zaloy | I79: 20 | K79: =G79*I79% -> 2000000 | L79: =G79*7% -> 700000 | M79: =G79*5% -> 500000
A80: 80 | B80: IT-INTEGRATOR | E80: Muslimbek | F80: Azizbek | G80: 1500000 | H80: Go'zaloy | I80: 20 | J80: =G80*5% -> 75000 | K80: =G80*I80% -> 300000 | L80: =G80*7% -> 105000 | M80: =G80*5% -> 75000
A81: 81 | B81: UNI GLOBAL | E81: Humora | F81: Azizbek | G81: 0 | H81: Go'zaloy | I81: 20 | J81: =G81*5% -> 0 | K81: =G81*I81% -> 0 | L81: =G81*7% -> 0 | M81: =G81*5% -> 0
A82: 82 | B82: NOEL TRIP | E82: Otabek | F82: Azizbek | G82: 800000 | H82: Muslimbek | I82: 20 | J82: =G82*5% -> 40000 | K82: =G82*I82% -> 160000 | L82: =G82*7% -> 56000 | M82: =G82*5% -> 40000
A83: 83 | B83: KOLBERG MEDICAL | E83: Ilhom | F83: Bekzod | G83: 15000000 | H83: Go'zaloy | I83: 20 | J83: =G83*5% -> 750000 | K83: =Таблица3[[#This Row],[Столбец7]]*Таблица3[[#This Row],[Столбец10]]% -> 3000000 | L83: =G83*7% -> 1050000 | M83: =G83*10% -> 1500000
A84: 84 | B84: TULYAGANOV FX | E84: Mirabbos | F84: Azizbek | G84: 1000000 | H84: Muslimbek | I84: 20 | J84: =G84*5% -> 50000 | K84: =G84*I84% -> 200000 | L84: =G84*7% -> 70000 | M84: =G84*5% -> 50000
A85: 85 | B85: SOFI TEAM | E85: Ruslan | F85: Ruslan | G85: 700000 | H85: Go'zaloy | I85: 20 | J85: =G85*5% -> 35000 | K85: =G85*I85% -> 140000 | L85: =G85*7% -> 49000 | M85: =G85*5% -> 35000
A86: 86 | B86: RM MUROD BIZNES | E86: Abrorbek | F86: Ruslan | G86: 1000000 | H86: Go'zaloy | I86: 20 | J86: =G86*5% -> 50000 | K86: =G86*I86% -> 200000 | L86: =G86*7% -> 70000 | M86: =G86*5% -> 50000
A87: 87 | B87: BAROKAT TEAM | E87: Ruslan | F87: Ruslan | G87: 700000 | H87: Go'zaloy | I87: 20 | J87: =G87*5% -> 35000 | K87: =G87*I87% -> 140000 | L87: =G87*7% -> 49000 | M87: =G87*5% -> 35000
A88: 88 | B88: UZART GROUP PROJEKT | E88: Abrorbek | F88: Azizbek | G88: 3000000 | H88: Go'zaloy | I88: 20 | J88: =G88*5% -> 150000 | K88: 0 | L88: =G88*7%+300000 -> 510000 | M88: =G88*5% -> 150000
A89: 89 | B89: KORBAZAAR | E89: Abdugani | F89: Ruslan | G89: 3000000 | H89: Go'zaloy | I89: 20 | J89: =G89*5% -> 150000 | K89: =G89*I89% -> 600000 | L89: =G89*7% -> 210000 | M89: =G89*5% -> 150000
A90: 90 | B90: NURDEVAI | E90: Aziz shogird | F90: Ruslan | G90: 500000 | H90: Musobek | I90: 25 | J90: =G90*5% -> 25000 | K90: =G90*I90% -> 125000 | L90: =G90*7% -> 35000 | M90: =G90*5% -> 25000
A91: 91 | B91: MEDICAL GM | E91: Musobek | G91: 2500000 | H91: Go'zaloy | I91: 20 | J91: 0 | K91: =G91*I91% -> 500000 | L91: =G91*7% -> 175000 | M91: =G91*5% -> 125000
A92: 92 | B92: LUNA CATERING TEAM | E92: Humora | F92: Azizbek | G92: 0 | H92: Go'zaloy | I92: 20 | J92: =G92*5% -> 0 | K92: =G92*I92% -> 0 | L92: =G92*7% -> 0 | M92: =G92*5% -> 0
A93: 93 | B93: IE ASILBEKOVA ZULFIYA | E93: Dilhush | F93: Azizbek | G93: 700000 | H93: Go'zaloy | I93: 20 | J93: =G93*5% -> 35000 | K93: =G93*I93% -> 140000 | L93: =G93*7% -> 49000 | M93: =G93*5% -> 35000
A94: 94 | B94: QUDRATILLA ILA | E94: Otabek | F94: Ruslan | G94: 700000 | H94: Muslimbek | I94: 25 | J94: =G94*5% -> 35000 | K94: =G94*I94% -> 175000 | L94: =G94*7% -> 49000 | M94: =G94*5% -> 35000
A95: 95 | B95: MG BUSINESS BROKERS | E95: Aziz shogird | G95: 500000 | H95: Musobek | I95: 20 | J95: 0 | K95: =G95*I95% -> 100000 | L95: =G95*7% -> 35000 | M95: =G95*5% -> 25000
A96: 96 | B96: FIDELITY SERVISE | E96: Humora | F96: Azizbek | G96: 1000000 | H96: Go'zaloy | I96: 20 | J96: =G96*5% -> 50000 | K96: =G96*I96% -> 200000 | L96: =G96*7% -> 70000 | M96: =G96*5% -> 50000
A97: 97 | B97: EASTREX | E97: Dilhush | F97: Azizbek | G97: 700000 | H97: Go'zaloy | I97: 20 | J97: =G97*5% -> 35000 | K97: =G97*I97% -> 140000 | L97: =G97*7% -> 49000 | M97: =G97*5% -> 35000
A98: 98 | B98: XURSHID AVTO | E98: Otabek | F98: Ruslan | G98: 750000 | H98: Muslimbek | I98: 20 | J98: =G98*5% -> 37500 | K98: =G98*I98% -> 150000 | L98: =G98*7% -> 52500 | M98: =G98*5% -> 37500
A99: 99 | B99: VIKTORIYA TIBBIY KORIK | E99: Musobek | F99: Azizbek | G99: 700000 | H99: Go'zaloy | I99: 20 | J99: =G99*5% -> 35000 | K99: =G99*I99% -> 140000 | L99: =G99*7% -> 49000 | M99: =G99*5% -> 35000
A100: 100
A101: 101 | B101: NOMDOR PALOV | E101: Maxmuda | F101: Ruslan | G101: 10000000 | H101: Go'zaloy | I101: 20 | J101: =G101*5% -> 500000 | K101: =G101*I101% -> 2000000 | L101: =G101*7% -> 700000 | M101: =G101*5% -> 500000
...

Sheet 09,2018
A1: № | B1: НАИМЕНОВАНИЯ | C1: ИНПС | D1: ЕСП | E1: ПОД НАЛ | F1: ЕНП | G1: ОПЛАТА | H1: БАЛАНС | I1: ФИН РЕЗ | J1: ПЕНСИЯ
A2: 1 | B2: "MUZAFFARXO`JA-HILOL" Х.Ф. ИНН: 206450634 | K2: 84564973 | L2: 1575434
A3: 2 | B3: "ЧП ENGLISH SERVICE" ИНН: 303256439 | K3: 72641824
A4: 3 | B4: "STUDY GUIDE" ИНН: 303408381 | K4: 45313285
A5: 4 | B5: "ЧП INTER PROF EDUCATION" ИНН: 304107369 | K5: 100186
A6: 5 | B6: "AVTOMOTOHAVASKORLAR YANGIOBOD" ИНН: 304632864 | K6: 86722119
A7: 6 | B7: AVTOMOTOHAVASKOR TALABALAR , ИНН: 304651169 | K7: 36275148
A8: 7 | B8: "DILFUZAXON AVTO" ИНН: 304825630 | K8: 35324962
A9: 8 | B9: "GLOBALMED" , ИНН: 304979653 | K9: 100186
A10: 9 | B10: "УП CHORBOG` AVTOUSTOZ" ИНН: 305133922 | K10: 50995539
A11: 10 | B11: "FLY HIGH TICKET" ИНН: 305650493 | C11: вопросной | K11: 100186
A12: 11 | B12: "RUSLAN GRAND "ИНН: 303451710 | K12: 23956654
A13: 12 | B13: "GULBAHOR BUSINESS" ИНН: 304737756 | C13: картотека | K13: 100186
A14: 13 | B14: "MUXLISA NUR FARM" ИНН: 303004885 | K14: 100186
A15: 14 | B15: "AKJ SEBZOR BO`LIMI" , ИНН: 305150198 | K15: 100186
A16: 15 | B16: "C A WOLVES" , ИНН: 305713761 | C16: нет ещё | K16: 100186
A17: 16 | B17: "ASADTILLO BIZNES" ИНН : 304453422 | K17: 33979629
A18: 17 | B18: "INSHOOT MAXSUSMONTAJ QURILISH" ИНН : 301716199 | C18: картотека | K18: 33979629
A19: 18 | B19: "ООО "MUBINA RAYONA BUSINESS" ИНН: 305023742 | C19: картотека | K19: 34406143
A20: 19 | B20: ABSOLUTE STRENGTH NTM , ИНН: 303434754 | C20: картотека | K20: 100186
A21: 20 | B21: "SHINEART MCHJ" ИНН: 300821821 | C21: картотека | K21: 100186
A22: 21 | B22: "MCHJ "METCOM" VAKOLATXONASI: 505612344 | K22: 14467934
K23: 79026958

Sheet 10,2018 
A1: № | B1: НАИМЕНОВАНИЯ | C1: ИНПС | D1: ЕСП | E1: ПОД НАЛ | F1: ЕНП | G1: ОПЛАТА | H1: БАЛАНС | I1: ФИН РЕЗ | J1: ПЕНСИЯ
A2: 1 | B2: AVTOMOTOHAVASKOR TALABALAR , ИНН: 304651169 | K2: 36275148
A3: 2 | B3: "ASADTILLO BIZNES" ИНН : 304453422 | K3: 13540974
A4: 3 | B4: "INSHOOT MAXSUSMONTAJ QURILISH" ИНН : 301716199 | C4: картотека | K4: 33979629
A5: 4 | B5: "ЧП ENGLISH SERVICE" ИНН: 303256439 | K5: 72641824
A6: 5 | B6: "MUZAFFARXO`JA-HILOL" Х.Ф. ИНН: 206450634 | K6: 84564973
A7: 6 | B7: "STUDY GUIDE" ИНН: 303408381 | K7: 45313285
A8: 7 | B8: "ЧП INTER PROF EDUCATION" ИНН: 304107369 | K8: 88700206
A9: 8 | B9: "AVTOMOTOHAVASKORLAR YANGIOBOD" ИНН: 304632864 | K9: 86722119
A10: 9 | B10: "DILFUZAXON AVTO" ИНН: 304825630 | K10: 35324962
A11: 10 | B11: "GLOBALMED" , ИНН: 304979653 | K11: 100186
A12: 11 | B12: "УП CHORBOG` AVTOUSTOZ" ИНН: 305133922 | K12: 50995539
A13: 12 | B13: "C A WOLVES" , ИНН: 305713761 | C13: нет ещё | K13: 100186
A14: 13 | B14: "MUXLISA NUR FARM" ИНН: 303004885 | K14: 100186
A15: 14 | B15: "AKJ SEBZOR BO`LIMI" , ИНН: 305150198 | K15: 100186
A16: 15 | B16: ООО "MUBINA RAYONA BUSINESS" ИНН: 305023742 | C16: картотека | K16: 34406143
A17: 16 | B17: "RUSLAN GRAND "ИНН: 303451710 | K17: 23956654
A18: 17 | B18: "GULBAHOR BUSINESS" ИНН: 304737756 | C18: картотека | K18: 100186
A19: 18 | B19: ABSOLUTE STRENGTH NTM , ИНН: 303434754 | C19: картотека | K19: 100186
A20: 19 | B20: "FLY HIGH TICKET" ИНН: 305650493 | C20: картотека | K20: 100186
A21: 20 | B21: 300821821 | C21: картотека | K21: 100186
A22: 21 | B22: ЯТТ 537852647 Акрамов | C22: керакмас | K22: 100186
A23: 22 | B23: "MCHJ "METCOM" VAKOLATXONASI" ИНН: 207285442, | K23: 100186

Sheet KPI
A2: № | B2: НАИМЕНОВАНИЯ | C2: Бухгалтер | D2: bank klient | E2: Столбец7 | F2: Назоратчи | G2: Ishga vaqtida kelish ketish | H2: Ishga kelish bank klient | I2: Ishga kelish nazoratchi2 | J2: Gruppa buxgalter | K2: Gruppa bank klient | L2: Didox | M2: xatlar | N2: мехнат | O2: 1c | P2: Avtokameral | Q2: Pul oqimlari | R2: Chiqadigan soliqlar | S2: Hisoblangan oylik | T2: Debitor kreditor | U2: Foyda va zarar | V2: Nazoratchi | W2: Ishga vaqtida kelish nazoratchi | X2: Ishga vaqtida kelish ketish2 | Y2: Ishga kelish bank klient3 | Z2: Gruppa buxgalter4 | AA2: Gruppa bank klient 2 | AB2: 1C baza3 | AC2: xatlar4 | AD2: Belgilangan otchetlar5 | AE2: Nazoratchi2 | AF2: NazoratchiKPI | AG2: Buxgalter KPI | AH2: Bank klient KPI
A3: 1 | B3: MONTAJ TEPLO ENERGO MCHJ | C3: Otabek | D3: Azizbek | E3: 500000 | F3: Muslimbek | H3: 1 | J3: 1 | K3: 1 | L3: 0.25 | M3: 0.25 | O3: 1 | P3: 0.25 | Q3: 0.2 | R3: 0.2 | S3: 0.2 | T3: 0.2 | U3: 0.2 | V3: 0.5 | W3: =Таблица32[[#This Row],[Столбец7]]*Таблица32[[#This Row],[Ishga kelish nazoratchi2]]% -> 0 | X3: =Таблица32[[#This Row],[Столбец7]]*Таблица32[[#This Row],[Ishga vaqtida kelish ketish]]% -> 0 | Y3: =Таблица32[[#This Row],[Столбец7]]*Таблица32[[#This Row],[Ishga kelish bank klient]]% -> 5000 | Z3: =Таблица32[[#This Row],[Столбец7]]*Таблица32[[#This Row],[Gruppa buxgalter]]% -> 5000 | AA3: =Таблица32[[#This Row],[Столбец7]]*Таблица32[[#This Row],[Gruppa bank klient ]]% -> 5000 | AB3: =Таблица32[[#This Row],[1c]]*Таблица32[[#This Row],[Столбец7]]/100 -> 5000 | AC3: =SUM(Таблица32[[#This Row],[Didox]:[ мехнат]],Таблица32[[#This Row],[Avtokameral]])*Таблица32[[#This Row],[Столбец7]]/100 -> 3750 | AD3: =SUM(Таблица32[[#This Row],[Pul oqimlari]:[Foyda va zarar]])*Таблица32[[#This Row],[Столбец7]]/100 -> 5000 | AE3: =Таблица32[[#This Row],[Столбец7]]*Таблица32[[#This Row],[Nazoratchi]]% -> 2500 | AF3: =Таблица32[[#This Row],[Ishga vaqtida kelish nazoratchi]]+Таблица32[[#This Row],[Nazoratchi2]] -> 2500 | AG3: =Таблица32[[#This Row],[Ishga vaqtida kelish ketish2]]+Таблица32[[#This Row],[Gruppa buxgalter4]]+Таблица32[[#This Row],[1C baza3]]+Таблица32[[#This Row],[xatlar4]]+Таблица32[[#This Row],[Belgilangan otchetlar5]] -> 18750 | AH3: =Таблица32[[#This Row],[Ishga kelish bank klient3]]+Таблица32[[#This Row],[Gruppa bank klient 2]] -> 10000
A4: 2 | B4: "FINANCE COUNCIL" MCHJ | C4: Ruslan | D4: Ruslan | E4: 700000 | F4: Go'zaloy | H4: 1 | K4: 1 | L4: -0.25 | M4: 0.25 | N4: 0.25 | P4: 0.25 | Q4: 0 | R4: 0 | S4: 0 | T4: 0 | U4: 0 | W4: =Таблица32[[#This Row],[Столбец7]]*Таблица32[[#This Row],[Ishga kelish nazoratchi2]]% -> 0 | X4: =Таблица32[[#This Row],[Столбец7]]*Таблица32[[#This Row],[Ishga vaqtida kelish ketish]]% -> 0 | Y4: =Таблица32[[#This Row],[Столбец7]]*Таблица32[[#This Row],[Ishga kelish bank klient]]% -> 7000 | Z4: =Таблица32[[#This Row],[Столбец7]]*Таблица32[[#This Row],[Gruppa buxgalter]]% -> 0 | AA4: =Таблица32[[#This Row],[Столбец7]]*Таблица32[[#This Row],[Gruppa bank klient ]]% -> 7000 | AB4: =Таблица32[[#This Row],[1c]]*Таблица32[[#This Row],[Столбец7]]/100 -> 0 | AC4: =SUM(Таблица32[[#This Row],[Didox]:[ мехнат]],Таблица32[[#This Row],[Avtokameral]])*Таблица32[[#This Row],[Столбец7]]/100 -> 3500 | AD4: =SUM(Таблица32[[#This Row],[Pul oqimlari]:[Foyda va zarar]])*Таблица32[[#This Row],[Столбец7]]/100 -> 0 | AE4: =Таблица32[[#This Row],[Столбец7]]*Таблица32[[#This Row],[Nazoratchi]]% -> 0 | AF4: =Таблица32[[#This Row],[Ishga vaqtida kelish nazoratchi]]+Таблица32[[#This Row],[Nazoratchi2]] -> 0 | AG4: =Таблица32[[#This Row],[Ishga vaqtida kelish ketish2]]+Таблица32[[#This Row],[Gruppa buxgalter4]]+Таблица32[[#This Row],[1C baza3]]+Таблица32[[#This Row],[xatlar4]]+Таблица32[[#This Row],[Belgilangan otchetlar5]] -> 3500 | AH4: =Таблица32[[#This Row],[Ishga kelish bank klient3]]+Таблица32[[#This Row],[Gruppa bank klient 2]] -> 14000
A5: 3 | B5: "ЧП "ROAD RIDERS" | C5: Abrorbek | D5: Ruslan | E5: 700000 | F5: Go'zaloy | H5: 1 | J5: 1 | K5: -0.5 | L5: 0.25 | M5: 0.25 | P5: 0.25 | Q5: 0 | R5: 0.2 | S5: 0.2 | T5: 0.2 | U5: 0 | V5: 0.5 | W5: =Таблица32[[#This Row],[Столбец7]]*Таблица32[[#This Row],[Ishga kelish nazoratchi2]]% -> 0 | X5: =Таблица32[[#This Row],[Столбец7]]*Таблица32[[#This Row],[Ishga vaqtida kelish ketish]]% -> 0 | Y5: =Таблица32[[#This Row],[Столбец7]]*Таблица32[[#This Row],[Ishga kelish bank klient]]% -> 7000 | Z5: =Таблица32[[#This Row],[Столбец7]]*Таблица32[[#This Row],[Gruppa buxgalter]]% -> 7000 | AA5: =Таблица32[[#This Row],[Столбец7]]*Таблица32[[#This Row],[Gruppa bank klient ]]% -> -3500 | AB5: =Таблица32[[#This Row],[1c]]*Таблица32[[#This Row],[Столбец7]]/100 -> 0 | AC5: =SUM(Таблица32[[#This Row],[Didox]:[ мехнат]],Таблица32[[#This Row],[Avtokameral]])*Таблица32[[#This Row],[Столбец7]]/100 -> 5250 | AD5: =SUM(Таблица32[[#This Row],[Pul oqimlari]:[Foyda va zarar]])*Таблица32[[#This Row],[Столбец7]]/100 -> 4200 | AE5: =Таблица32[[#This Row],[Столбец7]]*Таблица32[[#This Row],[Nazoratchi]]% -> 3500 | AF5: =Таблица32[[#This Row],[Ishga vaqtida kelish nazoratchi]]+Таблица32[[#This Row],[Nazoratchi2]] -> 3500 | AG5: =Таблица32[[#This Row],[Ishga vaqtida kelish ketish2]]+Таблица32[[#This Row],[Gruppa buxgalter4]]+Таблица32[[#This Row],[1C baza3]]+Таблица32[[#This Row],[xatlar4]]+Таблица32[[#This Row],[Belgilangan otchetlar5]] -> 16450 | AH5: =Таблица32[[#This Row],[Ishga kelish bank klient3]]+Таблица32[[#This Row],[Gruppa bank klient 2]] -> 3500
A6: 4 | B6: ЧП "SEVEN`S UP" | C6: Ruslan | D6: Ruslan | E6: 700000 | F6: Go'zaloy | H6: 1 | K6: 1 | L6: 0.25 | M6: 0.25 | N6: 0.25 | P6: 0.25 | Q6: 0 | R6: 0 | S6: 0 | T6: 0 | U6: 0 | W6: =Таблица32[[#This Row],[Столбец7]]*Таблица32[[#This Row],[Ishga kelish nazoratchi2]]% -> 0 | X6: =Таблица32[[#This Row],[Столбец7]]*Таблица32[[#This Row],[Ishga vaqtida kelish ketish]]% -> 0 | Y6: =Таблица32[[#This Row],[Столбец7]]*Таблица32[[#This Row],[Ishga kelish bank klient]]% -> 7000 | Z6: =Таблица32[[#This Row],[Столбец7]]*Таблица32[[#This Row],[Gruppa buxgalter]]% -> 0 | AA6: =Таблица32[[#This Row],[Столбец7]]*Таблица32[[#This Row],[Gruppa bank klient ]]% -> 7000 | AB6: =Таблица32[[#This Row],[1c]]*Таблица32[[#This Row],[Столбец7]]/100 -> 0 | AC6: =SUM(Таблица32[[#This Row],[Didox]:[ мехнат]],Таблица32[[#This Row],[Avtokameral]])*Таблица32[[#This Row],[Столбец7]]/100 -> 7000 | AD6: =SUM(Таблица32[[#This Row],[Pul oqimlari]:[Foyda va zarar]])*Таблица32[[#This Row],[Столбец7]]/100 -> 0 | AE6: =Таблица32[[#This Row],[Столбец7]]*Таблица32[[#This Row],[Nazoratchi]]% -> 0 | AF6: =Таблица32[[#This Row],[Ishga vaqtida kelish nazoratchi]]+Таблица32[[#This Row],[Nazoratchi2]] -> 0 | AG6: =Таблица32[[#This Row],[Ishga vaqtida kelish ketish2]]+Таблица32[[#This Row],[Gruppa buxgalter4]]+Таблица32[[#This Row],[1C baza3]]+Таблица32[[#This Row],[xatlar4]]+Таблица32[[#This Row],[Belgilangan otchetlar5]] -> 7000 | AH6: =Таблица32[[#This Row],[Ishga kelish bank klient3]]+Таблица32[[#This Row],[Gruppa bank klient 2]] -> 14000
A7: 5 | B7: ООО "TEN BRANCHES" | C7: Go'zaloy | E7: 0 | F7: Muslimbek | G7: 0.05 | J7: 1 | L7: 0 | M7: 0 | P7: 0 | Q7: 0 | R7: 0 | S7: 0 | T7: 0 | U7: 0 | V7: 0.5 | W7: =Таблица32[[#This Row],[Столбец7]]*Таблица32[[#This Row],[Ishga kelish nazoratchi2]]% -> 0 | X7: =Таблица32[[#This Row],[Столбец7]]*Таблица32[[#This Row],[Ishga vaqtida kelish ketish]]% -> 0 | Y7: =Таблица32[[#This Row],[Столбец7]]*Таблица32[[#This Row],[Ishga kelish bank klient]]% -> 0 | Z7: =Таблица32[[#This Row],[Столбец7]]*Таблица32[[#This Row],[Gruppa buxgalter]]% -> 0 | AA7: =Таблица32[[#This Row],[Столбец7]]*Таблица32[[#This Row],[Gruppa bank klient ]]% -> 0 | AB7: =Таблица32[[#This Row],[1c]]*Таблица32[[#This Row],[Столбец7]]/100 -> 0 | AC7: =SUM(Таблица32[[#This Row],[Didox]:[ мехнат]],Таблица32[[#This Row],[Avtokameral]])*Таблица32[[#This Row],[Столбец7]]/100 -> 0 | AD7: =SUM(Таблица32[[#This Row],[Pul oqimlari]:[Foyda va zarar]])*Таблица32[[#This Row],[Столбец7]]/100 -> 0 | AE7: =Таблица32[[#This Row],[Столбец7]]*Таблица32[[#This Row],[Nazoratchi]]% -> 0 | AF7: =Таблица32[[#This Row],[Ishga vaqtida kelish nazoratchi]]+Таблица32[[#This Row],[Nazoratchi2]] -> 0 | AG7: =Таблица32[[#This Row],[Ishga vaqtida kelish ketish2]]+Таблица32[[#This Row],[Gruppa buxgalter4]]+Таблица32[[#This Row],[1C baza3]]+Таблица32[[#This Row],[xatlar4]]+Таблица32[[#This Row],[Belgilangan otchetlar5]] -> 0 | AH7: =Таблица32[[#This Row],[Ishga kelish bank klient3]]+Таблица32[[#This Row],[Gruppa bank klient 2]] -> 0
A8: 6 | B8: СП "ZIL-BAX" | C8: Abrorbek | D8: Ruslan | E8: 700000 | F8: Go'zaloy | H8: 1 | J8: 1 | K8: 1 | L8: 0.25 | M8: 0.25 | P8: 0.25 | Q8: 0 | R8: 0.2 | S8: 0.2 | T8: 0.2 | U8: 0 | V8: 0.5 | W8: =Таблица32[[#This Row],[Столбец7]]*Таблица32[[#This Row],[Ishga kelish nazoratchi2]]% -> 0 | X8: =Таблица32[[#This Row],[Столбец7]]*Таблица32[[#This Row],[Ishga vaqtida kelish ketish]]% -> 0 | Y8: =Таблица32[[#This Row],[Столбец7]]*Таблица32[[#This Row],[Ishga kelish bank klient]]% -> 7000 | Z8: =Таблица32[[#This Row],[Столбец7]]*Таблица32[[#This Row],[Gruppa buxgalter]]% -> 7000 | AA8: =Таблица32[[#This Row],[Столбец7]]*Таблица32[[#This Row],[Gruppa bank klient ]]% -> 7000 | AB8: =Таблица32[[#This Row],[1c]]*Таблица32[[#This Row],[Столбец7]]/100 -> 0 | AC8: =SUM(Таблица32[[#This Row],[Didox]:[ мехнат]],Таблица32[[#This Row],[Avtokameral]])*Таблица32[[#This Row],[Столбец7]]/100 -> 5250 | AD8: =SUM(Таблица32[[#This Row],[Pul oqimlari]:[Foyda va zarar]])*Таблица32[[#This Row],[Столбец7]]/100 -> 4200 | AE8: =Таблица32[[#This Row],[Столбец7]]*Таблица32[[#This Row],[Nazoratchi]]% -> 3500 | AF8: =Таблица32[[#This Row],[Ishga vaqtida kelish nazoratchi]]+Таблица32[[#This Row],[Nazoratchi2]] -> 3500 | AG8: =Таблица32[[#This Row],[Ishga vaqtida kelish ketish2]]+Таблица32[[#This Row],[Gruppa buxgalter4]]+Таблица32[[#This Row],[1C baza3]]+Таблица32[[#This Row],[xatlar4]]+Таблица32[[#This Row],[Belgilangan otchetlar5]] -> 16450 | AH8: =Таблица32[[#This Row],[Ishga kelish bank klient3]]+Таблица32[[#This Row],[Gruppa bank klient 2]] -> 14000
A9: 7 | B9: OOO "SARDORBEK HOUSE" | C9: Ruslan | D9: Ruslan | E9: 700000 | F9: Go'zaloy | H9: 1 | K9: 1 | L9: 0.25 | M9: 0.25 | P9: 0.25 | Q9: 0 | R9: 0 | S9: 0 | T9: 0 | U9: 0 | W9: =Таблица32[[#This Row],[Столбец7]]*Таблица32[[#This Row],[Ishga kelish nazoratchi2]]% -> 0 | X9: =Таблица32[[#This Row],[Столбец7]]*Таблица32[[#This Row],[Ishga vaqtida kelish ketish]]% -> 0 | Y9: =Таблица32[[#This Row],[Столбец7]]*Таблица32[[#This Row],[Ishga kelish bank klient]]% -> 7000 | Z9: =Таблица32[[#This Row],[Столбец7]]*Таблица32[[#This Row],[Gruppa buxgalter]]% -> 0 | AA9: =Таблица32[[#This Row],[Столбец7]]*Таблица32[[#This Row],[Gruppa bank klient ]]% -> 7000 | AB9: =Таблица32[[#This Row],[1c]]*Таблица32[[#This Row],[Столбец7]]/100 -> 0 | AC9: =SUM(Таблица32[[#This Row],[Didox]:[ мехнат]],Таблица32[[#This Row],[Avtokameral]])*Таблица32[[#This Row],[Столбец7]]/100 -> 5250 | AD9: =SUM(Таблица32[[#This Row],[Pul oqimlari]:[Foyda va zarar]])*Таблица32[[#This Row],[Столбец7]]/100 -> 0 | AE9: =Таблица32[[#This Row],[Столбец7]]*Таблица32[[#This Row],[Nazoratchi]]% -> 0 | AF9: =Таблица32[[#This Row],[Ishga vaqtida kelish nazoratchi]]+Таблица32[[#This Row],[Nazoratchi2]] -> 0 | AG9: =Таблица32[[#This Row],[Ishga vaqtida kelish ketish2]]+Таблица32[[#This Row],[Gruppa buxgalter4]]+Таблица32[[#This Row],[1C baza3]]+Таблица32[[#This Row],[xatlar4]]+Таблица32[[#This Row],[Belgilangan otchetlar5]] -> 5250 | AH9: =Таблица32[[#This Row],[Ishga kelish bank klient3]]+Таблица32[[#This Row],[Gruppa bank klient 2]] -> 14000
A10: 8 | B10: "DILFUZAXON AVTO" | C10: Abrorbek | D10: Ruslan | E10: 2000000 | F10: Go'zaloy | H10: 1 | J10: -2 | K10: 1 | L10: 0.25 | M10: 0.25 | P10: -0.25 | Q10: 0 | R10: 0.2 | S10: 0.2 | T10: 0.2 | U10: 0.2 | V10: -2 | W10: =Таблица32[[#This Row],[Столбец7]]*Таблица32[[#This Row],[Ishga kelish nazoratchi2]]% -> 0 | X10: =Таблица32[[#This Row],[Столбец7]]*Таблица32[[#This Row],[Ishga vaqtida kelish ketish]]% -> 0 | Y10: =Таблица32[[#This Row],[Столбец7]]*Таблица32[[#This Row],[Ishga kelish bank klient]]% -> 20000 | Z10: =Таблица32[[#This Row],[Столбец7]]*Таблица32[[#This Row],[Gruppa buxgalter]]% -> -40000 | AA10: =Таблица32[[#This Row],[Столбец7]]*Таблица32[[#This Row],[Gruppa bank klient ]]% -> 20000 | AB10: =Таблица32[[#This Row],[1c]]*Таблица32[[#This Row],[Столбец7]]/100 -> 0 | AC10: =SUM(Таблица32[[#This Row],[Didox]:[ мехнат]],Таблица32[[#This Row],[Avtokameral]])*Таблица32[[#This Row],[Столбец7]]/100 -> 5000 | AD10: =SUM(Таблица32[[#This Row],[Pul oqimlari]:[Foyda va zarar]])*Таблица32[[#This Row],[Столбец7]]/100 -> 16000 | AE10: =Таблица32[[#This Row],[Столбец7]]*Таблица32[[#This Row],[Nazoratchi]]% -> -40000 | AF10: =Таблица32[[#This Row],[Ishga vaqtida kelish nazoratchi]]+Таблица32[[#This Row],[Nazoratchi2]] -> -40000 | AG10: =Таблица32[[#This Row],[Ishga vaqtida kelish ketish2]]+Таблица32[[#This Row],[Gruppa buxgalter4]]+Таблица32[[#This Row],[1C baza3]]+Таблица32[[#This Row],[xatlar4]]+Таблица32[[#This Row],[Belgilangan otchetlar5]] -> -19000 | AH10: =Таблица32[[#This Row],[Ishga kelish bank klient3]]+Таблица32[[#This Row],[Gruppa bank klient 2]] -> 40000
A11: 9 | B11: "SOF MEDTEX" MCHJ | C11: Maxmuda | D11: Azizbek | E11: 6000000 | F11: Go'zaloy | H11: 1 | J11: 1 | K11: 1 | L11: 0.25 | M11: 0.25 | N11: 0.25 | P11: 0.25 | Q11: -0.2 | R11: 0.2 | S11: -0.2 | T11: -0.2 | U11: -0.2 | V11: 0.5 | W11: =Таблица32[[#This Row],[Столбец7]]*Таблица32[[#This Row],[Ishga kelish nazoratchi2]]% -> 0 | X11: =Таблица32[[#This Row],[Столбец7]]*Таблица32[[#This Row],[Ishga vaqtida kelish ketish]]% -> 0 | Y11: =Таблица32[[#This Row],[Столбец7]]*Таблица32[[#This Row],[Ishga kelish bank klient]]% -> 60000 | Z11: =Таблица32[[#This Row],[Столбец7]]*Таблица32[[#This Row],[Gruppa buxgalter]]% -> 60000 | AA11: =Таблица32[[#This Row],[Столбец7]]*Таблица32[[#This Row],[Gruppa bank klient ]]% -> 60000 | AB11: =Таблица32[[#This Row],[1c]]*Таблица32[[#This Row],[Столбец7]]/100 -> 0 | AC11: =SUM(Таблица32[[#This Row],[Didox]:[ мехнат]],Таблица32[[#This Row],[Avtokameral]])*Таблица32[[#This Row],[Столбец7]]/100 -> 60000 | AD11: =SUM(Таблица32[[#This Row],[Pul oqimlari]:[Foyda va zarar]])*Таблица32[[#This Row],[Столбец7]]/100 -> -36000 | AE11: =Таблица32[[#This Row],[Столбец7]]*Таблица32[[#This Row],[Nazoratchi]]% -> 30000 | AF11: =Таблица32[[#This Row],[Ishga vaqtida kelish nazoratchi]]+Таблица32[[#This Row],[Nazoratchi2]] -> 30000 | AG11: =Таблица32[[#This Row],[Ishga vaqtida kelish ketish2]]+Таблица32[[#This Row],[Gruppa buxgalter4]]+Таблица32[[#This Row],[1C baza3]]+Таблица32[[#This Row],[xatlar4]]+Таблица32[[#This Row],[Belgilangan otchetlar5]] -> 84000 | AH11: =Таблица32[[#This Row],[Ishga kelish bank klient3]]+Таблица32[[#This Row],[Gruppa bank klient 2]] -> 120000
A12: 10 | B12: OOO "RONICS" | C12: Muslimbek | D12: Azizbek | E12: 2500000 | F12: Go'zaloy | G12: -0.8 | H12: 1 | J12: -0.5 | K12: 1 | L12: 0.25 | M12: 0.25 | O12: 1 | P12: 0 | Q12: 0.2 | R12: 0.2 | S12: 0.2 | T12: 0.2 | U12: 0.2 | V12: -0.5 | W12: =Таблица32[[#This Row],[Столбец7]]*Таблица32[[#This Row],[Ishga kelish nazoratchi2]]% -> 0 | X12: =Таблица32[[#This Row],[Столбец7]]*Таблица32[[#This Row],[Ishga vaqtida kelish ketish]]% -> -20000 | Y12: =Таблица32[[#This Row],[Столбец7]]*Таблица32[[#This Row],[Ishga kelish bank klient]]% -> 25000 | Z12: =Таблица32[[#This Row],[Столбец7]]*Таблица32[[#This Row],[Gruppa buxgalter]]% -> -12500 | AA12: =Таблица32[[#This Row],[Столбец7]]*Таблица32[[#This Row],[Gruppa bank klient ]]% -> 25000 | AB12: =Таблица32[[#This Row],[1c]]*Таблица32[[#This Row],[Столбец7]]/100 -> 25000 | AC12: =SUM(Таблица32[[#This Row],[Didox]:[ мехнат]],Таблица32[[#This Row],[Avtokameral]])*Таблица32[[#This Row],[Столбец7]]/100 -> 12500 | AD12: =SUM(Таблица32[[#This Row],[Pul oqimlari]:[Foyda va zarar]])*Таблица32[[#This Row],[Столбец7]]/100 -> 25000 | AE12: =Таблица32[[#This Row],[Столбец7]]*Таблица32[[#This Row],[Nazoratchi]]% -> -12500 | AF12: =Таблица32[[#This Row],[Ishga vaqtida kelish nazoratchi]]+Таблица32[[#This Row],[Nazoratchi2]] -> -12500 | AG12: =Таблица32[[#This Row],[Ishga vaqtida kelish ketish2]]+Таблица32[[#This Row],[Gruppa buxgalter4]]+Таблица32[[#This Row],[1C baza3]]+Таблица32[[#This Row],[xatlar4]]+Таблица32[[#This Row],[Belgilangan otchetlar5]] -> 30000 | AH12: =Таблица32[[#This Row],[Ishga kelish bank klient3]]+Таблица32[[#This Row],[Gruppa bank klient 2]] -> 50000
A13: 11 | B13: "SAPRAMTECH" OOO | C13: Muslimbek | D13: Azizbek | E13: 7000000 | F13: Go'zaloy | G13: -0.8 | H13: 1 | J13: -0.5 | K13: 1 | L13: 0.25 | M13: 0.25 | N13: 0.25 | O13: 1 | P13: 0 | Q13: 0.2 | R13: 0.2 | S13: 0.2 | T13: 0.2 | U13: 0.2 | V13: -0.5 | W13: =Таблица32[[#This Row],[Столбец7]]*Таблица32[[#This Row],[Ishga kelish nazoratchi2]]% -> 0 | X13: =Таблица32[[#This Row],[Столбец7]]*Таблица32[[#This Row],[Ishga vaqtida kelish ketish]]% -> -56000 | Y13: =Таблица32[[#This Row],[Столбец7]]*Таблица32[[#This Row],[Ishga kelish bank klient]]% -> 70000 | Z13: =Таблица32[[#This Row],[Столбец7]]*Таблица32[[#This Row],[Gruppa buxgalter]]% -> -35000 | AA13: =Таблица32[[#This Row],[Столбец7]]*Таблица32[[#This Row],[Gruppa bank klient ]]% -> 70000 | AB13: =Таблица32[[#This Row],[1c]]*Таблица32[[#This Row],[Столбец7]]/100 -> 70000 | AC13: =SUM(Таблица32[[#This Row],[Didox]:[ мехнат]],Таблица32[[#This Row],[Avtokameral]])*Таблица32[[#This Row],[Столбец7]]/100 -> 52500 | AD13: =SUM(Таблица32[[#This Row],[Pul oqimlari]:[Foyda va zarar]])*Таблица32[[#This Row],[Столбец7]]/100 -> 70000 | AE13: =Таблица32[[#This Row],[Столбец7]]*Таблица32[[#This Row],[Nazoratchi]]% -> -35000 | AF13: =Таблица32[[#This Row],[Ishga vaqtida kelish nazoratchi]]+Таблица32[[#This Row],[Nazoratchi2]] -> -35000 | AG13: =Таблица32[[#This Row],[Ishga vaqtida kelish ketish2]]+Таблица32[[#This Row],[Gruppa buxgalter4]]+Таблица32[[#This Row],[1C baza3]]+Таблица32[[#This Row],[xatlar4]]+Таблица32[[#This Row],[Belgilangan otchetlar5]] -> 101500 | AH13: =Таблица32[[#This Row],[Ishga kelish bank klient3]]+Таблица32[[#This Row],[Gruppa bank klient 2]] -> 140000
A14: 12 | B14: GELECTRONIC | C14: Mirabbos | D14: Ruslan | E14: 4000000 | F14: Muslimbek | H14: 1 | J14: 1 | K14: 1 | L14: 0.25 | M14: 0.25 | N14: 0.25 | P14: 0.25 | Q14: 0.2 | R14: 0.2 | S14: 0.2 | T14: 0.2 | U14: 0.2 | V14: 0.5 | W14: =Таблица32[[#This Row],[Столбец7]]*Таблица32[[#This Row],[Ishga kelish nazoratchi2]]% -> 0 | X14: =Таблица32[[#This Row],[Столбец7]]*Таблица32[[#This Row],[Ishga vaqtida kelish ketish]]% -> 0 | Y14: =Таблица32[[#This Row],[Столбец7]]*Таблица32[[#This Row],[Ishga kelish bank klient]]% -> 40000 | Z14: =Таблица32[[#This Row],[Столбец7]]*Таблица32[[#This Row],[Gruppa buxgalter]]% -> 40000 | AA14: =Таблица32[[#This Row],[Столбец7]]*Таблица32[[#This Row],[Gruppa bank klient ]]% -> 40000 | AB14: =Таблица32[[#This Row],[1c]]*Таблица32[[#This Row],[Столбец7]]/100 -> 0 | AC14: =SUM(Таблица32[[#This Row],[Didox]:[ мехнат]],Таблица32[[#This Row],[Avtokameral]])*Таблица32[[#This Row],[Столбец7]]/100 -> 40000 | AD14: =SUM(Таблица32[[#This Row],[Pul oqimlari]:[Foyda va zarar]])*Таблица32[[#This Row],[Столбец7]]/100 -> 40000 | AE14: =Таблица32[[#This Row],[Столбец7]]*Таблица32[[#This Row],[Nazoratchi]]% -> 20000 | AF14: =Таблица32[[#This Row],[Ishga vaqtida kelish nazoratchi]]+Таблица32[[#This Row],[Nazoratchi2]] -> 20000 | AG14: =Таблица32[[#This Row],[Ishga vaqtida kelish ketish2]]+Таблица32[[#This Row],[Gruppa buxgalter4]]+Таблица32[[#This Row],[1C baza3]]+Таблица32[[#This Row],[xatlar4]]+Таблица32[[#This Row],[Belgilangan otchetlar5]] -> 120000 | AH14: =Таблица32[[#This Row],[Ishga kelish bank klient3]]+Таблица32[[#This Row],[Gruppa bank klient 2]] -> 80000
A15: 13 | B15: SHIRIN XK | C15: Go'zaloy | E15: 2000000 | F15: Muslimbek | G15: 0.05 | J15: 1 | L15: 0.25 | M15: 0.25 | N15: 0.25 | O15: 1 | P15: 0.25 | Q15: 0.2 | R15: 0.2 | S15: 0.2 | T15: 0.2 | U15: 0.2 | V15: 0.5 | W15: =Таблица32[[#This Row],[Столбец7]]*Таблица32[[#This Row],[Ishga kelish nazoratchi2]]% -> 0 | X15: =Таблица32[[#This Row],[Столбец7]]*Таблица32[[#This Row],[Ishga vaqtida kelish ketish]]% -> 1000 | Y15: =Таблица32[[#This Row],[Столбец7]]*Таблица32[[#This Row],[Ishga kelish bank klient]]% -> 0 | Z15: =Таблица32[[#This Row],[Столбец7]]*Таблица32[[#This Row],[Gruppa buxgalter]]% -> 20000 | AA15: =Таблица32[[#This Row],[Столбец7]]*Таблица32[[#This Row],[Gruppa bank klient ]]% -> 0 | AB15: =Таблица32[[#This Row],[1c]]*Таблица32[[#This Row],[Столбец7]]/100 -> 20000 | AC15: =SUM(Таблица32[[#This Row],[Didox]:[ мехнат]],Таблица32[[#This Row],[Avtokameral]])*Таблица32[[#This Row],[Столбец7]]/100 -> 20000 | AD15: =SUM(Таблица32[[#This Row],[Pul oqimlari]:[Foyda va zarar]])*Таблица32[[#This Row],[Столбец7]]/100 -> 20000 | AE15: =Таблица32[[#This Row],[Столбец7]]*Таблица32[[#This Row],[Nazoratchi]]% -> 10000 | AF15: =Таблица32[[#This Row],[Ishga vaqtida kelish nazoratchi]]+Таблица32[[#This Row],[Nazoratchi2]] -> 10000 | AG15: =Таблица32[[#This Row],[Ishga vaqtida kelish ketish2]]+Таблица32[[#This Row],[Gruppa buxgalter4]]+Таблица32[[#This Row],[1C baza3]]+Таблица32[[#This Row],[xatlar4]]+Таблица32[[#This Row],[Belgilangan otchetlar5]] -> 81000 | AH15: =Таблица32[[#This Row],[Ishga kelish bank klient3]]+Таблица32[[#This Row],[Gruppa bank klient 2]] -> 0
A16: 14 | B16: MELIOMASH | C16: Go'zaloy | E16: 0 | F16: Muslimbek | G16: 0.05 | J16: 1 | L16: 0 | M16: 0 | P16: 0 | Q16: 0 | R16: 0 | S16: 0 | T16: 0 | U16: 0 | V16: 0.5 | W16: =Таблица32[[#This Row],[Столбец7]]*Таблица32[[#This Row],[Ishga kelish nazoratchi2]]% -> 0 | X16: =Таблица32[[#This Row],[Столбец7]]*Таблица32[[#This Row],[Ishga vaqtida kelish ketish]]% -> 0 | Y16: =Таблица32[[#This Row],[Столбец7]]*Таблица32[[#This Row],[Ishga kelish bank klient]]% -> 0 | Z16: =Таблица32[[#This Row],[Столбец7]]*Таблица32[[#This Row],[Gruppa buxgalter]]% -> 0 | AA16: =Таблица32[[#This Row],[Столбец7]]*Таблица32[[#This Row],[Gruppa bank klient ]]% -> 0 | AB16: =Таблица32[[#This Row],[1c]]*Таблица32[[#This Row],[Столбец7]]/100 -> 0 | AC16: =SUM(Таблица32[[#This Row],[Didox]:[ мехнат]],Таблица32[[#This Row],[Avtokameral]])*Таблица32[[#This Row],[Столбец7]]/100 -> 0 | AD16: =SUM(Таблица32[[#This Row],[Pul oqimlari]:[Foyda va zarar]])*Таблица32[[#This Row],[Столбец7]]/100 -> 0 | AE16: =Таблица32[[#This Row],[Столбец7]]*Таблица32[[#This Row],[Nazoratchi]]% -> 0 | AF16: =Таблица32[[#This Row],[Ishga vaqtida kelish nazoratchi]]+Таблица32[[#This Row],[Nazoratchi2]] -> 0 | AG16: =Таблица32[[#This Row],[Ishga vaqtida kelish ketish2]]+Таблица32[[#This Row],[Gruppa buxgalter4]]+Таблица32[[#This Row],[1C baza3]]+Таблица32[[#This Row],[xatlar4]]+Таблица32[[#This Row],[Belgilangan otchetlar5]] -> 0 | AH16: =Таблица32[[#This Row],[Ishga kelish bank klient3]]+Таблица32[[#This Row],[Gruppa bank klient 2]] -> 0
A17: 15 | B17: "C A WOLVES" | C17: Axmadjon | D17: Azizbek | E17: 3000000 | F17: Muslimbek | H17: 1 | J17: 1 | K17: 1 | L17: 0.25 | M17: 0.25 | O17: 1 | P17: 0.25 | Q17: 0.2 | R17: 0.2 | S17: 0 | T17: 0.2 | U17: 0.2 | V17: 0.5 | W17: =Таблица32[[#This Row],[Столбец7]]*Таблица32[[#This Row],[Ishga kelish nazoratchi2]]% -> 0 | X17: =Таблица32[[#This Row],[Столбец7]]*Таблица32[[#This Row],[Ishga vaqtida kelish ketish]]% -> 0 | Y17: =Таблица32[[#This Row],[Столбец7]]*Таблица32[[#This Row],[Ishga kelish bank klient]]% -> 30000 | Z17: =Таблица32[[#This Row],[Столбец7]]*Таблица32[[#This Row],[Gruppa buxgalter]]% -> 30000 | AA17: =Таблица32[[#This Row],[Столбец7]]*Таблица32[[#This Row],[Gruppa bank klient ]]% -> 30000 | AB17: =Таблица32[[#This Row],[1c]]*Таблица32[[#This Row],[Столбец7]]/100 -> 30000 | AC17: =SUM(Таблица32[[#This Row],[Didox]:[ мехнат]],Таблица32[[#This Row],[Avtokameral]])*Таблица32[[#This Row],[Столбец7]]/100 -> 22500 | AD17: =SUM(Таблица32[[#This Row],[Pul oqimlari]:[Foyda va zarar]])*Таблица32[[#This Row],[Столбец7]]/100 -> 24000 | AE17: =Таблица32[[#This Row],[Столбец7]]*Таблица32[[#This Row],[Nazoratchi]]% -> 15000 | AF17: =Таблица32[[#This Row],[Ishga vaqtida kelish nazoratchi]]+Таблица32[[#This Row],[Nazoratchi2]] -> 15000 | AG17: =Таблица32[[#This Row],[Ishga vaqtida kelish ketish2]]+Таблица32[[#This Row],[Gruppa buxgalter4]]+Таблица32[[#This Row],[1C baza3]]+Таблица32[[#This Row],[xatlar4]]+Таблица32[[#This Row],[Belgilangan otchetlar5]] -> 106500 | AH17: =Таблица32[[#This Row],[Ishga kelish bank klient3]]+Таблица32[[#This Row],[Gruppa bank klient 2]] -> 60000
A18: 16 | B18: "AL-AZIZ ACADEMY" НОУ | C18: Musobek | D18: Azizbek | E18: 3500000 | F18: Go'zaloy | G18: 0.9 | H18: 1 | J18: 1 | K18: 1 | L18: 0.25 | M18: 0.25 | P18: 0.25 | Q18: 0.2 | R18: 0.2 | S18: 0.2 | T18: -0.2 | U18: -0.2 | V18: 0.5 | W18: =Таблица32[[#This Row],[Столбец7]]*Таблица32[[#This Row],[Ishga kelish nazoratchi2]]% -> 0 | X18: =Таблица32[[#This Row],[Столбец7]]*Таблица32[[#This Row],[Ishga vaqtida kelish ketish]]% -> 31500 | Y18: =Таблица32[[#This Row],[Столбец7]]*Таблица32[[#This Row],[Ishga kelish bank klient]]% -> 35000 | Z18: =Таблица32[[#This Row],[Столбец7]]*Таблица32[[#This Row],[Gruppa buxgalter]]% -> 35000 | AA18: =Таблица32[[#This Row],[Столбец7]]*Таблица32[[#This Row],[Gruppa bank klient ]]% -> 35000 | AB18: =Таблица32[[#This Row],[1c]]*Таблица32[[#This Row],[Столбец7]]/100 -> 0 | AC18: =SUM(Таблица32[[#This Row],[Didox]:[ мехнат]],Таблица32[[#This Row],[Avtokameral]])*Таблица32[[#This Row],[Столбец7]]/100 -> 26250 | AD18: =SUM(Таблица32[[#This Row],[Pul oqimlari]:[Foyda va zarar]])*Таблица32[[#This Row],[Столбец7]]/100 -> 7000 | AE18: =Таблица32[[#This Row],[Столбец7]]*Таблица32[[#This Row],[Nazoratchi]]% -> 17500 | AF18: =Таблица32[[#This Row],[Ishga vaqtida kelish nazoratchi]]+Таблица32[[#This Row],[Nazoratchi2]] -> 17500 | AG18: =Таблица32[[#This Row],[Ishga vaqtida kelish ketish2]]+Таблица32[[#This Row],[Gruppa buxgalter4]]+Таблица32[[#This Row],[1C baza3]]+Таблица32[[#This Row],[xatlar4]]+Таблица32[[#This Row],[Belgilangan otchetlar5]] -> 99750 | AH18: =Таблица32[[#This Row],[Ishga kelish bank klient3]]+Таблица32[[#This Row],[Gruppa bank klient 2]] -> 70000
A19: 17 | B19: ООО "INTEST MAX" | C19: Go'zaloy | D19: Azizbek | E19: 25000000 | F19: Muslimbek | G19: 0.05 | H19: 1 | J19: 1 | K19: 1 | L19: 0.25 | M19: 0.25 | N19: 0.25 | O19: 1 | P19: 0.25 | Q19: 0 | R19: 0.2 | S19: 0.2 | T19: 0.2 | U19: 0 | V19: 0.5 | W19: =Таблица32[[#This Row],[Столбец7]]*Таблица32[[#This Row],[Ishga kelish nazoratchi2]]% -> 0 | X19: =Таблица32[[#This Row],[Столбец7]]*Таблица32[[#This Row],[Ishga vaqtida kelish ketish]]% -> 12500 | Y19: =Таблица32[[#This Row],[Столбец7]]*Таблица32[[#This Row],[Ishga kelish bank klient]]% -> 250000 | Z19: =Таблица32[[#This Row],[Столбец7]]*Таблица32[[#This Row],[Gruppa buxgalter]]% -> 250000 | AA19: =Таблица32[[#This Row],[Столбец7]]*Таблица32[[#This Row],[Gruppa bank klient ]]% -> 250000 | AB19: =Таблица32[[#This Row],[1c]]*Таблица32[[#This Row],[Столбец7]]/100 -> 250000 | AC19: =SUM(Таблица32[[#This Row],[Didox]:[ мехнат]],Таблица32[[#This Row],[Avtokameral]])*Таблица32[[#This Row],[Столбец7]]/100 -> 250000 | AD19: =SUM(Таблица32[[#This Row],[Pul oqimlari]:[Foyda va zarar]])*Таблица32[[#This Row],[Столбец7]]/100 -> 150000 | AE19: =Таблица32[[#This Row],[Столбец7]]*Таблица32[[#This Row],[Nazoratchi]]% -> 125000 | AF19: =Таблица32[[#This Row],[Ishga vaqtida kelish nazoratchi]]+Таблица32[[#This Row],[Nazoratchi2]] -> 125000 | AG19: =Таблица32[[#This Row],[Ishga vaqtida kelish ketish2]]+Таблица32[[#This Row],[Gruppa buxgalter4]]+Таблица32[[#This Row],[1C baza3]]+Таблица32[[#This Row],[xatlar4]]+Таблица32[[#This Row],[Belgilangan otchetlar5]] -> 912500 | AH19: =Таблица32[[#This Row],[Ishga kelish bank klient3]]+Таблица32[[#This Row],[Gruppa bank klient 2]] -> 500000
A20: 18 | B20: "AVIA GORODOK" | C20: Axmadjon | D20: Ruslan | E20: 1000000 | F20: Muslimbek | H20: 1 | J20: 1 | K20: 1 | L20: 0.25 | M20: 0.25 | N20: 0.25 | O20: 1 | P20: 0.25 | Q20: 0.2 | R20: 0.2 | S20: 0.2 | T20: 0.2 | U20: 0.2 | V20: 0.5 | W20: =Таблица32[[#This Row],[Столбец7]]*Таблица32[[#This Row],[Ishga kelish nazoratchi2]]% -> 0 | X20: =Таблица32[[#This Row],[Столбец7]]*Таблица32[[#This Row],[Ishga vaqtida kelish ketish]]% -> 0 | Y20: =Таблица32[[#This Row],[Столбец7]]*Таблица32[[#This Row],[Ishga kelish bank klient]]% -> 10000 | Z20: =Таблица32[[#This Row],[Столбец7]]*Таблица32[[#This Row],[Gruppa buxgalter]]% -> 10000 | AA20: =Таблица32[[#This Row],[Столбец7]]*Таблица32[[#This Row],[Gruppa bank klient ]]% -> 10000 | AB20: =Таблица32[[#This Row],[1c]]*Таблица32[[#This Row],[Столбец7]]/100 -> 10000 | AC20: =SUM(Таблица32[[#This Row],[Didox]:[ мехнат]],Таблица32[[#This Row],[Avtokameral]])*Таблица32[[#This Row],[Столбец7]]/100 -> 10000 | AD20: =SUM(Таблица32[[#This Row],[Pul oqimlari]:[Foyda va zarar]])*Таблица32[[#This Row],[Столбец7]]/100 -> 10000 | AE20: =Таблица32[[#This Row],[Столбец7]]*Таблица32[[#This Row],[Nazoratchi]]% -> 5000 | AF20: =Таблица32[[#This Row],[Ishga vaqtida kelish nazoratchi]]+Таблица32[[#This Row],[Nazoratchi2]] -> 5000 | AG20: =Таблица32[[#This Row],[Ishga vaqtida kelish ketish2]]+Таблица32[[#This Row],[Gruppa buxgalter4]]+Таблица32[[#This Row],[1C baza3]]+Таблица32[[#This Row],[xatlar4]]+Таблица32[[#This Row],[Belgilangan otchetlar5]] -> 40000 | AH20: =Таблица32[[#This Row],[Ishga kelish bank klient3]]+Таблица32[[#This Row],[Gruppa bank klient 2]] -> 20000
A21: 19 | B21: "AVTOMATLASHTIRILGAN ELEKTRIK YURITMA" | C21: Otabek | E21: 500000 | F21: Muslimbek | J21: 1 | L21: 0.25 | M21: 0.25 | P21: 0.25 | Q21: 0 | R21: 0 | S21: 0 | T21: 0 | U21: 0 | V21: 0.5 | W21: =Таблица32[[#This Row],[Столбец7]]*Таблица32[[#This Row],[Ishga kelish nazoratchi2]]% -> 0 | X21: =Таблица32[[#This Row],[Столбец7]]*Таблица32[[#This Row],[Ishga vaqtida kelish ketish]]% -> 0 | Y21: =Таблица32[[#This Row],[Столбец7]]*Таблица32[[#This Row],[Ishga kelish bank klient]]% -> 0 | Z21: =Таблица32[[#This Row],[Столбец7]]*Таблица32[[#This Row],[Gruppa buxgalter]]% -> 5000 | AA21: =Таблица32[[#This Row],[Столбец7]]*Таблица32[[#This Row],[Gruppa bank klient ]]% -> 0 | AB21: =Таблица32[[#This Row],[1c]]*Таблица32[[#This Row],[Столбец7]]/100 -> 0 | AC21: =SUM(Таблица32[[#This Row],[Didox]:[ мехнат]],Таблица32[[#This Row],[Avtokameral]])*Таблица32[[#This Row],[Столбец7]]/100 -> 3750 | AD21: =SUM(Таблица32[[#This Row],[Pul oqimlari]:[Foyda va zarar]])*Таблица32[[#This Row],[Столбец7]]/100 -> 0 | AE21: =Таблица32[[#This Row],[Столбец7]]*Таблица32[[#This Row],[Nazoratchi]]% -> 2500 | AF21: =Таблица32[[#This Row],[Ishga vaqtida kelish nazoratchi]]+Таблица32[[#This Row],[Nazoratchi2]] -> 2500 | AG21: =Таблица32[[#This Row],[Ishga vaqtida kelish ketish2]]+Таблица32[[#This Row],[Gruppa buxgalter4]]+Таблица32[[#This Row],[1C baza3]]+Таблица32[[#This Row],[xatlar4]]+Таблица32[[#This Row],[Belgilangan otchetlar5]] -> 8750 | AH21: =Таблица32[[#This Row],[Ishga kelish bank klient3]]+Таблица32[[#This Row],[Gruppa bank klient 2]] -> 0
A22: 20 | B22: BM UNIT | C22: Humora | D22: Azizbek | E22: 1000000 | F22: Go'zaloy | G22: -0.35 | H22: 1 | J22: 1 | K22: 1 | L22: 0.25 | M22: 0.25 | O22: 1 | P22: 0.25 | Q22: 0.2 | R22: 0.2 | S22: 0.2 | T22: 0.2 | U22: 0.2 | V22: 0.5 | W22: =Таблица32[[#This Row],[Столбец7]]*Таблица32[[#This Row],[Ishga kelish nazoratchi2]]% -> 0 | X22: =Таблица32[[#This Row],[Столбец7]]*Таблица32[[#This Row],[Ishga vaqtida kelish ketish]]% -> -3500 | Y22: =Таблица32[[#This Row],[Столбец7]]*Таблица32[[#This Row],[Ishga kelish bank klient]]% -> 10000 | Z22: =Таблица32[[#This Row],[Столбец7]]*Таблица32[[#This Row],[Gruppa buxgalter]]% -> 10000 | AA22: =Таблица32[[#This Row],[Столбец7]]*Таблица32[[#This Row],[Gruppa bank klient ]]% -> 10000 | AB22: =Таблица32[[#This Row],[1c]]*Таблица32[[#This Row],[Столбец7]]/100 -> 10000 | AC22: =SUM(Таблица32[[#This Row],[Didox]:[ мехнат]],Таблица32[[#This Row],[Avtokameral]])*Таблица32[[#This Row],[Столбец7]]/100 -> 7500 | AD22: =SUM(Таблица32[[#This Row],[Pul oqimlari]:[Foyda va zarar]])*Таблица32[[#This Row],[Столбец7]]/100 -> 10000 | AE22: =Таблица32[[#This Row],[Столбец7]]*Таблица32[[#This Row],[Nazoratchi]]% -> 5000 | AF22: =Таблица32[[#This Row],[Ishga vaqtida kelish nazoratchi]]+Таблица32[[#This Row],[Nazoratchi2]] -> 5000 | AG22: =Таблица32[[#This Row],[Ishga vaqtida kelish ketish2]]+Таблица32[[#This Row],[Gruppa buxgalter4]]+Таблица32[[#This Row],[1C baza3]]+Таблица32[[#This Row],[xatlar4]]+Таблица32[[#This Row],[Belgilangan otchetlar5]] -> 34000 | AH22: =Таблица32[[#This Row],[Ishga kelish bank klient3]]+Таблица32[[#This Row],[Gruppa bank klient 2]] -> 20000
A23: 21 | B23: ООО "AVTO LUXUSARY TRADE" | C23: Axmadjon | D23: Ruslan | E23: 1000000 | F23: Muslimbek | H23: 1 | J23: 1 | K23: 1 | L23: 0.25 | M23: 0.25 | O23: 1 | P23: 0.25 | Q23: 0.2 | R23: 0.2 | S23: 0.2 | T23: 0.2 | U23: 0.2 | V23: 0.5 | W23: =Таблица32[[#This Row],[Столбец7]]*Таблица32[[#This Row],[Ishga kelish nazoratchi2]]% -> 0 | X23: =Таблица32[[#This Row],[Столбец7]]*Таблица32[[#This Row],[Ishga vaqtida kelish ketish]]% -> 0 | Y23: =Таблица32[[#This Row],[Столбец7]]*Таблица32[[#This Row],[Ishga kelish bank klient]]% -> 10000 | Z23: =Таблица32[[#This Row],[Столбец7]]*Таблица32[[#This Row],[Gruppa buxgalter]]% -> 10000 | AA23: =Таблица32[[#This Row],[Столбец7]]*Таблица32[[#This Row],[Gruppa bank klient ]]% -> 10000 | AB23: =Таблица32[[#This Row],[1c]]*Таблица32[[#This Row],[Столбец7]]/100 -> 10000 | AC23: =SUM(Таблица32[[#This Row],[Didox]:[ мехнат]],Таблица32[[#This Row],[Avtokameral]])*Таблица32[[#This Row],[Столбец7]]/100 -> 7500 | AD23: =SUM(Таблица32[[#This Row],[Pul oqimlari]:[Foyda va zarar]])*Таблица32[[#This Row],[Столбец7]]/100 -> 10000 | AE23: =Таблица32[[#This Row],[Столбец7]]*Таблица32[[#This Row],[Nazoratchi]]% -> 5000 | AF23: =Таблица32[[#This Row],[Ishga vaqtida kelish nazoratchi]]+Таблица32[[#This Row],[Nazoratchi2]] -> 5000 | AG23: =Таблица32[[#This Row],[Ishga vaqtida kelish ketish2]]+Таблица32[[#This Row],[Gruppa buxgalter4]]+Таблица32[[#This Row],[1C baza3]]+Таблица32[[#This Row],[xatlar4]]+Таблица32[[#This Row],[Belgilangan otchetlar5]] -> 37500 | AH23: =Таблица32[[#This Row],[Ishga kelish bank klient3]]+Таблица32[[#This Row],[Gruppa bank klient 2]] -> 20000
A24: 22 | B24: KOLBERG PRODUCTION | E24: 50000000 | L24: 0 | M24: 0 | P24: 0 | Q24: 0 | R24: 0 | S24: 0 | T24: 0 | U24: 0 | W24: =Таблица32[[#This Row],[Столбец7]]*Таблица32[[#This Row],[Ishga kelish nazoratchi2]]% -> 0 | X24: =Таблица32[[#This Row],[Столбец7]]*Таблица32[[#This Row],[Ishga vaqtida kelish ketish]]% -> 0 | Y24: =Таблица32[[#This Row],[Столбец7]]*Таблица32[[#This Row],[Ishga kelish bank klient]]% -> 0 | Z24: =Таблица32[[#This Row],[Столбец7]]*Таблица32[[#This Row],[Gruppa buxgalter]]% -> 0 | AA24: =Таблица32[[#This Row],[Столбец7]]*Таблица32[[#This Row],[Gruppa bank klient ]]% -> 0 | AB24: =Таблица32[[#This Row],[1c]]*Таблица32[[#This Row],[Столбец7]]/100 -> 0 | AC24: =SUM(Таблица32[[#This Row],[Didox]:[ мехнат]],Таблица32[[#This Row],[Avtokameral]])*Таблица32[[#This Row],[Столбец7]]/100 -> 0 | AD24: =SUM(Таблица32[[#This Row],[Pul oqimlari]:[Foyda va zarar]])*Таблица32[[#This Row],[Столбец7]]/100 -> 0 | AE24: =Таблица32[[#This Row],[Столбец7]]*Таблица32[[#This Row],[Nazoratchi]]% -> 0 | AF24: =Таблица32[[#This Row],[Ishga vaqtida kelish nazoratchi]]+Таблица32[[#This Row],[Nazoratchi2]] -> 0 | AG24: =Таблица32[[#This Row],[Ishga vaqtida kelish ketish2]]+Таблица32[[#This Row],[Gruppa buxgalter4]]+Таблица32[[#This Row],[1C baza3]]+Таблица32[[#This Row],[xatlar4]]+Таблица32[[#This Row],[Belgilangan otchetlar5]] -> 0 | AH24: =Таблица32[[#This Row],[Ishga kelish bank klient3]]+Таблица32[[#This Row],[Gruppa bank klient 2]] -> 0
A25: 23 | B25: "AKJ SEBZOR BO`LIMI" | C25: Otabek | D25: Ruslan | E25: 500000 | F25: Muslimbek | H25: 1 | J25: 1 | K25: 1 | L25: 0.25 | M25: 0.25 | P25: 0.25 | Q25: 0 | R25: 0 | S25: 0 | T25: 0 | U25: 0 | V25: 0.5 | W25: =Таблица32[[#This Row],[Столбец7]]*Таблица32[[#This Row],[Ishga kelish nazoratchi2]]% -> 0 | X25: =Таблица32[[#This Row],[Столбец7]]*Таблица32[[#This Row],[Ishga vaqtida kelish ketish]]% -> 0 | Y25: =Таблица32[[#This Row],[Столбец7]]*Таблица32[[#This Row],[Ishga kelish bank klient]]% -> 5000 | Z25: =Таблица32[[#This Row],[Столбец7]]*Таблица32[[#This Row],[Gruppa buxgalter]]% -> 5000 | AA25: =Таблица32[[#This Row],[Столбец7]]*Таблица32[[#This Row],[Gruppa bank klient ]]% -> 5000 | AB25: =Таблица32[[#This Row],[1c]]*Таблица32[[#This Row],[Столбец7]]/100 -> 0 | AC25: =SUM(Таблица32[[#This Row],[Didox]:[ мехнат]],Таблица32[[#This Row],[Avtokameral]])*Таблица32[[#This Row],[Столбец7]]/100 -> 3750 | AD25: =SUM(Таблица32[[#This Row],[Pul oqimlari]:[Foyda va zarar]])*Таблица32[[#This Row],[Столбец7]]/100 -> 0 | AE25: =Таблица32[[#This Row],[Столбец7]]*Таблица32[[#This Row],[Nazoratchi]]% -> 2500 | AF25: =Таблица32[[#This Row],[Ishga vaqtida kelish nazoratchi]]+Таблица32[[#This Row],[Nazoratchi2]] -> 2500 | AG25: =Таблица32[[#This Row],[Ishga vaqtida kelish ketish2]]+Таблица32[[#This Row],[Gruppa buxgalter4]]+Таблица32[[#This Row],[1C baza3]]+Таблица32[[#This Row],[xatlar4]]+Таблица32[[#This Row],[Belgilangan otchetlar5]] -> 8750 | AH25: =Таблица32[[#This Row],[Ishga kelish bank klient3]]+Таблица32[[#This Row],[Gruppa bank klient 2]] -> 10000
A26: 24 | B26: "AKJ TUZEL BO`LIMI" | C26: Otabek | D26: Ruslan | E26: 500000 | F26: Muslimbek | H26: 1 | J26: 1 | K26: 1 | L26: 0.25 | M26: 0.25 | P26: 0.25 | Q26: 0 | R26: 0 | S26: 0 | T26: 0 | U26: 0 | V26: 0.5 | W26: =Таблица32[[#This Row],[Столбец7]]*Таблица32[[#This Row],[Ishga kelish nazoratchi2]]% -> 0 | X26: =Таблица32[[#This Row],[Столбец7]]*Таблица32[[#This Row],[Ishga vaqtida kelish ketish]]% -> 0 | Y26: =Таблица32[[#This Row],[Столбец7]]*Таблица32[[#This Row],[Ishga kelish bank klient]]% -> 5000 | Z26: =Таблица32[[#This Row],[Столбец7]]*Таблица32[[#This Row],[Gruppa buxgalter]]% -> 5000 | AA26: =Таблица32[[#This Row],[Столбец7]]*Таблица32[[#This Row],[Gruppa bank klient ]]% -> 5000 | AB26: =Таблица32[[#This Row],[1c]]*Таблица32[[#This Row],[Столбец7]]/100 -> 0 | AC26: =SUM(Таблица32[[#This Row],[Didox]:[ мехнат]],Таблица32[[#This Row],[Avtokameral]])*Таблица32[[#This Row],[Столбец7]]/100 -> 3750 | AD26: =SUM(Таблица32[[#This Row],[Pul oqimlari]:[Foyda va zarar]])*Таблица32[[#This Row],[Столбец7]]/100 -> 0 | AE26: =Таблица32[[#This Row],[Столбец7]]*Таблица32[[#This Row],[Nazoratchi]]% -> 2500 | AF26: =Таблица32[[#This Row],[Ishga vaqtida kelish nazoratchi]]+Таблица32[[#This Row],[Nazoratchi2]] -> 2500 | AG26: =Таблица32[[#This Row],[Ishga vaqtida kelish ketish2]]+Таблица32[[#This Row],[Gruppa buxgalter4]]+Таблица32[[#This Row],[1C baza3]]+Таблица32[[#This Row],[xatlar4]]+Таблица32[[#This Row],[Belgilangan otchetlar5]] -> 8750 | AH26: =Таблица32[[#This Row],[Ishga kelish bank klient3]]+Таблица32[[#This Row],[Gruppa bank klient 2]] -> 10000
A27: 25 | B27: "WALL STREET ACADEMY" | C27: Maxmuda | D27: Ruslan | E27: 2300000 | F27: Go'zaloy | H27: 1 | J27: 1 | K27: 1 | L27: 0.25 | M27: 0.25 | N27: 0.25 | O27: 1 | P27: 0.25 | Q27: 0.2 | R27: 0.2 | S27: 0.2 | T27: 0.2 | U27: 0.2 | V27: 0.5 | W27: =Таблица32[[#This Row],[Столбец7]]*Таблица32[[#This Row],[Ishga kelish nazoratchi2]]% -> 0 | X27: =Таблица32[[#This Row],[Столбец7]]*Таблица32[[#This Row],[Ishga vaqtida kelish ketish]]% -> 0 | Y27: =Таблица32[[#This Row],[Столбец7]]*Таблица32[[#This Row],[Ishga kelish bank klient]]% -> 23000 | Z27: =Таблица32[[#This Row],[Столбец7]]*Таблица32[[#This Row],[Gruppa buxgalter]]% -> 23000 | AA27: =Таблица32[[#This Row],[Столбец7]]*Таблица32[[#This Row],[Gruppa bank klient ]]% -> 23000 | AB27: =Таблица32[[#This Row],[1c]]*Таблица32[[#This Row],[Столбец7]]/100 -> 23000 | AC27: =SUM(Таблица32[[#This Row],[Didox]:[ мехнат]],Таблица32[[#This Row],[Avtokameral]])*Таблица32[[#This Row],[Столбец7]]/100 -> 23000 | AD27: =SUM(Таблица32[[#This Row],[Pul oqimlari]:[Foyda va zarar]])*Таблица32[[#This Row],[Столбец7]]/100 -> 23000 | AE27: =Таблица32[[#This Row],[Столбец7]]*Таблица32[[#This Row],[Nazoratchi]]% -> 11500 | AF27: =Таблица32[[#This Row],[Ishga vaqtida kelish nazoratchi]]+Таблица32[[#This Row],[Nazoratchi2]] -> 11500 | AG27: =Таблица32[[#This Row],[Ishga vaqtida kelish ketish2]]+Таблица32[[#This Row],[Gruppa buxgalter4]]+Таблица32[[#This Row],[1C baza3]]+Таблица32[[#This Row],[xatlar4]]+Таблица32[[#This Row],[Belgilangan otchetlar5]] -> 92000 | AH27: =Таблица32[[#This Row],[Ishga kelish bank klient3]]+Таблица32[[#This Row],[Gruppa bank klient 2]] -> 46000
A28: 26 | B28: DOMINANT DOMKUR- SIGN OF QUALITY | C28: Otabek | D28: Azizbek | E28: 600000 | F28: Muslimbek | H28: 1 | J28: 1 | K28: 1 | L28: 0.25 | M28: 0.25 | O28: 1 | P28: 0.25 | Q28: 0.2 | R28: 0.2 | S28: 0.2 | T28: 0.2 | U28: 0.2 | V28: 0.5 | W28: =Таблица32[[#This Row],[Столбец7]]*Таблица32[[#This Row],[Ishga kelish nazoratchi2]]% -> 0 | X28: =Таблица32[[#This Row],[Столбец7]]*Таблица32[[#This Row],[Ishga vaqtida kelish ketish]]% -> 0 | Y28: =Таблица32[[#This Row],[Столбец7]]*Таблица32[[#This Row],[Ishga kelish bank klient]]% -> 6000 | Z28: =Таблица32[[#This Row],[Столбец7]]*Таблица32[[#This Row],[Gruppa buxgalter]]% -> 6000 | AA28: =Таблица32[[#This Row],[Столбец7]]*Таблица32[[#This Row],[Gruppa bank klient ]]% -> 6000 | AB28: =Таблица32[[#This Row],[1c]]*Таблица32[[#This Row],[Столбец7]]/100 -> 6000 | AC28: =SUM(Таблица32[[#This Row],[Didox]:[ мехнат]],Таблица32[[#This Row],[Avtokameral]])*Таблица32[[#This Row],[Столбец7]]/100 -> 4500 | AD28: =SUM(Таблица32[[#This Row],[Pul oqimlari]:[Foyda va zarar]])*Таблица32[[#This Row],[Столбец7]]/100 -> 6000 | AE28: =Таблица32[[#This Row],[Столбец7]]*Таблица32[[#This Row],[Nazoratchi]]% -> 3000 | AF28: =Таблица32[[#This Row],[Ishga vaqtida kelish nazoratchi]]+Таблица32[[#This Row],[Nazoratchi2]] -> 3000 | AG28: =Таблица32[[#This Row],[Ishga vaqtida kelish ketish2]]+Таблица32[[#This Row],[Gruppa buxgalter4]]+Таблица32[[#This Row],[1C baza3]]+Таблица32[[#This Row],[xatlar4]]+Таблица32[[#This Row],[Belgilangan otchetlar5]] -> 22500 | AH28: =Таблица32[[#This Row],[Ishga kelish bank klient3]]+Таблица32[[#This Row],[Gruppa bank klient 2]] -> 12000
A29: 27 | B29: LIDER ELITE | C29: Zamira | D29: Azizbek | E29: 2500000 | F29: Go'zaloy | G29: -0.25 | H29: 1 | J29: 1 | K29: 1 | L29: 0.25 | M29: 0.25 | N29: 0.25 | O29: 1 | P29: 0.25 | Q29: 0.2 | R29: 0.2 | S29: 0.2 | T29: 0.2 | U29: 0.2 | V29: 0.5 | W29: =Таблица32[[#This Row],[Столбец7]]*Таблица32[[#This Row],[Ishga kelish nazoratchi2]]% -> 0 | X29: =Таблица32[[#This Row],[Столбец7]]*Таблица32[[#This Row],[Ishga vaqtida kelish ketish]]% -> -6250 | Y29: =Таблица32[[#This Row],[Столбец7]]*Таблица32[[#This Row],[Ishga kelish bank klient]]% -> 25000 | Z29: =Таблица32[[#This Row],[Столбец7]]*Таблица32[[#This Row],[Gruppa buxgalter]]% -> 25000 | AA29: =Таблица32[[#This Row],[Столбец7]]*Таблица32[[#This Row],[Gruppa bank klient ]]% -> 25000 | AB29: =Таблица32[[#This Row],[1c]]*Таблица32[[#This Row],[Столбец7]]/100 -> 25000 | AC29: =SUM(Таблица32[[#This Row],[Didox]:[ мехнат]],Таблица32[[#This Row],[Avtokameral]])*Таблица32[[#This Row],[Столбец7]]/100 -> 25000 | AD29: =SUM(Таблица32[[#This Row],[Pul oqimlari]:[Foyda va zarar]])*Таблица32[[#This Row],[Столбец7]]/100 -> 25000 | AE29: =Таблица32[[#This Row],[Столбец7]]*Таблица32[[#This Row],[Nazoratchi]]% -> 12500 | AF29: =Таблица32[[#This Row],[Ishga vaqtida kelish nazoratchi]]+Таблица32[[#This Row],[Nazoratchi2]] -> 12500 | AG29: =Таблица32[[#This Row],[Ishga vaqtida kelish ketish2]]+Таблица32[[#This Row],[Gruppa buxgalter4]]+Таблица32[[#This Row],[1C baza3]]+Таблица32[[#This Row],[xatlar4]]+Таблица32[[#This Row],[Belgilangan otchetlar5]] -> 93750 | AH29: =Таблица32[[#This Row],[Ishga kelish bank klient3]]+Таблица32[[#This Row],[Gruppa bank klient 2]] -> 50000
A30: 28 | B30: NATURE ECO WOOD MCHJ | C30: Mirabbos | F30: Muslimbek | J30: 1 | L30: 0 | M30: 0 | P30: 0 | Q30: 0 | R30: 0 | S30: 0 | T30: 0 | U30: 0 | V30: 0.5 | W30: =Таблица32[[#This Row],[Столбец7]]*Таблица32[[#This Row],[Ishga kelish nazoratchi2]]% -> 0 | X30: =Таблица32[[#This Row],[Столбец7]]*Таблица32[[#This Row],[Ishga vaqtida kelish ketish]]% -> 0 | Y30: =Таблица32[[#This Row],[Столбец7]]*Таблица32[[#This Row],[Ishga kelish bank klient]]% -> 0 | Z30: =Таблица32[[#This Row],[Столбец7]]*Таблица32[[#This Row],[Gruppa buxgalter]]% -> 0 | AA30: =Таблица32[[#This Row],[Столбец7]]*Таблица32[[#This Row],[Gruppa bank klient ]]% -> 0 | AB30: =Таблица32[[#This Row],[1c]]*Таблица32[[#This Row],[Столбец7]]/100 -> 0 | AC30: =SUM(Таблица32[[#This Row],[Didox]:[ мехнат]],Таблица32[[#This Row],[Avtokameral]])*Таблица32[[#This Row],[Столбец7]]/100 -> 0 | AD30: =SUM(Таблица32[[#This Row],[Pul oqimlari]:[Foyda va zarar]])*Таблица32[[#This Row],[Столбец7]]/100 -> 0 | AE30: =Таблица32[[#This Row],[Столбец7]]*Таблица32[[#This Row],[Nazoratchi]]% -> 0 | AF30: =Таблица32[[#This Row],[Ishga vaqtida kelish nazoratchi]]+Таблица32[[#This Row],[Nazoratchi2]] -> 0 | AG30: =Таблица32[[#This Row],[Ishga vaqtida kelish ketish2]]+Таблица32[[#This Row],[Gruppa buxgalter4]]+Таблица32[[#This Row],[1C baza3]]+Таблица32[[#This Row],[xatlar4]]+Таблица32[[#This Row],[Belgilangan otchetlar5]] -> 0 | AH30: =Таблица32[[#This Row],[Ishga kelish bank klient3]]+Таблица32[[#This Row],[Gruppa bank klient 2]] -> 0
A31: 29 | B31: Wood city 1999 | C31: Mirabbos | F31: Muslimbek | J31: 1 | L31: 0 | M31: 0 | P31: 0 | Q31: 0 | R31: 0 | S31: 0 | T31: 0 | U31: 0 | V31: 0.5 | W31: =Таблица32[[#This Row],[Столбец7]]*Таблица32[[#This Row],[Ishga kelish nazoratchi2]]% -> 0 | X31: =Таблица32[[#This Row],[Столбец7]]*Таблица32[[#This Row],[Ishga vaqtida kelish ketish]]% -> 0 | Y31: =Таблица32[[#This Row],[Столбец7]]*Таблица32[[#This Row],[Ishga kelish bank klient]]% -> 0 | Z31: =Таблица32[[#This Row],[Столбец7]]*Таблица32[[#This Row],[Gruppa buxgalter]]% -> 0 | AA31: =Таблица32[[#This Row],[Столбец7]]*Таблица32[[#This Row],[Gruppa bank klient ]]% -> 0 | AB31: =Таблица32[[#This Row],[1c]]*Таблица32[[#This Row],[Столбец7]]/100 -> 0 | AC31: =SUM(Таблица32[[#This Row],[Didox]:[ мехнат]],Таблица32[[#This Row],[Avtokameral]])*Таблица32[[#This Row],[Столбец7]]/100 -> 0 | AD31: =SUM(Таблица32[[#This Row],[Pul oqimlari]:[Foyda va zarar]])*Таблица32[[#This Row],[Столбец7]]/100 -> 0 | AE31: =Таблица32[[#This Row],[Столбец7]]*Таблица32[[#This Row],[Nazoratchi]]% -> 0 | AF31: =Таблица32[[#This Row],[Ishga vaqtida kelish nazoratchi]]+Таблица32[[#This Row],[Nazoratchi2]] -> 0 | AG31: =Таблица32[[#This Row],[Ishga vaqtida kelish ketish2]]+Таблица32[[#This Row],[Gruppa buxgalter4]]+Таблица32[[#This Row],[1C baza3]]+Таблица32[[#This Row],[xatlar4]]+Таблица32[[#This Row],[Belgilangan otchetlar5]] -> 0 | AH31: =Таблица32[[#This Row],[Ishga kelish bank klient3]]+Таблица32[[#This Row],[Gruppa bank klient 2]] -> 0
A32: 30 | B32: "G-R-A-N-D ELECTRONICS" | C32: Mirabbos | D32: Azizbek | E32: 1000000 | F32: Muslimbek | H32: 1 | J32: 1 | K32: 1 | L32: 0.25 | M32: 0.25 | N32: 0.25 | P32: 0.25 | Q32: -0.2 | R32: 0.2 | S32: -0.2 | T32: -0.2 | U32: -0.2 | V32: 0.5 | W32: =Таблица32[[#This Row],[Столбец7]]*Таблица32[[#This Row],[Ishga kelish nazoratchi2]]% -> 0 | X32: =Таблица32[[#This Row],[Столбец7]]*Таблица32[[#This Row],[Ishga vaqtida kelish ketish]]% -> 0 | Y32: =Таблица32[[#This Row],[Столбец7]]*Таблица32[[#This Row],[Ishga kelish bank klient]]% -> 10000 | Z32: =Таблица32[[#This Row],[Столбец7]]*Таблица32[[#This Row],[Gruppa buxgalter]]% -> 10000 | AA32: =Таблица32[[#This Row],[Столбец7]]*Таблица32[[#This Row],[Gruppa bank klient ]]% -> 10000 | AB32: =Таблица32[[#This Row],[1c]]*Таблица32[[#This Row],[Столбец7]]/100 -> 0 | AC32: =SUM(Таблица32[[#This Row],[Didox]:[ мехнат]],Таблица32[[#This Row],[Avtokameral]])*Таблица32[[#This Row],[Столбец7]]/100 -> 10000 | AD32: =SUM(Таблица32[[#This Row],[Pul oqimlari]:[Foyda va zarar]])*Таблица32[[#This Row],[Столбец7]]/100 -> -6000 | AE32: =Таблица32[[#This Row],[Столбец7]]*Таблица32[[#This Row],[Nazoratchi]]% -> 5000 | AF32: =Таблица32[[#This Row],[Ishga vaqtida kelish nazoratchi]]+Таблица32[[#This Row],[Nazoratchi2]] -> 5000 | AG32: =Таблица32[[#This Row],[Ishga vaqtida kelish ketish2]]+Таблица32[[#This Row],[Gruppa buxgalter4]]+Таблица32[[#This Row],[1C baza3]]+Таблица32[[#This Row],[xatlar4]]+Таблица32[[#This Row],[Belgilangan otchetlar5]] -> 14000 | AH32: =Таблица32[[#This Row],[Ishga kelish bank klient3]]+Таблица32[[#This Row],[Gruppa bank klient 2]] -> 20000
A33: 31 | B33: KIFTI OFTOB SARBONI | C33: Mirabbos | D33: Ruslan | E33: 2000000 | F33: Muslimbek | H33: 1 | J33: 1 | K33: 1 | L33: 0.25 | M33: 0.25 | N33: -0.25 | P33: -0.25 | Q33: 0.2 | R33: 0.2 | S33: 0.2 | T33: 0.2 | U33: 0.2 | V33: 0.5 | W33: =Таблица32[[#This Row],[Столбец7]]*Таблица32[[#This Row],[Ishga kelish nazoratchi2]]% -> 0 | X33: =Таблица32[[#This Row],[Столбец7]]*Таблица32[[#This Row],[Ishga vaqtida kelish ketish]]% -> 0 | Y33: =Таблица32[[#This Row],[Столбец7]]*Таблица32[[#This Row],[Ishga kelish bank klient]]% -> 20000 | Z33: =Таблица32[[#This Row],[Столбец7]]*Таблица32[[#This Row],[Gruppa buxgalter]]% -> 20000 | AA33: =Таблица32[[#This Row],[Столбец7]]*Таблица32[[#This Row],[Gruppa bank klient ]]% -> 20000 | AB33: =Таблица32[[#This Row],[1c]]*Таблица32[[#This Row],[Столбец7]]/100 -> 0 | AC33: =SUM(Таблица32[[#This Row],[Didox]:[ мехнат]],Таблица32[[#This Row],[Avtokameral]])*Таблица32[[#This Row],[Столбец7]]/100 -> 0 | AD33: =SUM(Таблица32[[#This Row],[Pul oqimlari]:[Foyda va zarar]])*Таблица32[[#This Row],[Столбец7]]/100 -> 20000 | AE33: =Таблица32[[#This Row],[Столбец7]]*Таблица32[[#This Row],[Nazoratchi]]% -> 10000 | AF33: =Таблица32[[#This Row],[Ishga vaqtida kelish nazoratchi]]+Таблица32[[#This Row],[Nazoratchi2]] -> 10000 | AG33: =Таблица32[[#This Row],[Ishga vaqtida kelish ketish2]]+Таблица32[[#This Row],[Gruppa buxgalter4]]+Таблица32[[#This Row],[1C baza3]]+Таблица32[[#This Row],[xatlar4]]+Таблица32[[#This Row],[Belgilangan otchetlar5]] -> 40000 | AH33: =Таблица32[[#This Row],[Ishga kelish bank klient3]]+Таблица32[[#This Row],[Gruppa bank klient 2]] -> 40000
A34: 32 | B34: ЧП "MATYUSUF SALAEV" | C34: Humora | D34: Azizbek | E34: 0 | F34: Go'zaloy | G34: -0.35 | H34: 1 | J34: 1 | K34: 1 | L34: 0 | M34: 0 | P34: 0 | Q34: 0 | R34: 0 | S34: 0 | T34: 0 | U34: 0 | V34: 0.5 | W34: =Таблица32[[#This Row],[Столбец7]]*Таблица32[[#This Row],[Ishga kelish nazoratchi2]]% -> 0 | X34: =Таблица32[[#This Row],[Столбец7]]*Таблица32[[#This Row],[Ishga vaqtida kelish ketish]]% -> 0 | Y34: =Таблица32[[#This Row],[Столбец7]]*Таблица32[[#This Row],[Ishga kelish bank klient]]% -> 0 | Z34: =Таблица32[[#This Row],[Столбец7]]*Таблица32[[#This Row],[Gruppa buxgalter]]% -> 0 | AA34: =Таблица32[[#This Row],[Столбец7]]*Таблица32[[#This Row],[Gruppa bank klient ]]% -> 0 | AB34: =Таблица32[[#This Row],[1c]]*Таблица32[[#This Row],[Столбец7]]/100 -> 0 | AC34: =SUM(Таблица32[[#This Row],[Didox]:[ мехнат]],Таблица32[[#This Row],[Avtokameral]])*Таблица32[[#This Row],[Столбец7]]/100 -> 0 | AD34: =SUM(Таблица32[[#This Row],[Pul oqimlari]:[Foyda va zarar]])*Таблица32[[#This Row],[Столбец7]]/100 -> 0 | AE34: =Таблица32[[#This Row],[Столбец7]]*Таблица32[[#This Row],[Nazoratchi]]% -> 0 | AF34: =Таблица32[[#This Row],[Ishga vaqtida kelish nazoratchi]]+Таблица32[[#This Row],[Nazoratchi2]] -> 0 | AG34: =Таблица32[[#This Row],[Ishga vaqtida kelish ketish2]]+Таблица32[[#This Row],[Gruppa buxgalter4]]+Таблица32[[#This Row],[1C baza3]]+Таблица32[[#This Row],[xatlar4]]+Таблица32[[#This Row],[Belgilangan otchetlar5]] -> 0 | AH34: =Таблица32[[#This Row],[Ishga kelish bank klient3]]+Таблица32[[#This Row],[Gruppa bank klient 2]] -> 0
A35: 33 | B35: OOO "MAGISTRAL TRANS QURILISH" | C35: Humora | D35: Ruslan | E35: 3500000 | F35: Go'zaloy | G35: -0.35 | H35: 1 | J35: 1 | K35: 1 | L35: -0.25 | M35: 0.25 | O35: 1 | P35: 0.25 | Q35: 0.2 | R35: 0.2 | S35: 0.2 | T35: 0.2 | U35: 0.2 | V35: 0.5 | W35: =Таблица32[[#This Row],[Столбец7]]*Таблица32[[#This Row],[Ishga kelish nazoratchi2]]% -> 0 | X35: =Таблица32[[#This Row],[Столбец7]]*Таблица32[[#This Row],[Ishga vaqtida kelish ketish]]% -> -12250 | Y35: =Таблица32[[#This Row],[Столбец7]]*Таблица32[[#This Row],[Ishga kelish bank klient]]% -> 35000 | Z35: =Таблица32[[#This Row],[Столбец7]]*Таблица32[[#This Row],[Gruppa buxgalter]]% -> 35000 | AA35: =Таблица32[[#This Row],[Столбец7]]*Таблица32[[#This Row],[Gruppa bank klient ]]% -> 35000 | AB35: =Таблица32[[#This Row],[1c]]*Таблица32[[#This Row],[Столбец7]]/100 -> 35000 | AC35: =SUM(Таблица32[[#This Row],[Didox]:[ мехнат]],Таблица32[[#This Row],[Avtokameral]])*Таблица32[[#This Row],[Столбец7]]/100 -> 8750 | AD35: =SUM(Таблица32[[#This Row],[Pul oqimlari]:[Foyda va zarar]])*Таблица32[[#This Row],[Столбец7]]/100 -> 35000 | AE35: =Таблица32[[#This Row],[Столбец7]]*Таблица32[[#This Row],[Nazoratchi]]% -> 17500 | AF35: =Таблица32[[#This Row],[Ishga vaqtida kelish nazoratchi]]+Таблица32[[#This Row],[Nazoratchi2]] -> 17500 | AG35: =Таблица32[[#This Row],[Ishga vaqtida kelish ketish2]]+Таблица32[[#This Row],[Gruppa buxgalter4]]+Таблица32[[#This Row],[1C baza3]]+Таблица32[[#This Row],[xatlar4]]+Таблица32[[#This Row],[Belgilangan otchetlar5]] -> 101500 | AH35: =Таблица32[[#This Row],[Ishga kelish bank klient3]]+Таблица32[[#This Row],[Gruppa bank klient 2]] -> 70000
A36: 34 | B36: "SHIRIN LYUKS TAOM" 01.09.2021 | C36: Musobek | E36: 0 | F36: Go'zaloy | G36: 0.9 | J36: 1 | L36: 0 | M36: 0 | P36: 0 | Q36: 0 | R36: 0 | S36: 0 | T36: 0 | U36: 0 | V36: 0.5 | W36: =Таблица32[[#This Row],[Столбец7]]*Таблица32[[#This Row],[Ishga kelish nazoratchi2]]% -> 0 | X36: =Таблица32[[#This Row],[Столбец7]]*Таблица32[[#This Row],[Ishga vaqtida kelish ketish]]% -> 0 | Y36: =Таблица32[[#This Row],[Столбец7]]*Таблица32[[#This Row],[Ishga kelish bank klient]]% -> 0 | Z36: =Таблица32[[#This Row],[Столбец7]]*Таблица32[[#This Row],[Gruppa buxgalter]]% -> 0 | AA36: =Таблица32[[#This Row],[Столбец7]]*Таблица32[[#This Row],[Gruppa bank klient ]]% -> 0 | AB36: =Таблица32[[#This Row],[1c]]*Таблица32[[#This Row],[Столбец7]]/100 -> 0 | AC36: =SUM(Таблица32[[#This Row],[Didox]:[ мехнат]],Таблица32[[#This Row],[Avtokameral]])*Таблица32[[#This Row],[Столбец7]]/100 -> 0 | AD36: =SUM(Таблица32[[#This Row],[Pul oqimlari]:[Foyda va zarar]])*Таблица32[[#This Row],[Столбец7]]/100 -> 0 | AE36: =Таблица32[[#This Row],[Столбец7]]*Таблица32[[#This Row],[Nazoratchi]]% -> 0 | AF36: =Таблица32[[#This Row],[Ishga vaqtida kelish nazoratchi]]+Таблица32[[#This Row],[Nazoratchi2]] -> 0 | AG36: =Таблица32[[#This Row],[Ishga vaqtida kelish ketish2]]+Таблица32[[#This Row],[Gruppa buxgalter4]]+Таблица32[[#This Row],[1C baza3]]+Таблица32[[#This Row],[xatlar4]]+Таблица32[[#This Row],[Belgilangan otchetlar5]] -> 0 | AH36: =Таблица32[[#This Row],[Ishga kelish bank klient3]]+Таблица32[[#This Row],[Gruppa bank klient 2]] -> 0
A37: 35 | B37: BY ETIKETKA | C37: Abrorbek | D37: Azizbek | E37: 1500000 | F37: Go'zaloy | H37: 1 | J37: 1 | K37: 1 | L37: -0.25 | M37: -0.25 | P37: 0.25 | Q37: 0 | R37: 0.2 | S37: 0.2 | T37: 0.2 | U37: 0.2 | V37: 0.5 | W37: =Таблица32[[#This Row],[Столбец7]]*Таблица32[[#This Row],[Ishga kelish nazoratchi2]]% -> 0 | X37: =Таблица32[[#This Row],[Столбец7]]*Таблица32[[#This Row],[Ishga vaqtida kelish ketish]]% -> 0 | Y37: =Таблица32[[#This Row],[Столбец7]]*Таблица32[[#This Row],[Ishga kelish bank klient]]% -> 15000 | Z37: =Таблица32[[#This Row],[Столбец7]]*Таблица32[[#This Row],[Gruppa buxgalter]]% -> 15000 | AA37: =Таблица32[[#This Row],[Столбец7]]*Таблица32[[#This Row],[Gruppa bank klient ]]% -> 15000 | AB37: =Таблица32[[#This Row],[1c]]*Таблица32[[#This Row],[Столбец7]]/100 -> 0 | AC37: =SUM(Таблица32[[#This Row],[Didox]:[ мехнат]],Таблица32[[#This Row],[Avtokameral]])*Таблица32[[#This Row],[Столбец7]]/100 -> -3750 | AD37: =SUM(Таблица32[[#This Row],[Pul oqimlari]:[Foyda va zarar]])*Таблица32[[#This Row],[Столбец7]]/100 -> 12000 | AE37: =Таблица32[[#This Row],[Столбец7]]*Таблица32[[#This Row],[Nazoratchi]]% -> 7500 | AF37: =Таблица32[[#This Row],[Ishga vaqtida kelish nazoratchi]]+Таблица32[[#This Row],[Nazoratchi2]] -> 7500 | AG37: =Таблица32[[#This Row],[Ishga vaqtida kelish ketish2]]+Таблица32[[#This Row],[Gruppa buxgalter4]]+Таблица32[[#This Row],[1C baza3]]+Таблица32[[#This Row],[xatlar4]]+Таблица32[[#This Row],[Belgilangan otchetlar5]] -> 23250 | AH37: =Таблица32[[#This Row],[Ishga kelish bank klient3]]+Таблица32[[#This Row],[Gruppa bank klient 2]] -> 30000
A38: 36 | B38: IN VITRO PLANTS | C38: Mirabbos | D38: Azizbek | E38: 2000000 | F38: Muslimbek | H38: 1 | J38: 1 | K38: 1 | L38: 0.25 | M38: 0.25 | N38: 0.25 | P38: 0.25 | Q38: -0.2 | R38: -0.2 | S38: -0.2 | T38: -0.2 | U38: -0.2 | V38: 0.5 | W38: =Таблица32[[#This Row],[Столбец7]]*Таблица32[[#This Row],[Ishga kelish nazoratchi2]]% -> 0 | X38: =Таблица32[[#This Row],[Столбец7]]*Таблица32[[#This Row],[Ishga vaqtida kelish ketish]]% -> 0 | Y38: =Таблица32[[#This Row],[Столбец7]]*Таблица32[[#This Row],[Ishga kelish bank klient]]% -> 20000 | Z38: =Таблица32[[#This Row],[Столбец7]]*Таблица32[[#This Row],[Gruppa buxgalter]]% -> 20000 | AA38: =Таблица32[[#This Row],[Столбец7]]*Таблица32[[#This Row],[Gruppa bank klient ]]% -> 20000 | AB38: =Таблица32[[#This Row],[1c]]*Таблица32[[#This Row],[Столбец7]]/100 -> 0 | AC38: =SUM(Таблица32[[#This Row],[Didox]:[ мехнат]],Таблица32[[#This Row],[Avtokameral]])*Таблица32[[#This Row],[Столбец7]]/100 -> 20000 | AD38: =SUM(Таблица32[[#This Row],[Pul oqimlari]:[Foyda va zarar]])*Таблица32[[#This Row],[Столбец7]]/100 -> -20000 | AE38: =Таблица32[[#This Row],[Столбец7]]*Таблица32[[#This Row],[Nazoratchi]]% -> 10000 | AF38: =Таблица32[[#This Row],[Ishga vaqtida kelish nazoratchi]]+Таблица32[[#This Row],[Nazoratchi2]] -> 10000 | AG38: =Таблица32[[#This Row],[Ishga vaqtida kelish ketish2]]+Таблица32[[#This Row],[Gruppa buxgalter4]]+Таблица32[[#This Row],[1C baza3]]+Таблица32[[#This Row],[xatlar4]]+Таблица32[[#This Row],[Belgilangan otchetlar5]] -> 20000 | AH38: =Таблица32[[#This Row],[Ishga kelish bank klient3]]+Таблица32[[#This Row],[Gruppa bank klient 2]] -> 40000
A39: 37 | B39: ООО "BASKETBALL ACADEMY" | C39: Otabek | D39: Ruslan | E39: 700000 | F39: Muslimbek | H39: 1 | J39: 1 | K39: 1 | L39: 0.25 | M39: 0.25 | O39: 1 | P39: 0.25 | Q39: 0.2 | R39: 0.2 | S39: 0.2 | T39: 0.2 | U39: 0.2 | V39: 0.5 | W39: =Таблица32[[#This Row],[Столбец7]]*Таблица32[[#This Row],[Ishga kelish nazoratchi2]]% -> 0 | X39: =Таблица32[[#This Row],[Столбец7]]*Таблица32[[#This Row],[Ishga vaqtida kelish ketish]]% -> 0 | Y39: =Таблица32[[#This Row],[Столбец7]]*Таблица32[[#This Row],[Ishga kelish bank klient]]% -> 7000 | Z39: =Таблица32[[#This Row],[Столбец7]]*Таблица32[[#This Row],[Gruppa buxgalter]]% -> 7000 | AA39: =Таблица32[[#This Row],[Столбец7]]*Таблица32[[#This Row],[Gruppa bank klient ]]% -> 7000 | AB39: =Таблица32[[#This Row],[1c]]*Таблица32[[#This Row],[Столбец7]]/100 -> 7000 | AC39: =SUM(Таблица32[[#This Row],[Didox]:[ мехнат]],Таблица32[[#This Row],[Avtokameral]])*Таблица32[[#This Row],[Столбец7]]/100 -> 5250 | AD39: =SUM(Таблица32[[#This Row],[Pul oqimlari]:[Foyda va zarar]])*Таблица32[[#This Row],[Столбец7]]/100 -> 7000 | AE39: =Таблица32[[#This Row],[Столбец7]]*Таблица32[[#This Row],[Nazoratchi]]% -> 3500 | AF39: =Таблица32[[#This Row],[Ishga vaqtida kelish nazoratchi]]+Таблица32[[#This Row],[Nazoratchi2]] -> 3500 | AG39: =Таблица32[[#This Row],[Ishga vaqtida kelish ketish2]]+Таблица32[[#This Row],[Gruppa buxgalter4]]+Таблица32[[#This Row],[1C baza3]]+Таблица32[[#This Row],[xatlar4]]+Таблица32[[#This Row],[Belgilangan otchetlar5]] -> 26250 | AH39: =Таблица32[[#This Row],[Ishga kelish bank klient3]]+Таблица32[[#This Row],[Gruppa bank klient 2]] -> 14000
A40: 38 | B40: "KESH LOGIST" | C40: Otabek | D40: Ruslan | E40: 500000 | F40: Muslimbek | H40: 1 | J40: 1 | K40: 1 | L40: 0.25 | M40: 0.25 | P40: 0.25 | Q40: 0 | R40: 0 | S40: 0 | T40: 0 | U40: 0 | V40: 0.5 | W40: =Таблица32[[#This Row],[Столбец7]]*Таблица32[[#This Row],[Ishga kelish nazoratchi2]]% -> 0 | X40: =Таблица32[[#This Row],[Столбец7]]*Таблица32[[#This Row],[Ishga vaqtida kelish ketish]]% -> 0 | Y40: =Таблица32[[#This Row],[Столбец7]]*Таблица32[[#This Row],[Ishga kelish bank klient]]% -> 5000 | Z40: =Таблица32[[#This Row],[Столбец7]]*Таблица32[[#This Row],[Gruppa buxgalter]]% -> 5000 | AA40: =Таблица32[[#This Row],[Столбец7]]*Таблица32[[#This Row],[Gruppa bank klient ]]% -> 5000 | AB40: =Таблица32[[#This Row],[1c]]*Таблица32[[#This Row],[Столбец7]]/100 -> 0 | AC40: =SUM(Таблица32[[#This Row],[Didox]:[ мехнат]],Таблица32[[#This Row],[Avtokameral]])*Таблица32[[#This Row],[Столбец7]]/100 -> 3750 | AD40: =SUM(Таблица32[[#This Row],[Pul oqimlari]:[Foyda va zarar]])*Таблица32[[#This Row],[Столбец7]]/100 -> 0 | AE40: =Таблица32[[#This Row],[Столбец7]]*Таблица32[[#This Row],[Nazoratchi]]% -> 2500 | AF40: =Таблица32[[#This Row],[Ishga vaqtida kelish nazoratchi]]+Таблица32[[#This Row],[Nazoratchi2]] -> 2500 | AG40: =Таблица32[[#This Row],[Ishga vaqtida kelish ketish2]]+Таблица32[[#This Row],[Gruppa buxgalter4]]+Таблица32[[#This Row],[1C baza3]]+Таблица32[[#This Row],[xatlar4]]+Таблица32[[#This Row],[Belgilangan otchetlar5]] -> 8750 | AH40: =Таблица32[[#This Row],[Ishga kelish bank klient3]]+Таблица32[[#This Row],[Gruppa bank klient 2]] -> 10000
A41: 39 | B41: "GITA DASTURCHILAR AKADEMIYASI" MCHJ | C41: Dilhush | D41: Azizbek | E41: 1000000 | F41: Go'zaloy | H41: 1 | J41: 1 | K41: 1 | L41: 0.25 | M41: 0.25 | O41: 1 | P41: 0.25 | Q41: 0.2 | R41: 0.2 | S41: 0.2 | T41: -0.2 | U41: -0.2 | V41: 0.5 | W41: =Таблица32[[#This Row],[Столбец7]]*Таблица32[[#This Row],[Ishga kelish nazoratchi2]]% -> 0 | X41: =Таблица32[[#This Row],[Столбец7]]*Таблица32[[#This Row],[Ishga vaqtida kelish ketish]]% -> 0 | Y41: =Таблица32[[#This Row],[Столбец7]]*Таблица32[[#This Row],[Ishga kelish bank klient]]% -> 10000 | Z41: =Таблица32[[#This Row],[Столбец7]]*Таблица32[[#This Row],[Gruppa buxgalter]]% -> 10000 | AA41: =Таблица32[[#This Row],[Столбец7]]*Таблица32[[#This Row],[Gruppa bank klient ]]% -> 10000 | AB41: =Таблица32[[#This Row],[1c]]*Таблица32[[#This Row],[Столбец7]]/100 -> 10000 | AC41: =SUM(Таблица32[[#This Row],[Didox]:[ мехнат]],Таблица32[[#This Row],[Avtokameral]])*Таблица32[[#This Row],[Столбец7]]/100 -> 7500 | AD41: =SUM(Таблица32[[#This Row],[Pul oqimlari]:[Foyda va zarar]])*Таблица32[[#This Row],[Столбец7]]/100 -> 2000 | AE41: =Таблица32[[#This Row],[Столбец7]]*Таблица32[[#This Row],[Nazoratchi]]% -> 5000 | AF41: =Таблица32[[#This Row],[Ishga vaqtida kelish nazoratchi]]+Таблица32[[#This Row],[Nazoratchi2]] -> 5000 | AG41: =Таблица32[[#This Row],[Ishga vaqtida kelish ketish2]]+Таблица32[[#This Row],[Gruppa buxgalter4]]+Таблица32[[#This Row],[1C baza3]]+Таблица32[[#This Row],[xatlar4]]+Таблица32[[#This Row],[Belgilangan otchetlar5]] -> 29500 | AH41: =Таблица32[[#This Row],[Ishga kelish bank klient3]]+Таблица32[[#This Row],[Gruppa bank klient 2]] -> 20000
A42: 40 | B42: "JS MUROTOV" АДВОКАТЛИК БЮРОСИ" | C42: Maxmuda | D42: Azizbek | E42: 800000 | F42: Go'zaloy | H42: 1 | J42: 1 | K42: 1 | L42: 0.25 | M42: 0.25 | N42: 0.25 | O42: 1 | P42: 0.25 | Q42: 0.2 | R42: 0.2 | S42: 0.2 | T42: 0.2 | U42: 0 | V42: 0.5 | W42: =Таблица32[[#This Row],[Столбец7]]*Таблица32[[#This Row],[Ishga kelish nazoratchi2]]% -> 0 | X42: =Таблица32[[#This Row],[Столбец7]]*Таблица32[[#This Row],[Ishga vaqtida kelish ketish]]% -> 0 | Y42: =Таблица32[[#This Row],[Столбец7]]*Таблица32[[#This Row],[Ishga kelish bank klient]]% -> 8000 | Z42: =Таблица32[[#This Row],[Столбец7]]*Таблица32[[#This Row],[Gruppa buxgalter]]% -> 8000 | AA42: =Таблица32[[#This Row],[Столбец7]]*Таблица32[[#This Row],[Gruppa bank klient ]]% -> 8000 | AB42: =Таблица32[[#This Row],[1c]]*Таблица32[[#This Row],[Столбец7]]/100 -> 8000 | AC42: =SUM(Таблица32[[#This Row],[Didox]:[ мехнат]],Таблица32[[#This Row],[Avtokameral]])*Таблица32[[#This Row],[Столбец7]]/100 -> 8000 | AD42: =SUM(Таблица32[[#This Row],[Pul oqimlari]:[Foyda va zarar]])*Таблица32[[#This Row],[Столбец7]]/100 -> 6400 | AE42: =Таблица32[[#This Row],[Столбец7]]*Таблица32[[#This Row],[Nazoratchi]]% -> 4000 | AF42: =Таблица32[[#This Row],[Ishga vaqtida kelish nazoratchi]]+Таблица32[[#This Row],[Nazoratchi2]] -> 4000 | AG42: =Таблица32[[#This Row],[Ishga vaqtida kelish ketish2]]+Таблица32[[#This Row],[Gruppa buxgalter4]]+Таблица32[[#This Row],[1C baza3]]+Таблица32[[#This Row],[xatlar4]]+Таблица32[[#This Row],[Belgilangan otchetlar5]] -> 30400 | AH42: =Таблица32[[#This Row],[Ishga kelish bank klient3]]+Таблица32[[#This Row],[Gruppa bank klient 2]] -> 16000
A43: 41 | B43: VMM RELIABLE LEGAL PROTECTION | C43: Maxmuda | D43: Azizbek | E43: 500000 | F43: Go'zaloy | H43: 1 | J43: 1 | K43: 1 | L43: 0.25 | M43: 0.25 | N43: 0.25 | O43: 1 | P43: 0.25 | Q43: 0.2 | R43: 0.2 | S43: 0.2 | T43: 0.2 | U43: 0 | V43: 0.5 | W43: =Таблица32[[#This Row],[Столбец7]]*Таблица32[[#This Row],[Ishga kelish nazoratchi2]]% -> 0 | X43: =Таблица32[[#This Row],[Столбец7]]*Таблица32[[#This Row],[Ishga vaqtida kelish ketish]]% -> 0 | Y43: =Таблица32[[#This Row],[Столбец7]]*Таблица32[[#This Row],[Ishga kelish bank klient]]% -> 5000 | Z43: =Таблица32[[#This Row],[Столбец7]]*Таблица32[[#This Row],[Gruppa buxgalter]]% -> 5000 | AA43: =Таблица32[[#This Row],[Столбец7]]*Таблица32[[#This Row],[Gruppa bank klient ]]% -> 5000 | AB43: =Таблица32[[#This Row],[1c]]*Таблица32[[#This Row],[Столбец7]]/100 -> 5000 | AC43: =SUM(Таблица32[[#This Row],[Didox]:[ мехнат]],Таблица32[[#This Row],[Avtokameral]])*Таблица32[[#This Row],[Столбец7]]/100 -> 5000 | AD43: =SUM(Таблица32[[#This Row],[Pul oqimlari]:[Foyda va zarar]])*Таблица32[[#This Row],[Столбец7]]/100 -> 4000 | AE43: =Таблица32[[#This Row],[Столбец7]]*Таблица32[[#This Row],[Nazoratchi]]% -> 2500 | AF43: =Таблица32[[#This Row],[Ishga vaqtida kelish nazoratchi]]+Таблица32[[#This Row],[Nazoratchi2]] -> 2500 | AG43: =Таблица32[[#This Row],[Ishga vaqtida kelish ketish2]]+Таблица32[[#This Row],[Gruppa buxgalter4]]+Таблица32[[#This Row],[1C baza3]]+Таблица32[[#This Row],[xatlar4]]+Таблица32[[#This Row],[Belgilangan otchetlar5]] -> 19000 | AH43: =Таблица32[[#This Row],[Ishga kelish bank klient3]]+Таблица32[[#This Row],[Gruppa bank klient 2]] -> 10000
A44: 42 | B44: "RUSLAN GRAND " | C44: Javohir | D44: Ruslan | E44: 1500000 | F44: Muslimbek | G44: -0.05 | H44: 1 | J44: 1 | K44: 1 | L44: 0.25 | M44: 0.25 | P44: 0.25 | Q44: -0.2 | R44: 0.2 | S44: -0.2 | T44: -0.2 | U44: -0.2 | V44: 0.5 | W44: =Таблица32[[#This Row],[Столбец7]]*Таблица32[[#This Row],[Ishga kelish nazoratchi2]]% -> 0 | X44: =Таблица32[[#This Row],[Столбец7]]*Таблица32[[#This Row],[Ishga vaqtida kelish ketish]]% -> -750 | Y44: =Таблица32[[#This Row],[Столбец7]]*Таблица32[[#This Row],[Ishga kelish bank klient]]% -> 15000 | Z44: =Таблица32[[#This Row],[Столбец7]]*Таблица32[[#This Row],[Gruppa buxgalter]]% -> 15000 | AA44: =Таблица32[[#This Row],[Столбец7]]*Таблица32[[#This Row],[Gruppa bank klient ]]% -> 15000 | AB44: =Таблица32[[#This Row],[1c]]*Таблица32[[#This Row],[Столбец7]]/100 -> 0 | AC44: =SUM(Таблица32[[#This Row],[Didox]:[ мехнат]],Таблица32[[#This Row],[Avtokameral]])*Таблица32[[#This Row],[Столбец7]]/100 -> 11250 | AD44: =SUM(Таблица32[[#This Row],[Pul oqimlari]:[Foyda va zarar]])*Таблица32[[#This Row],[Столбец7]]/100 -> -9000 | AE44: =Таблица32[[#This Row],[Столбец7]]*Таблица32[[#This Row],[Nazoratchi]]% -> 7500 | AF44: =Таблица32[[#This Row],[Ishga vaqtida kelish nazoratchi]]+Таблица32[[#This Row],[Nazoratchi2]] -> 7500 | AG44: =Таблица32[[#This Row],[Ishga vaqtida kelish ketish2]]+Таблица32[[#This Row],[Gruppa buxgalter4]]+Таблица32[[#This Row],[1C baza3]]+Таблица32[[#This Row],[xatlar4]]+Таблица32[[#This Row],[Belgilangan otchetlar5]] -> 16500 | AH44: =Таблица32[[#This Row],[Ishga kelish bank klient3]]+Таблица32[[#This Row],[Gruppa bank klient 2]] -> 30000
A45: 43 | B45: ЧП "CHIRCHIQ SAHOVAT" | C45: Ruslan | D45: Ruslan | E45: 400000 | F45: Go'zaloy | H45: 1 | K45: 1 | L45: -0.25 | M45: 0.25 | P45: 0.25 | Q45: 0 | R45: 0 | S45: 0 | T45: 0 | U45: 0 | W45: =Таблица32[[#This Row],[Столбец7]]*Таблица32[[#This Row],[Ishga kelish nazoratchi2]]% -> 0 | X45: =Таблица32[[#This Row],[Столбец7]]*Таблица32[[#This Row],[Ishga vaqtida kelish ketish]]% -> 0 | Y45: =Таблица32[[#This Row],[Столбец7]]*Таблица32[[#This Row],[Ishga kelish bank klient]]% -> 4000 | Z45: =Таблица32[[#This Row],[Столбец7]]*Таблица32[[#This Row],[Gruppa buxgalter]]% -> 0 | AA45: =Таблица32[[#This Row],[Столбец7]]*Таблица32[[#This Row],[Gruppa bank klient ]]% -> 4000 | AB45: =Таблица32[[#This Row],[1c]]*Таблица32[[#This Row],[Столбец7]]/100 -> 0 | AC45: =SUM(Таблица32[[#This Row],[Didox]:[ мехнат]],Таблица32[[#This Row],[Avtokameral]])*Таблица32[[#This Row],[Столбец7]]/100 -> 1000 | AD45: =SUM(Таблица32[[#This Row],[Pul oqimlari]:[Foyda va zarar]])*Таблица32[[#This Row],[Столбец7]]/100 -> 0 | AE45: =Таблица32[[#This Row],[Столбец7]]*Таблица32[[#This Row],[Nazoratchi]]% -> 0 | AF45: =Таблица32[[#This Row],[Ishga vaqtida kelish nazoratchi]]+Таблица32[[#This Row],[Nazoratchi2]] -> 0 | AG45: =Таблица32[[#This Row],[Ishga vaqtida kelish ketish2]]+Таблица32[[#This Row],[Gruppa buxgalter4]]+Таблица32[[#This Row],[1C baza3]]+Таблица32[[#This Row],[xatlar4]]+Таблица32[[#This Row],[Belgilangan otchetlar5]] -> 1000 | AH45: =Таблица32[[#This Row],[Ishga kelish bank klient3]]+Таблица32[[#This Row],[Gruppa bank klient 2]] -> 8000
A46: 44 | B46: "JT INVESTMENT HUB" | C46: Maxmuda | D46: Azizbek | E46: 2000000 | F46: Go'zaloy | H46: 1 | J46: 1 | K46: 1 | L46: 0.25 | M46: 0.25 | N46: 0.25 | P46: 0.25 | Q46: -0.2 | R46: 0.2 | S46: 0.2 | T46: -0.2 | U46: -0.2 | V46: 0.5 | W46: =Таблица32[[#This Row],[Столбец7]]*Таблица32[[#This Row],[Ishga kelish nazoratchi2]]% -> 0 | X46: =Таблица32[[#This Row],[Столбец7]]*Таблица32[[#This Row],[Ishga vaqtida kelish ketish]]% -> 0 | Y46: =Таблица32[[#This Row],[Столбец7]]*Таблица32[[#This Row],[Ishga kelish bank klient]]% -> 20000 | Z46: =Таблица32[[#This Row],[Столбец7]]*Таблица32[[#This Row],[Gruppa buxgalter]]% -> 20000 | AA46: =Таблица32[[#This Row],[Столбец7]]*Таблица32[[#This Row],[Gruppa bank klient ]]% -> 20000 | AB46: =Таблица32[[#This Row],[1c]]*Таблица32[[#This Row],[Столбец7]]/100 -> 0 | AC46: =SUM(Таблица32[[#This Row],[Didox]:[ мехнат]],Таблица32[[#This Row],[Avtokameral]])*Таблица32[[#This Row],[Столбец7]]/100 -> 20000 | AD46: =SUM(Таблица32[[#This Row],[Pul oqimlari]:[Foyda va zarar]])*Таблица32[[#This Row],[Столбец7]]/100 -> -4000 | AE46: =Таблица32[[#This Row],[Столбец7]]*Таблица32[[#This Row],[Nazoratchi]]% -> 10000 | AF46: =Таблица32[[#This Row],[Ishga vaqtida kelish nazoratchi]]+Таблица32[[#This Row],[Nazoratchi2]] -> 10000 | AG46: =Таблица32[[#This Row],[Ishga vaqtida kelish ketish2]]+Таблица32[[#This Row],[Gruppa buxgalter4]]+Таблица32[[#This Row],[1C baza3]]+Таблица32[[#This Row],[xatlar4]]+Таблица32[[#This Row],[Belgilangan otchetlar5]] -> 36000 | AH46: =Таблица32[[#This Row],[Ishga kelish bank klient3]]+Таблица32[[#This Row],[Gruppa bank klient 2]] -> 40000
A47: 45 | B47: "AMIRBEK-RUXSHONA PHARM" XK | C47: Zamira | E47: 4000000 | F47: Go'zaloy | G47: -0.25 | J47: 1 | L47: 0.25 | M47: 0.25 | N47: 0.25 | O47: 1 | P47: -0.25 | Q47: 0.2 | R47: 0.2 | S47: 0.2 | T47: -0.2 | U47: -0.2 | V47: 0.5 | W47: =Таблица32[[#This Row],[Столбец7]]*Таблица32[[#This Row],[Ishga kelish nazoratchi2]]% -> 0 | X47: =Таблица32[[#This Row],[Столбец7]]*Таблица32[[#This Row],[Ishga vaqtida kelish ketish]]% -> -10000 | Y47: =Таблица32[[#This Row],[Столбец7]]*Таблица32[[#This Row],[Ishga kelish bank klient]]% -> 0 | Z47: =Таблица32[[#This Row],[Столбец7]]*Таблица32[[#This Row],[Gruppa buxgalter]]% -> 40000 | AA47: =Таблица32[[#This Row],[Столбец7]]*Таблица32[[#This Row],[Gruppa bank klient ]]% -> 0 | AB47: =Таблица32[[#This Row],[1c]]*Таблица32[[#This Row],[Столбец7]]/100 -> 40000 | AC47: =SUM(Таблица32[[#This Row],[Didox]:[ мехнат]],Таблица32[[#This Row],[Avtokameral]])*Таблица32[[#This Row],[Столбец7]]/100 -> 20000 | AD47: =SUM(Таблица32[[#This Row],[Pul oqimlari]:[Foyda va zarar]])*Таблица32[[#This Row],[Столбец7]]/100 -> 8000 | AE47: =Таблица32[[#This Row],[Столбец7]]*Таблица32[[#This Row],[Nazoratchi]]% -> 20000 | AF47: =Таблица32[[#This Row],[Ishga vaqtida kelish nazoratchi]]+Таблица32[[#This Row],[Nazoratchi2]] -> 20000 | AG47: =Таблица32[[#This Row],[Ishga vaqtida kelish ketish2]]+Таблица32[[#This Row],[Gruppa buxgalter4]]+Таблица32[[#This Row],[1C baza3]]+Таблица32[[#This Row],[xatlar4]]+Таблица32[[#This Row],[Belgilangan otchetlar5]] -> 98000 | AH47: =Таблица32[[#This Row],[Ishga kelish bank klient3]]+Таблица32[[#This Row],[Gruppa bank klient 2]] -> 0
A48: 46 | B48: "XASANOV SABIRJAN LASHOVICH" AB | C48: Dilhush | D48: Azizbek | E48: 700000 | F48: Go'zaloy | H48: 1 | J48: 1 | K48: 1 | L48: 0.25 | M48: 0.25 | O48: 1 | P48: 0.25 | Q48: 0.2 | R48: 0.2 | S48: -0.2 | T48: -0.2 | U48: -0.2 | V48: 0.5 | W48: =Таблица32[[#This Row],[Столбец7]]*Таблица32[[#This Row],[Ishga kelish nazoratchi2]]% -> 0 | X48: =Таблица32[[#This Row],[Столбец7]]*Таблица32[[#This Row],[Ishga vaqtida kelish ketish]]% -> 0 | Y48: =Таблица32[[#This Row],[Столбец7]]*Таблица32[[#This Row],[Ishga kelish bank klient]]% -> 7000 | Z48: =Таблица32[[#This Row],[Столбец7]]*Таблица32[[#This Row],[Gruppa buxgalter]]% -> 7000 | AA48: =Таблица32[[#This Row],[Столбец7]]*Таблица32[[#This Row],[Gruppa bank klient ]]% -> 7000 | AB48: =Таблица32[[#This Row],[1c]]*Таблица32[[#This Row],[Столбец7]]/100 -> 7000 | AC48: =SUM(Таблица32[[#This Row],[Didox]:[ мехнат]],Таблица32[[#This Row],[Avtokameral]])*Таблица32[[#This Row],[Столбец7]]/100 -> 5250 | AD48: =SUM(Таблица32[[#This Row],[Pul oqimlari]:[Foyda va zarar]])*Таблица32[[#This Row],[Столбец7]]/100 -> -1400 | AE48: =Таблица32[[#This Row],[Столбец7]]*Таблица32[[#This Row],[Nazoratchi]]% -> 3500 | AF48: =Таблица32[[#This Row],[Ishga vaqtida kelish nazoratchi]]+Таблица32[[#This Row],[Nazoratchi2]] -> 3500 | AG48: =Таблица32[[#This Row],[Ishga vaqtida kelish ketish2]]+Таблица32[[#This Row],[Gruppa buxgalter4]]+Таблица32[[#This Row],[1C baza3]]+Таблица32[[#This Row],[xatlar4]]+Таблица32[[#This Row],[Belgilangan otchetlar5]] -> 17850 | AH48: =Таблица32[[#This Row],[Ishga kelish bank klient3]]+Таблица32[[#This Row],[Gruppa bank klient 2]] -> 14000
A49: 47 | B49: HAPPY CLEAN MChJ | C49: Dilhush | D49: Azizbek | E49: 1000000 | F49: Go'zaloy | H49: 1 | J49: 1 | K49: 1 | L49: 0.25 | M49: 0.25 | O49: 1 | P49: 0.25 | Q49: 0 | R49: 0.2 | S49: 0.2 | T49: 0 | U49: 0 | V49: 0.5 | W49: =Таблица32[[#This Row],[Столбец7]]*Таблица32[[#This Row],[Ishga kelish nazoratchi2]]% -> 0 | X49: =Таблица32[[#This Row],[Столбец7]]*Таблица32[[#This Row],[Ishga vaqtida kelish ketish]]% -> 0 | Y49: =Таблица32[[#This Row],[Столбец7]]*Таблица32[[#This Row],[Ishga kelish bank klient]]% -> 10000 | Z49: =Таблица32[[#This Row],[Столбец7]]*Таблица32[[#This Row],[Gruppa buxgalter]]% -> 10000 | AA49: =Таблица32[[#This Row],[Столбец7]]*Таблица32[[#This Row],[Gruppa bank klient ]]% -> 10000 | AB49: =Таблица32[[#This Row],[1c]]*Таблица32[[#This Row],[Столбец7]]/100 -> 10000 | AC49: =SUM(Таблица32[[#This Row],[Didox]:[ мехнат]],Таблица32[[#This Row],[Avtokameral]])*Таблица32[[#This Row],[Столбец7]]/100 -> 7500 | AD49: =SUM(Таблица32[[#This Row],[Pul oqimlari]:[Foyda va zarar]])*Таблица32[[#This Row],[Столбец7]]/100 -> 4000 | AE49: =Таблица32[[#This Row],[Столбец7]]*Таблица32[[#This Row],[Nazoratchi]]% -> 5000 | AF49: =Таблица32[[#This Row],[Ishga vaqtida kelish nazoratchi]]+Таблица32[[#This Row],[Nazoratchi2]] -> 5000 | AG49: =Таблица32[[#This Row],[Ishga vaqtida kelish ketish2]]+Таблица32[[#This Row],[Gruppa buxgalter4]]+Таблица32[[#This Row],[1C baza3]]+Таблица32[[#This Row],[xatlar4]]+Таблица32[[#This Row],[Belgilangan otchetlar5]] -> 31500 | AH49: =Таблица32[[#This Row],[Ishga kelish bank klient3]]+Таблица32[[#This Row],[Gruppa bank klient 2]] -> 20000
A50: 48 | B50: ООО "HIGH-TECH GROUP" | C50: Maxmuda | E50: 3000000 | F50: Go'zaloy | J50: -1 | L50: 0.25 | M50: 0.25 | N50: 0.25 | O50: 1 | P50: 0.25 | Q50: 0.2 | R50: 0.2 | S50: 0.2 | T50: 0.2 | U50: 0.2 | V50: -1 | W50: =Таблица32[[#This Row],[Столбец7]]*Таблица32[[#This Row],[Ishga kelish nazoratchi2]]% -> 0 | X50: =Таблица32[[#This Row],[Столбец7]]*Таблица32[[#This Row],[Ishga vaqtida kelish ketish]]% -> 0 | Y50: =Таблица32[[#This Row],[Столбец7]]*Таблица32[[#This Row],[Ishga kelish bank klient]]% -> 0 | Z50: =Таблица32[[#This Row],[Столбец7]]*Таблица32[[#This Row],[Gruppa buxgalter]]% -> -30000 | AA50: =Таблица32[[#This Row],[Столбец7]]*Таблица32[[#This Row],[Gruppa bank klient ]]% -> 0 | AB50: =Таблица32[[#This Row],[1c]]*Таблица32[[#This Row],[Столбец7]]/100 -> 30000 | AC50: =SUM(Таблица32[[#This Row],[Didox]:[ мехнат]],Таблица32[[#This Row],[Avtokameral]])*Таблица32[[#This Row],[Столбец7]]/100 -> 30000 | AD50: =SUM(Таблица32[[#This Row],[Pul oqimlari]:[Foyda va zarar]])*Таблица32[[#This Row],[Столбец7]]/100 -> 30000 | AE50: =Таблица32[[#This Row],[Столбец7]]*Таблица32[[#This Row],[Nazoratchi]]% -> -30000 | AF50: =Таблица32[[#This Row],[Ishga vaqtida kelish nazoratchi]]+Таблица32[[#This Row],[Nazoratchi2]] -> -30000 | AG50: =Таблица32[[#This Row],[Ishga vaqtida kelish ketish2]]+Таблица32[[#This Row],[Gruppa buxgalter4]]+Таблица32[[#This Row],[1C baza3]]+Таблица32[[#This Row],[xatlar4]]+Таблица32[[#This Row],[Belgilangan otchetlar5]] -> 60000 | AH50: =Таблица32[[#This Row],[Ishga kelish bank klient3]]+Таблица32[[#This Row],[Gruppa bank klient 2]] -> 0
A51: 49 | B51: XK UNIMEAL BUSINESS ENTITY | C51: Humora | D51: Azizbek | E51: 1000000 | F51: Go'zaloy | G51: -0.35 | H51: 1 | J51: 1 | K51: 1 | L51: 0.25 | M51: -0.25 | O51: 1 | P51: 0.25 | Q51: 0.2 | R51: 0.2 | S51: 0.2 | T51: 0.2 | U51: 0.2 | V51: 0.5 | W51: =Таблица32[[#This Row],[Столбец7]]*Таблица32[[#This Row],[Ishga kelish nazoratchi2]]% -> 0 | X51: =Таблица32[[#This Row],[Столбец7]]*Таблица32[[#This Row],[Ishga vaqtida kelish ketish]]% -> -3500 | Y51: =Таблица32[[#This Row],[Столбец7]]*Таблица32[[#This Row],[Ishga kelish bank klient]]% -> 10000 | Z51: =Таблица32[[#This Row],[Столбец7]]*Таблица32[[#This Row],[Gruppa buxgalter]]% -> 10000 | AA51: =Таблица32[[#This Row],[Столбец7]]*Таблица32[[#This Row],[Gruppa bank klient ]]% -> 10000 | AB51: =Таблица32[[#This Row],[1c]]*Таблица32[[#This Row],[Столбец7]]/100 -> 10000 | AC51: =SUM(Таблица32[[#This Row],[Didox]:[ мехнат]],Таблица32[[#This Row],[Avtokameral]])*Таблица32[[#This Row],[Столбец7]]/100 -> 2500 | AD51: =SUM(Таблица32[[#This Row],[Pul oqimlari]:[Foyda va zarar]])*Таблица32[[#This Row],[Столбец7]]/100 -> 10000 | AE51: =Таблица32[[#This Row],[Столбец7]]*Таблица32[[#This Row],[Nazoratchi]]% -> 5000 | AF51: =Таблица32[[#This Row],[Ishga vaqtida kelish nazoratchi]]+Таблица32[[#This Row],[Nazoratchi2]] -> 5000 | AG51: =Таблица32[[#This Row],[Ishga vaqtida kelish ketish2]]+Таблица32[[#This Row],[Gruppa buxgalter4]]+Таблица32[[#This Row],[1C baza3]]+Таблица32[[#This Row],[xatlar4]]+Таблица32[[#This Row],[Belgilangan otchetlar5]] -> 29000 | AH51: =Таблица32[[#This Row],[Ishga kelish bank klient3]]+Таблица32[[#This Row],[Gruppa bank klient 2]] -> 20000
A52: 50 | B52: "ЧП INTER PROF EDUCATION" | C52: Humora | D52: Ruslan | E52: 2000000 | F52: Go'zaloy | G52: -0.35 | H52: 1 | J52: 1 | K52: 1 | L52: 0.25 | M52: 0.25 | N52: 0.25 | O52: 1 | P52: 0.25 | Q52: 0.2 | R52: 0.2 | S52: 0.2 | T52: 0.2 | U52: 0.2 | V52: 0.5 | W52: =Таблица32[[#This Row],[Столбец7]]*Таблица32[[#This Row],[Ishga kelish nazoratchi2]]% -> 0 | X52: =Таблица32[[#This Row],[Столбец7]]*Таблица32[[#This Row],[Ishga vaqtida kelish ketish]]% -> -7000 | Y52: =Таблица32[[#This Row],[Столбец7]]*Таблица32[[#This Row],[Ishga kelish bank klient]]% -> 20000 | Z52: =Таблица32[[#This Row],[Столбец7]]*Таблица32[[#This Row],[Gruppa buxgalter]]% -> 20000 | AA52: =Таблица32[[#This Row],[Столбец7]]*Таблица32[[#This Row],[Gruppa bank klient ]]% -> 20000 | AB52: =Таблица32[[#This Row],[1c]]*Таблица32[[#This Row],[Столбец7]]/100 -> 20000 | AC52: =SUM(Таблица32[[#This Row],[Didox]:[ мехнат]],Таблица32[[#This Row],[Avtokameral]])*Таблица32[[#This Row],[Столбец7]]/100 -> 20000 | AD52: =SUM(Таблица32[[#This Row],[Pul oqimlari]:[Foyda va zarar]])*Таблица32[[#This Row],[Столбец7]]/100 -> 20000 | AE52: =Таблица32[[#This Row],[Столбец7]]*Таблица32[[#This Row],[Nazoratchi]]% -> 10000 | AF52: =Таблица32[[#This Row],[Ishga vaqtida kelish nazoratchi]]+Таблица32[[#This Row],[Nazoratchi2]] -> 10000 | AG52: =Таблица32[[#This Row],[Ishga vaqtida kelish ketish2]]+Таблица32[[#This Row],[Gruppa buxgalter4]]+Таблица32[[#This Row],[1C baza3]]+Таблица32[[#This Row],[xatlar4]]+Таблица32[[#This Row],[Belgilangan otchetlar5]] -> 73000 | AH52: =Таблица32[[#This Row],[Ishga kelish bank klient3]]+Таблица32[[#This Row],[Gruppa bank klient 2]] -> 40000
A53: 51 | B53: LANGUAGE ACADEMY" | C53: Abdugani | D53: Azizbek | E53: 2500000 | F53: Go'zaloy | G53: -0.8 | H53: 1 | J53: 1 | K53: 1 | L53: 0.25 | M53: 0.25 | N53: 0.25 | O53: 1 | P53: 0.25 | Q53: 0.2 | R53: 0.2 | S53: 0.2 | T53: -0.2 | U53: 0.2 | V53: 0.5 | W53: =Таблица32[[#This Row],[Столбец7]]*Таблица32[[#This Row],[Ishga kelish nazoratchi2]]% -> 0 | X53: =Таблица32[[#This Row],[Столбец7]]*Таблица32[[#This Row],[Ishga vaqtida kelish ketish]]% -> -20000 | Y53: =Таблица32[[#This Row],[Столбец7]]*Таблица32[[#This Row],[Ishga kelish bank klient]]% -> 25000 | Z53: =Таблица32[[#This Row],[Столбец7]]*Таблица32[[#This Row],[Gruppa buxgalter]]% -> 25000 | AA53: =Таблица32[[#This Row],[Столбец7]]*Таблица32[[#This Row],[Gruppa bank klient ]]% -> 25000 | AB53: =Таблица32[[#This Row],[1c]]*Таблица32[[#This Row],[Столбец7]]/100 -> 25000 | AC53: =SUM(Таблица32[[#This Row],[Didox]:[ мехнат]],Таблица32[[#This Row],[Avtokameral]])*Таблица32[[#This Row],[Столбец7]]/100 -> 25000 | AD53: =SUM(Таблица32[[#This Row],[Pul oqimlari]:[Foyda va zarar]])*Таблица32[[#This Row],[Столбец7]]/100 -> 15000 | AE53: =Таблица32[[#This Row],[Столбец7]]*Таблица32[[#This Row],[Nazoratchi]]% -> 12500 | AF53: =Таблица32[[#This Row],[Ishga vaqtida kelish nazoratchi]]+Таблица32[[#This Row],[Nazoratchi2]] -> 12500 | AG53: =Таблица32[[#This Row],[Ishga vaqtida kelish ketish2]]+Таблица32[[#This Row],[Gruppa buxgalter4]]+Таблица32[[#This Row],[1C baza3]]+Таблица32[[#This Row],[xatlar4]]+Таблица32[[#This Row],[Belgilangan otchetlar5]] -> 70000 | AH53: =Таблица32[[#This Row],[Ishga kelish bank klient3]]+Таблица32[[#This Row],[Gruppa bank klient 2]] -> 50000
A54: 52 | B54: BEK AND COMPANY | C54: Mirabbos | D54: Azizbek | E54: 1000000 | F54: Muslimbek | H54: 1 | J54: 1 | K54: 1 | L54: 0.25 | M54: -0.25 | P54: -0.25 | Q54: -0.2 | R54: -0.2 | S54: -0.2 | T54: -0.2 | U54: -0.2 | V54: 0.5 | W54: =Таблица32[[#This Row],[Столбец7]]*Таблица32[[#This Row],[Ishga kelish nazoratchi2]]% -> 0 | X54: =Таблица32[[#This Row],[Столбец7]]*Таблица32[[#This Row],[Ishga vaqtida kelish ketish]]% -> 0 | Y54: =Таблица32[[#This Row],[Столбец7]]*Таблица32[[#This Row],[Ishga kelish bank klient]]% -> 10000 | Z54: =Таблица32[[#This Row],[Столбец7]]*Таблица32[[#This Row],[Gruppa buxgalter]]% -> 10000 | AA54: =Таблица32[[#This Row],[Столбец7]]*Таблица32[[#This Row],[Gruppa bank klient ]]% -> 10000 | AB54: =Таблица32[[#This Row],[1c]]*Таблица32[[#This Row],[Столбец7]]/100 -> 0 | AC54: =SUM(Таблица32[[#This Row],[Didox]:[ мехнат]],Таблица32[[#This Row],[Avtokameral]])*Таблица32[[#This Row],[Столбец7]]/100 -> -2500 | AD54: =SUM(Таблица32[[#This Row],[Pul oqimlari]:[Foyda va zarar]])*Таблица32[[#This Row],[Столбец7]]/100 -> -10000 | AE54: =Таблица32[[#This Row],[Столбец7]]*Таблица32[[#This Row],[Nazoratchi]]% -> 5000 | AF54: =Таблица32[[#This Row],[Ishga vaqtida kelish nazoratchi]]+Таблица32[[#This Row],[Nazoratchi2]] -> 5000 | AG54: =Таблица32[[#This Row],[Ishga vaqtida kelish ketish2]]+Таблица32[[#This Row],[Gruppa buxgalter4]]+Таблица32[[#This Row],[1C baza3]]+Таблица32[[#This Row],[xatlar4]]+Таблица32[[#This Row],[Belgilangan otchetlar5]] -> -2500 | AH54: =Таблица32[[#This Row],[Ishga kelish bank klient3]]+Таблица32[[#This Row],[Gruppa bank klient 2]] -> 20000
A55: 53 | B55: 7-NINE МЧЖ | C55: Musobek | D55: Azizbek | E55: 1500000 | F55: Go'zaloy | G55: 0.9 | H55: 1 | J55: 1 | K55: 1 | L55: 0.25 | M55: 0.25 | N55: -0.25 | P55: -0.25 | Q55: 0.2 | R55: 0.2 | S55: 0.2 | T55: -0.2 | U55: -0.2 | V55: 0.5 | W55: =Таблица32[[#This Row],[Столбец7]]*Таблица32[[#This Row],[Ishga kelish nazoratchi2]]% -> 0 | X55: =Таблица32[[#This Row],[Столбец7]]*Таблица32[[#This Row],[Ishga vaqtida kelish ketish]]% -> 13500 | Y55: =Таблица32[[#This Row],[Столбец7]]*Таблица32[[#This Row],[Ishga kelish bank klient]]% -> 15000 | Z55: =Таблица32[[#This Row],[Столбец7]]*Таблица32[[#This Row],[Gruppa buxgalter]]% -> 15000 | AA55: =Таблица32[[#This Row],[Столбец7]]*Таблица32[[#This Row],[Gruppa bank klient ]]% -> 15000 | AB55: =Таблица32[[#This Row],[1c]]*Таблица32[[#This Row],[Столбец7]]/100 -> 0 | AC55: =SUM(Таблица32[[#This Row],[Didox]:[ мехнат]],Таблица32[[#This Row],[Avtokameral]])*Таблица32[[#This Row],[Столбец7]]/100 -> 0 | AD55: =SUM(Таблица32[[#This Row],[Pul oqimlari]:[Foyda va zarar]])*Таблица32[[#This Row],[Столбец7]]/100 -> 3000 | AE55: =Таблица32[[#This Row],[Столбец7]]*Таблица32[[#This Row],[Nazoratchi]]% -> 7500 | AF55: =Таблица32[[#This Row],[Ishga vaqtida kelish nazoratchi]]+Таблица32[[#This Row],[Nazoratchi2]] -> 7500 | AG55: =Таблица32[[#This Row],[Ishga vaqtida kelish ketish2]]+Таблица32[[#This Row],[Gruppa buxgalter4]]+Таблица32[[#This Row],[1C baza3]]+Таблица32[[#This Row],[xatlar4]]+Таблица32[[#This Row],[Belgilangan otchetlar5]] -> 31500 | AH55: =Таблица32[[#This Row],[Ishga kelish bank klient3]]+Таблица32[[#This Row],[Gruppa bank klient 2]] -> 30000
A56: 54 | B56: BELLSTORE | C56: Go'zaloy | D56: Azizbek | E56: 1000000 | F56: Muslimbek | G56: 0.05 | H56: 1 | J56: 1 | K56: 1 | L56: -0.25 | M56: 0.25 | N56: 0.25 | O56: 1 | P56: 0.25 | Q56: 0.2 | R56: 0.2 | S56: 0.2 | T56: -0.2 | U56: 0.2 | V56: 0.5 | W56: =Таблица32[[#This Row],[Столбец7]]*Таблица32[[#This Row],[Ishga kelish nazoratchi2]]% -> 0 | X56: =Таблица32[[#This Row],[Столбец7]]*Таблица32[[#This Row],[Ishga vaqtida kelish ketish]]% -> 500 | Y56: =Таблица32[[#This Row],[Столбец7]]*Таблица32[[#This Row],[Ishga kelish bank klient]]% -> 10000 | Z56: =Таблица32[[#This Row],[Столбец7]]*Таблица32[[#This Row],[Gruppa buxgalter]]% -> 10000 | AA56: =Таблица32[[#This Row],[Столбец7]]*Таблица32[[#This Row],[Gruppa bank klient ]]% -> 10000 | AB56: =Таблица32[[#This Row],[1c]]*Таблица32[[#This Row],[Столбец7]]/100 -> 10000 | AC56: =SUM(Таблица32[[#This Row],[Didox]:[ мехнат]],Таблица32[[#This Row],[Avtokameral]])*Таблица32[[#This Row],[Столбец7]]/100 -> 5000 | AD56: =SUM(Таблица32[[#This Row],[Pul oqimlari]:[Foyda va zarar]])*Таблица32[[#This Row],[Столбец7]]/100 -> 6000 | AE56: =Таблица32[[#This Row],[Столбец7]]*Таблица32[[#This Row],[Nazoratchi]]% -> 5000 | AF56: =Таблица32[[#This Row],[Ishga vaqtida kelish nazoratchi]]+Таблица32[[#This Row],[Nazoratchi2]] -> 5000 | AG56: =Таблица32[[#This Row],[Ishga vaqtida kelish ketish2]]+Таблица32[[#This Row],[Gruppa buxgalter4]]+Таблица32[[#This Row],[1C baza3]]+Таблица32[[#This Row],[xatlar4]]+Таблица32[[#This Row],[Belgilangan otchetlar5]] -> 31500 | AH56: =Таблица32[[#This Row],[Ishga kelish bank klient3]]+Таблица32[[#This Row],[Gruppa bank klient 2]] -> 20000
A57: 55 | B57: TRUST MEDICAL LAB | C57: Mirabbos | D57: Ruslan | E57: 1500000 | F57: Muslimbek | H57: 1 | J57: 1 | K57: 1 | L57: 0.25 | M57: 0.25 | N57: 0.25 | P57: 0.25 | Q57: 0.2 | R57: 0.2 | S57: 0.2 | T57: 0.2 | U57: 0.2 | V57: 0.5 | W57: =Таблица32[[#This Row],[Столбец7]]*Таблица32[[#This Row],[Ishga kelish nazoratchi2]]% -> 0 | X57: =Таблица32[[#This Row],[Столбец7]]*Таблица32[[#This Row],[Ishga vaqtida kelish ketish]]% -> 0 | Y57: =Таблица32[[#This Row],[Столбец7]]*Таблица32[[#This Row],[Ishga kelish bank klient]]% -> 15000 | Z57: =Таблица32[[#This Row],[Столбец7]]*Таблица32[[#This Row],[Gruppa buxgalter]]% -> 15000 | AA57: =Таблица32[[#This Row],[Столбец7]]*Таблица32[[#This Row],[Gruppa bank klient ]]% -> 15000 | AB57: =Таблица32[[#This Row],[1c]]*Таблица32[[#This Row],[Столбец7]]/100 -> 0 | AC57: =SUM(Таблица32[[#This Row],[Didox]:[ мехнат]],Таблица32[[#This Row],[Avtokameral]])*Таблица32[[#This Row],[Столбец7]]/100 -> 15000 | AD57: =SUM(Таблица32[[#This Row],[Pul oqimlari]:[Foyda va zarar]])*Таблица32[[#This Row],[Столбец7]]/100 -> 15000 | AE57: =Таблица32[[#This Row],[Столбец7]]*Таблица32[[#This Row],[Nazoratchi]]% -> 7500 | AF57: =Таблица32[[#This Row],[Ishga vaqtida kelish nazoratchi]]+Таблица32[[#This Row],[Nazoratchi2]] -> 7500 | AG57: =Таблица32[[#This Row],[Ishga vaqtida kelish ketish2]]+Таблица32[[#This Row],[Gruppa buxgalter4]]+Таблица32[[#This Row],[1C baza3]]+Таблица32[[#This Row],[xatlar4]]+Таблица32[[#This Row],[Belgilangan otchetlar5]] -> 45000 | AH57: =Таблица32[[#This Row],[Ishga kelish bank klient3]]+Таблица32[[#This Row],[Gruppa bank klient 2]] -> 30000
A58: 56 | B58: "STUDY GUIDE" | C58: Axmadjon | D58: Azizbek | E58: 4000000 | F58: Muslimbek | H58: 1 | J58: -0.5 | K58: 1 | L58: 0.25 | M58: 0.25 | O58: 1 | P58: 0.25 | Q58: 0.2 | R58: 0.2 | S58: 0.2 | T58: 0.2 | U58: 0.2 | V58: -0.5 | W58: =Таблица32[[#This Row],[Столбец7]]*Таблица32[[#This Row],[Ishga kelish nazoratchi2]]% -> 0 | X58: =Таблица32[[#This Row],[Столбец7]]*Таблица32[[#This Row],[Ishga vaqtida kelish ketish]]% -> 0 | Y58: =Таблица32[[#This Row],[Столбец7]]*Таблица32[[#This Row],[Ishga kelish bank klient]]% -> 40000 | Z58: =Таблица32[[#This Row],[Столбец7]]*Таблица32[[#This Row],[Gruppa buxgalter]]% -> -20000 | AA58: =Таблица32[[#This Row],[Столбец7]]*Таблица32[[#This Row],[Gruppa bank klient ]]% -> 40000 | AB58: =Таблица32[[#This Row],[1c]]*Таблица32[[#This Row],[Столбец7]]/100 -> 40000 | AC58: =SUM(Таблица32[[#This Row],[Didox]:[ мехнат]],Таблица32[[#This Row],[Avtokameral]])*Таблица32[[#This Row],[Столбец7]]/100 -> 30000 | AD58: =SUM(Таблица32[[#This Row],[Pul oqimlari]:[Foyda va zarar]])*Таблица32[[#This Row],[Столбец7]]/100 -> 40000 | AE58: =Таблица32[[#This Row],[Столбец7]]*Таблица32[[#This Row],[Nazoratchi]]% -> -20000 | AF58: =Таблица32[[#This Row],[Ishga vaqtida kelish nazoratchi]]+Таблица32[[#This Row],[Nazoratchi2]] -> -20000 | AG58: =Таблица32[[#This Row],[Ishga vaqtida kelish ketish2]]+Таблица32[[#This Row],[Gruppa buxgalter4]]+Таблица32[[#This Row],[1C baza3]]+Таблица32[[#This Row],[xatlar4]]+Таблица32[[#This Row],[Belgilangan otchetlar5]] -> 90000 | AH58: =Таблица32[[#This Row],[Ishga kelish bank klient3]]+Таблица32[[#This Row],[Gruppa bank klient 2]] -> 80000
A59: 57 | B59: HILOL PHARM | C59: Abdugani | D59: Azizbek | E59: 2500000 | F59: Go'zaloy | G59: -0.8 | H59: 1 | J59: -0.5 | K59: 1 | L59: 0.25 | M59: 0.25 | N59: 0.25 | O59: 1 | P59: 0.25 | Q59: 0.2 | R59: 0.2 | S59: 0.2 | T59: 0.2 | U59: -0.2 | V59: -0.5 | W59: =Таблица32[[#This Row],[Столбец7]]*Таблица32[[#This Row],[Ishga kelish nazoratchi2]]% -> 0 | X59: =Таблица32[[#This Row],[Столбец7]]*Таблица32[[#This Row],[Ishga vaqtida kelish ketish]]% -> -20000 | Y59: =Таблица32[[#This Row],[Столбец7]]*Таблица32[[#This Row],[Ishga kelish bank klient]]% -> 25000 | Z59: =Таблица32[[#This Row],[Столбец7]]*Таблица32[[#This Row],[Gruppa buxgalter]]% -> -12500 | AA59: =Таблица32[[#This Row],[Столбец7]]*Таблица32[[#This Row],[Gruppa bank klient ]]% -> 25000 | AB59: =Таблица32[[#This Row],[1c]]*Таблица32[[#This Row],[Столбец7]]/100 -> 25000 | AC59: =SUM(Таблица32[[#This Row],[Didox]:[ мехнат]],Таблица32[[#This Row],[Avtokameral]])*Таблица32[[#This Row],[Столбец7]]/100 -> 25000 | AD59: =SUM(Таблица32[[#This Row],[Pul oqimlari]:[Foyda va zarar]])*Таблица32[[#This Row],[Столбец7]]/100 -> 15000 | AE59: =Таблица32[[#This Row],[Столбец7]]*Таблица32[[#This Row],[Nazoratchi]]% -> -12500 | AF59: =Таблица32[[#This Row],[Ishga vaqtida kelish nazoratchi]]+Таблица32[[#This Row],[Nazoratchi2]] -> -12500 | AG59: =Таблица32[[#This Row],[Ishga vaqtida kelish ketish2]]+Таблица32[[#This Row],[Gruppa buxgalter4]]+Таблица32[[#This Row],[1C baza3]]+Таблица32[[#This Row],[xatlar4]]+Таблица32[[#This Row],[Belgilangan otchetlar5]] -> 32500 | AH59: =Таблица32[[#This Row],[Ishga kelish bank klient3]]+Таблица32[[#This Row],[Gruppa bank klient 2]] -> 50000
A60: 58 | B60: "HI-TECH ORIENT MED-BUSINESS MCHJ | C60: Muslimbek | E60: 4000000 | F60: Go'zaloy | G60: -0.8 | J60: 1 | L60: 0.25 | M60: 0.25 | N60: 0.25 | O60: 1 | P60: 0.25 | Q60: 0.2 | R60: 0.2 | S60: 0.2 | T60: 0.2 | U60: 0.2 | V60: 0.5 | W60: =Таблица32[[#This Row],[Столбец7]]*Таблица32[[#This Row],[Ishga kelish nazoratchi2]]% -> 0 | X60: =Таблица32[[#This Row],[Столбец7]]*Таблица32[[#This Row],[Ishga vaqtida kelish ketish]]% -> -32000 | Y60: =Таблица32[[#This Row],[Столбец7]]*Таблица32[[#This Row],[Ishga kelish bank klient]]% -> 0 | Z60: =Таблица32[[#This Row],[Столбец7]]*Таблица32[[#This Row],[Gruppa buxgalter]]% -> 40000 | AA60: =Таблица32[[#This Row],[Столбец7]]*Таблица32[[#This Row],[Gruppa bank klient ]]% -> 0 | AB60: =Таблица32[[#This Row],[1c]]*Таблица32[[#This Row],[Столбец7]]/100 -> 40000 | AC60: =SUM(Таблица32[[#This Row],[Didox]:[ мехнат]],Таблица32[[#This Row],[Avtokameral]])*Таблица32[[#This Row],[Столбец7]]/100 -> 40000 | AD60: =SUM(Таблица32[[#This Row],[Pul oqimlari]:[Foyda va zarar]])*Таблица32[[#This Row],[Столбец7]]/100 -> 40000 | AE60: =Таблица32[[#This Row],[Столбец7]]*Таблица32[[#This Row],[Nazoratchi]]% -> 20000 | AF60: =Таблица32[[#This Row],[Ishga vaqtida kelish nazoratchi]]+Таблица32[[#This Row],[Nazoratchi2]] -> 20000 | AG60: =Таблица32[[#This Row],[Ishga vaqtida kelish ketish2]]+Таблица32[[#This Row],[Gruppa buxgalter4]]+Таблица32[[#This Row],[1C baza3]]+Таблица32[[#This Row],[xatlar4]]+Таблица32[[#This Row],[Belgilangan otchetlar5]] -> 128000 | AH60: =Таблица32[[#This Row],[Ishga kelish bank klient3]]+Таблица32[[#This Row],[Gruppa bank klient 2]] -> 0
A61: 59 | B61: "FINANCE SCHOOL" | C61: Humora | D61: Ruslan | E61: 700000 | F61: Go'zaloy | G61: -0.35 | H61: 1 | J61: 1 | K61: 1 | L61: 0.25 | M61: -0.25 | N61: 0.25 | O61: 1 | P61: 0.25 | Q61: 0.2 | R61: 0.2 | S61: 0.2 | T61: 0.2 | U61: 0.2 | V61: 0.5 | W61: =Таблица32[[#This Row],[Столбец7]]*Таблица32[[#This Row],[Ishga kelish nazoratchi2]]% -> 0 | X61: =Таблица32[[#This Row],[Столбец7]]*Таблица32[[#This Row],[Ishga vaqtida kelish ketish]]% -> -2450 | Y61: =Таблица32[[#This Row],[Столбец7]]*Таблица32[[#This Row],[Ishga kelish bank klient]]% -> 7000 | Z61: =Таблица32[[#This Row],[Столбец7]]*Таблица32[[#This Row],[Gruppa buxgalter]]% -> 7000 | AA61: =Таблица32[[#This Row],[Столбец7]]*Таблица32[[#This Row],[Gruppa bank klient ]]% -> 7000 | AB61: =Таблица32[[#This Row],[1c]]*Таблица32[[#This Row],[Столбец7]]/100 -> 7000 | AC61: =SUM(Таблица32[[#This Row],[Didox]:[ мехнат]],Таблица32[[#This Row],[Avtokameral]])*Таблица32[[#This Row],[Столбец7]]/100 -> 3500 | AD61: =SUM(Таблица32[[#This Row],[Pul oqimlari]:[Foyda va zarar]])*Таблица32[[#This Row],[Столбец7]]/100 -> 7000 | AE61: =Таблица32[[#This Row],[Столбец7]]*Таблица32[[#This Row],[Nazoratchi]]% -> 3500 | AF61: =Таблица32[[#This Row],[Ishga vaqtida kelish nazoratchi]]+Таблица32[[#This Row],[Nazoratchi2]] -> 3500 | AG61: =Таблица32[[#This Row],[Ishga vaqtida kelish ketish2]]+Таблица32[[#This Row],[Gruppa buxgalter4]]+Таблица32[[#This Row],[1C baza3]]+Таблица32[[#This Row],[xatlar4]]+Таблица32[[#This Row],[Belgilangan otchetlar5]] -> 22050 | AH61: =Таблица32[[#This Row],[Ishga kelish bank klient3]]+Таблица32[[#This Row],[Gruppa bank klient 2]] -> 14000
A62: 60 | B62: "KIDS NUR CITY" ООО | C62: Musobek | D62: Azizbek | E62: 4350000 | F62: Go'zaloy | G62: 0.9 | H62: 1 | J62: -1 | K62: 1 | L62: 0.25 | M62: 0.25 | N62: -0.25 | P62: 0.25 | Q62: 0.2 | R62: 0.2 | S62: 0.2 | T62: 0.2 | U62: 0.2 | V62: -1 | W62: =Таблица32[[#This Row],[Столбец7]]*Таблица32[[#This Row],[Ishga kelish nazoratchi2]]% -> 0 | X62: =Таблица32[[#This Row],[Столбец7]]*Таблица32[[#This Row],[Ishga vaqtida kelish ketish]]% -> 39150 | Y62: =Таблица32[[#This Row],[Столбец7]]*Таблица32[[#This Row],[Ishga kelish bank klient]]% -> 43500 | Z62: =Таблица32[[#This Row],[Столбец7]]*Таблица32[[#This Row],[Gruppa buxgalter]]% -> -43500 | AA62: =Таблица32[[#This Row],[Столбец7]]*Таблица32[[#This Row],[Gruppa bank klient ]]% -> 43500 | AB62: =Таблица32[[#This Row],[1c]]*Таблица32[[#This Row],[Столбец7]]/100 -> 0 | AC62: =SUM(Таблица32[[#This Row],[Didox]:[ мехнат]],Таблица32[[#This Row],[Avtokameral]])*Таблица32[[#This Row],[Столбец7]]/100 -> 21750 | AD62: =SUM(Таблица32[[#This Row],[Pul oqimlari]:[Foyda va zarar]])*Таблица32[[#This Row],[Столбец7]]/100 -> 43500 | AE62: =Таблица32[[#This Row],[Столбец7]]*Таблица32[[#This Row],[Nazoratchi]]% -> -43500 | AF62: =Таблица32[[#This Row],[Ishga vaqtida kelish nazoratchi]]+Таблица32[[#This Row],[Nazoratchi2]] -> -43500 | AG62: =Таблица32[[#This Row],[Ishga vaqtida kelish ketish2]]+Таблица32[[#This Row],[Gruppa buxgalter4]]+Таблица32[[#This Row],[1C baza3]]+Таблица32[[#This Row],[xatlar4]]+Таблица32[[#This Row],[Belgilangan otchetlar5]] -> 60900 | AH62: =Таблица32[[#This Row],[Ishga kelish bank klient3]]+Таблица32[[#This Row],[Gruppa bank klient 2]] -> 87000
A63: 61 | B63: TAKSIM-KEBAB GROUP MCHJ | C63: Abdugani | D63: Ruslan | E63: 0 | F63: Go'zaloy | G63: -0.8 | H63: 1 | J63: 1 | K63: 1 | L63: 0.25 | M63: -0.25 | P63: 0.25 | Q63: 0 | R63: 0 | S63: 0 | T63: 0 | U63: 0 | V63: 0.5 | W63: =Таблица32[[#This Row],[Столбец7]]*Таблица32[[#This Row],[Ishga kelish nazoratchi2]]% -> 0 | X63: =Таблица32[[#This Row],[Столбец7]]*Таблица32[[#This Row],[Ishga vaqtida kelish ketish]]% -> 0 | Y63: =Таблица32[[#This Row],[Столбец7]]*Таблица32[[#This Row],[Ishga kelish bank klient]]% -> 0 | Z63: =Таблица32[[#This Row],[Столбец7]]*Таблица32[[#This Row],[Gruppa buxgalter]]% -> 0 | AA63: =Таблица32[[#This Row],[Столбец7]]*Таблица32[[#This Row],[Gruppa bank klient ]]% -> 0 | AB63: =Таблица32[[#This Row],[1c]]*Таблица32[[#This Row],[Столбец7]]/100 -> 0 | AC63: =SUM(Таблица32[[#This Row],[Didox]:[ мехнат]],Таблица32[[#This Row],[Avtokameral]])*Таблица32[[#This Row],[Столбец7]]/100 -> 0 | AD63: =SUM(Таблица32[[#This Row],[Pul oqimlari]:[Foyda va zarar]])*Таблица32[[#This Row],[Столбец7]]/100 -> 0 | AE63: =Таблица32[[#This Row],[Столбец7]]*Таблица32[[#This Row],[Nazoratchi]]% -> 0 | AF63: =Таблица32[[#This Row],[Ishga vaqtida kelish nazoratchi]]+Таблица32[[#This Row],[Nazoratchi2]] -> 0 | AG63: =Таблица32[[#This Row],[Ishga vaqtida kelish ketish2]]+Таблица32[[#This Row],[Gruppa buxgalter4]]+Таблица32[[#This Row],[1C baza3]]+Таблица32[[#This Row],[xatlar4]]+Таблица32[[#This Row],[Belgilangan otchetlar5]] -> 0 | AH63: =Таблица32[[#This Row],[Ishga kelish bank klient3]]+Таблица32[[#This Row],[Gruppa bank klient 2]] -> 0
A64: 62 | B64: NIGINA FARM | C64: Zamira | E64: 5000000 | F64: Go'zaloy | G64: -0.25 | J64: 1 | L64: 0 | M64: 0.25 | N64: 0.25 | P64: 0.25 | Q64: 0.2 | R64: 0.2 | S64: 0.2 | T64: -0.2 | U64: 0.2 | V64: 0.5 | W64: =Таблица32[[#This Row],[Столбец7]]*Таблица32[[#This Row],[Ishga kelish nazoratchi2]]% -> 0 | X64: =Таблица32[[#This Row],[Столбец7]]*Таблица32[[#This Row],[Ishga vaqtida kelish ketish]]% -> -12500 | Y64: =Таблица32[[#This Row],[Столбец7]]*Таблица32[[#This Row],[Ishga kelish bank klient]]% -> 0 | Z64: =Таблица32[[#This Row],[Столбец7]]*Таблица32[[#This Row],[Gruppa buxgalter]]% -> 50000 | AA64: =Таблица32[[#This Row],[Столбец7]]*Таблица32[[#This Row],[Gruppa bank klient ]]% -> 0 | AB64: =Таблица32[[#This Row],[1c]]*Таблица32[[#This Row],[Столбец7]]/100 -> 0 | AC64: =SUM(Таблица32[[#This Row],[Didox]:[ мехнат]],Таблица32[[#This Row],[Avtokameral]])*Таблица32[[#This Row],[Столбец7]]/100 -> 37500 | AD64: =SUM(Таблица32[[#This Row],[Pul oqimlari]:[Foyda va zarar]])*Таблица32[[#This Row],[Столбец7]]/100 -> 30000 | AE64: =Таблица32[[#This Row],[Столбец7]]*Таблица32[[#This Row],[Nazoratchi]]% -> 25000 | AF64: =Таблица32[[#This Row],[Ishga vaqtida kelish nazoratchi]]+Таблица32[[#This Row],[Nazoratchi2]] -> 25000 | AG64: =Таблица32[[#This Row],[Ishga vaqtida kelish ketish2]]+Таблица32[[#This Row],[Gruppa buxgalter4]]+Таблица32[[#This Row],[1C baza3]]+Таблица32[[#This Row],[xatlar4]]+Таблица32[[#This Row],[Belgilangan otchetlar5]] -> 105000 | AH64: =Таблица32[[#This Row],[Ishga kelish bank klient3]]+Таблица32[[#This Row],[Gruppa bank klient 2]] -> 0
A65: 63 | B65: DOUBLE X PRO | C65: Hasan | D65: Azizbek | E65: 1000000 | F65: Muslimbek | G65: -6 | H65: 1 | J65: -0.5 | K65: 1 | L65: 0.25 | M65: 0.25 | P65: 0.25 | Q65: -0.2 | R65: 0.2 | S65: 0.2 | T65: -0.2 | U65: -0.2 | V65: -0.5 | W65: =Таблица32[[#This Row],[Столбец7]]*Таблица32[[#This Row],[Ishga kelish nazoratchi2]]% -> 0 | X65: =Таблица32[[#This Row],[Столбец7]]*Таблица32[[#This Row],[Ishga vaqtida kelish ketish]]% -> -60000 | Y65: =Таблица32[[#This Row],[Столбец7]]*Таблица32[[#This Row],[Ishga kelish bank klient]]% -> 10000 | Z65: =Таблица32[[#This Row],[Столбец7]]*Таблица32[[#This Row],[Gruppa buxgalter]]% -> -5000 | AA65: =Таблица32[[#This Row],[Столбец7]]*Таблица32[[#This Row],[Gruppa bank klient ]]% -> 10000 | AB65: =Таблица32[[#This Row],[1c]]*Таблица32[[#This Row],[Столбец7]]/100 -> 0 | AC65: =SUM(Таблица32[[#This Row],[Didox]:[ мехнат]],Таблица32[[#This Row],[Avtokameral]])*Таблица32[[#This Row],[Столбец7]]/100 -> 7500 | AD65: =SUM(Таблица32[[#This Row],[Pul oqimlari]:[Foyda va zarar]])*Таблица32[[#This Row],[Столбец7]]/100 -> -2000 | AE65: =Таблица32[[#This Row],[Столбец7]]*Таблица32[[#This Row],[Nazoratchi]]% -> -5000 | AF65: =Таблица32[[#This Row],[Ishga vaqtida kelish nazoratchi]]+Таблица32[[#This Row],[Nazoratchi2]] -> -5000 | AG65: =Таблица32[[#This Row],[Ishga vaqtida kelish ketish2]]+Таблица32[[#This Row],[Gruppa buxgalter4]]+Таблица32[[#This Row],[1C baza3]]+Таблица32[[#This Row],[xatlar4]]+Таблица32[[#This Row],[Belgilangan otchetlar5]] -> -59500 | AH65: =Таблица32[[#This Row],[Ishga kelish bank klient3]]+Таблица32[[#This Row],[Gruppa bank klient 2]] -> 20000
A66: 64 | B66: "MUZAFFARXO`JA-HILOL" Х.Ф. | C66: Musobek | D66: Ruslan | E66: 2500000 | F66: Go'zaloy | G66: 0.9 | H66: 1 | J66: -0.5 | K66: 1 | L66: -0.25 | M66: 0.25 | P66: 0.25 | Q66: 0.2 | R66: 0.2 | S66: 0.2 | T66: 0.2 | U66: 0.2 | V66: -0.5 | W66: =Таблица32[[#This Row],[Столбец7]]*Таблица32[[#This Row],[Ishga kelish nazoratchi2]]% -> 0 | X66: =Таблица32[[#This Row],[Столбец7]]*Таблица32[[#This Row],[Ishga vaqtida kelish ketish]]% -> 22500 | Y66: =Таблица32[[#This Row],[Столбец7]]*Таблица32[[#This Row],[Ishga kelish bank klient]]% -> 25000 | Z66: =Таблица32[[#This Row],[Столбец7]]*Таблица32[[#This Row],[Gruppa buxgalter]]% -> -12500 | AA66: =Таблица32[[#This Row],[Столбец7]]*Таблица32[[#This Row],[Gruppa bank klient ]]% -> 25000 | AB66: =Таблица32[[#This Row],[1c]]*Таблица32[[#This Row],[Столбец7]]/100 -> 0 | AC66: =SUM(Таблица32[[#This Row],[Didox]:[ мехнат]],Таблица32[[#This Row],[Avtokameral]])*Таблица32[[#This Row],[Столбец7]]/100 -> 6250 | AD66: =SUM(Таблица32[[#This Row],[Pul oqimlari]:[Foyda va zarar]])*Таблица32[[#This Row],[Столбец7]]/100 -> 25000 | AE66: =Таблица32[[#This Row],[Столбец7]]*Таблица32[[#This Row],[Nazoratchi]]% -> -12500 | AF66: =Таблица32[[#This Row],[Ishga vaqtida kelish nazoratchi]]+Таблица32[[#This Row],[Nazoratchi2]] -> -12500 | AG66: =Таблица32[[#This Row],[Ishga vaqtida kelish ketish2]]+Таблица32[[#This Row],[Gruppa buxgalter4]]+Таблица32[[#This Row],[1C baza3]]+Таблица32[[#This Row],[xatlar4]]+Таблица32[[#This Row],[Belgilangan otchetlar5]] -> 41250 | AH66: =Таблица32[[#This Row],[Ishga kelish bank klient3]]+Таблица32[[#This Row],[Gruppa bank klient 2]] -> 50000
A67: 65 | B67: VIRTUS-SOCIUM МЧЖ | C67: Abrorbek | D67: Azizbek | E67: 0 | F67: Go'zaloy | H67: 1 | J67: -0.5 | K67: 1 | L67: -0.25 | M67: 0.25 | P67: 0.25 | Q67: 0 | R67: -0.2 | S67: 0 | T67: 0 | U67: 0 | V67: -0.5 | W67: =Таблица32[[#This Row],[Столбец7]]*Таблица32[[#This Row],[Ishga kelish nazoratchi2]]% -> 0 | X67: =Таблица32[[#This Row],[Столбец7]]*Таблица32[[#This Row],[Ishga vaqtida kelish ketish]]% -> 0 | Y67: =Таблица32[[#This Row],[Столбец7]]*Таблица32[[#This Row],[Ishga kelish bank klient]]% -> 0 | Z67: =Таблица32[[#This Row],[Столбец7]]*Таблица32[[#This Row],[Gruppa buxgalter]]% -> 0 | AA67: =Таблица32[[#This Row],[Столбец7]]*Таблица32[[#This Row],[Gruppa bank klient ]]% -> 0 | AB67: =Таблица32[[#This Row],[1c]]*Таблица32[[#This Row],[Столбец7]]/100 -> 0 | AC67: =SUM(Таблица32[[#This Row],[Didox]:[ мехнат]],Таблица32[[#This Row],[Avtokameral]])*Таблица32[[#This Row],[Столбец7]]/100 -> 0 | AD67: =SUM(Таблица32[[#This Row],[Pul oqimlari]:[Foyda va zarar]])*Таблица32[[#This Row],[Столбец7]]/100 -> 0 | AE67: =Таблица32[[#This Row],[Столбец7]]*Таблица32[[#This Row],[Nazoratchi]]% -> 0 | AF67: =Таблица32[[#This Row],[Ishga vaqtida kelish nazoratchi]]+Таблица32[[#This Row],[Nazoratchi2]] -> 0 | AG67: =Таблица32[[#This Row],[Ishga vaqtida kelish ketish2]]+Таблица32[[#This Row],[Gruppa buxgalter4]]+Таблица32[[#This Row],[1C baza3]]+Таблица32[[#This Row],[xatlar4]]+Таблица32[[#This Row],[Belgilangan otchetlar5]] -> 0 | AH67: =Таблица32[[#This Row],[Ishga kelish bank klient3]]+Таблица32[[#This Row],[Gruppa bank klient 2]] -> 0
A68: 66 | B68: "PHARM SMART" MCHJ | C68: Javohir | D68: Azizbek | E68: 4000000 | F68: Muslimbek | G68: -0.05 | H68: 1 | J68: 1 | K68: 1 | L68: 0.25 | M68: 0.25 | N68: 0.25 | P68: -0.25 | Q68: 0.2 | R68: -0.2 | S68: -0.2 | T68: 0.2 | U68: -0.2 | V68: 0.5 | W68: =Таблица32[[#This Row],[Столбец7]]*Таблица32[[#This Row],[Ishga kelish nazoratchi2]]% -> 0 | X68: =Таблица32[[#This Row],[Столбец7]]*Таблица32[[#This Row],[Ishga vaqtida kelish ketish]]% -> -2000 | Y68: =Таблица32[[#This Row],[Столбец7]]*Таблица32[[#This Row],[Ishga kelish bank klient]]% -> 40000 | Z68: =Таблица32[[#This Row],[Столбец7]]*Таблица32[[#This Row],[Gruppa buxgalter]]% -> 40000 | AA68: =Таблица32[[#This Row],[Столбец7]]*Таблица32[[#This Row],[Gruppa bank klient ]]% -> 40000 | AB68: =Таблица32[[#This Row],[1c]]*Таблица32[[#This Row],[Столбец7]]/100 -> 0 | AC68: =SUM(Таблица32[[#This Row],[Didox]:[ мехнат]],Таблица32[[#This Row],[Avtokameral]])*Таблица32[[#This Row],[Столбец7]]/100 -> 20000 | AD68: =SUM(Таблица32[[#This Row],[Pul oqimlari]:[Foyda va zarar]])*Таблица32[[#This Row],[Столбец7]]/100 -> -8000 | AE68: =Таблица32[[#This Row],[Столбец7]]*Таблица32[[#This Row],[Nazoratchi]]% -> 20000 | AF68: =Таблица32[[#This Row],[Ishga vaqtida kelish nazoratchi]]+Таблица32[[#This Row],[Nazoratchi2]] -> 20000 | AG68: =Таблица32[[#This Row],[Ishga vaqtida kelish ketish2]]+Таблица32[[#This Row],[Gruppa buxgalter4]]+Таблица32[[#This Row],[1C baza3]]+Таблица32[[#This Row],[xatlar4]]+Таблица32[[#This Row],[Belgilangan otchetlar5]] -> 50000 | AH68: =Таблица32[[#This Row],[Ishga kelish bank klient3]]+Таблица32[[#This Row],[Gruppa bank klient 2]] -> 80000
A69: 67 | B69: PHARZAM FARM | C69: Javohir | D69: Ruslan | E69: 3000000 | F69: Muslimbek | G69: -0.05 | H69: 1 | J69: 1 | K69: 1 | L69: -0.25 | M69: 0.25 | P69: -0.25 | Q69: 0.2 | R69: 0.2 | S69: 0.2 | T69: 0.2 | U69: -0.2 | V69: 0.5 | W69: =Таблица32[[#This Row],[Столбец7]]*Таблица32[[#This Row],[Ishga kelish nazoratchi2]]% -> 0 | X69: =Таблица32[[#This Row],[Столбец7]]*Таблица32[[#This Row],[Ishga vaqtida kelish ketish]]% -> -1500 | Y69: =Таблица32[[#This Row],[Столбец7]]*Таблица32[[#This Row],[Ishga kelish bank klient]]% -> 30000 | Z69: =Таблица32[[#This Row],[Столбец7]]*Таблица32[[#This Row],[Gruppa buxgalter]]% -> 30000 | AA69: =Таблица32[[#This Row],[Столбец7]]*Таблица32[[#This Row],[Gruppa bank klient ]]% -> 30000 | AB69: =Таблица32[[#This Row],[1c]]*Таблица32[[#This Row],[Столбец7]]/100 -> 0 | AC69: =SUM(Таблица32[[#This Row],[Didox]:[ мехнат]],Таблица32[[#This Row],[Avtokameral]])*Таблица32[[#This Row],[Столбец7]]/100 -> -7500 | AD69: =SUM(Таблица32[[#This Row],[Pul oqimlari]:[Foyda va zarar]])*Таблица32[[#This Row],[Столбец7]]/100 -> 18000 | AE69: =Таблица32[[#This Row],[Столбец7]]*Таблица32[[#This Row],[Nazoratchi]]% -> 15000 | AF69: =Таблица32[[#This Row],[Ishga vaqtida kelish nazoratchi]]+Таблица32[[#This Row],[Nazoratchi2]] -> 15000 | AG69: =Таблица32[[#This Row],[Ishga vaqtida kelish ketish2]]+Таблица32[[#This Row],[Gruppa buxgalter4]]+Таблица32[[#This Row],[1C baza3]]+Таблица32[[#This Row],[xatlar4]]+Таблица32[[#This Row],[Belgilangan otchetlar5]] -> 39000 | AH69: =Таблица32[[#This Row],[Ishga kelish bank klient3]]+Таблица32[[#This Row],[Gruppa bank klient 2]] -> 60000
A70: 68 | B70: MIRGAS OIL MCHJ | C70: Mirabbos | D70: Azizbek | E70: 1500000 | F70: Muslimbek | H70: 1 | J70: 1 | K70: 1 | L70: 0.25 | M70: 0.25 | P70: -0.25 | Q70: 0 | R70: 0 | S70: 0 | T70: 0 | U70: 0 | V70: 0.5 | W70: =Таблица32[[#This Row],[Столбец7]]*Таблица32[[#This Row],[Ishga kelish nazoratchi2]]% -> 0 | X70: =Таблица32[[#This Row],[Столбец7]]*Таблица32[[#This Row],[Ishga vaqtida kelish ketish]]% -> 0 | Y70: =Таблица32[[#This Row],[Столбец7]]*Таблица32[[#This Row],[Ishga kelish bank klient]]% -> 15000 | Z70: =Таблица32[[#This Row],[Столбец7]]*Таблица32[[#This Row],[Gruppa buxgalter]]% -> 15000 | AA70: =Таблица32[[#This Row],[Столбец7]]*Таблица32[[#This Row],[Gruppa bank klient ]]% -> 15000 | AB70: =Таблица32[[#This Row],[1c]]*Таблица32[[#This Row],[Столбец7]]/100 -> 0 | AC70: =SUM(Таблица32[[#This Row],[Didox]:[ мехнат]],Таблица32[[#This Row],[Avtokameral]])*Таблица32[[#This Row],[Столбец7]]/100 -> 3750 | AD70: =SUM(Таблица32[[#This Row],[Pul oqimlari]:[Foyda va zarar]])*Таблица32[[#This Row],[Столбец7]]/100 -> 0 | AE70: =Таблица32[[#This Row],[Столбец7]]*Таблица32[[#This Row],[Nazoratchi]]% -> 7500 | AF70: =Таблица32[[#This Row],[Ishga vaqtida kelish nazoratchi]]+Таблица32[[#This Row],[Nazoratchi2]] -> 7500 | AG70: =Таблица32[[#This Row],[Ishga vaqtida kelish ketish2]]+Таблица32[[#This Row],[Gruppa buxgalter4]]+Таблица32[[#This Row],[1C baza3]]+Таблица32[[#This Row],[xatlar4]]+Таблица32[[#This Row],[Belgilangan otchetlar5]] -> 18750 | AH70: =Таблица32[[#This Row],[Ishga kelish bank klient3]]+Таблица32[[#This Row],[Gruppa bank klient 2]] -> 30000
A71: 69 | B71: TRINITY TECHNOLOGY MCHJ | E71: 20000000 | L71: 0 | M71: 0 | P71: 0 | Q71: 0 | R71: 0 | S71: 0 | T71: 0 | U71: 0 | W71: =Таблица32[[#This Row],[Столбец7]]*Таблица32[[#This Row],[Ishga kelish nazoratchi2]]% -> 0 | X71: =Таблица32[[#This Row],[Столбец7]]*Таблица32[[#This Row],[Ishga vaqtida kelish ketish]]% -> 0 | Y71: =Таблица32[[#This Row],[Столбец7]]*Таблица32[[#This Row],[Ishga kelish bank klient]]% -> 0 | Z71: =Таблица32[[#This Row],[Столбец7]]*Таблица32[[#This Row],[Gruppa buxgalter]]% -> 0 | AA71: =Таблица32[[#This Row],[Столбец7]]*Таблица32[[#This Row],[Gruppa bank klient ]]% -> 0 | AB71: =Таблица32[[#This Row],[1c]]*Таблица32[[#This Row],[Столбец7]]/100 -> 0 | AC71: =SUM(Таблица32[[#This Row],[Didox]:[ мехнат]],Таблица32[[#This Row],[Avtokameral]])*Таблица32[[#This Row],[Столбец7]]/100 -> 0 | AD71: =SUM(Таблица32[[#This Row],[Pul oqimlari]:[Foyda va zarar]])*Таблица32[[#This Row],[Столбец7]]/100 -> 0 | AE71: =Таблица32[[#This Row],[Столбец7]]*Таблица32[[#This Row],[Nazoratchi]]% -> 0 | AF71: =Таблица32[[#This Row],[Ishga vaqtida kelish nazoratchi]]+Таблица32[[#This Row],[Nazoratchi2]] -> 0 | AG71: =Таблица32[[#This Row],[Ishga vaqtida kelish ketish2]]+Таблица32[[#This Row],[Gruppa buxgalter4]]+Таблица32[[#This Row],[1C baza3]]+Таблица32[[#This Row],[xatlar4]]+Таблица32[[#This Row],[Belgilangan otchetlar5]] -> 0 | AH71: =Таблица32[[#This Row],[Ishga kelish bank klient3]]+Таблица32[[#This Row],[Gruppa bank klient 2]] -> 0
A72: 70 | B72: SOBIROV I YATT | C72: Abdugani | E72: 200000 | F72: Go'zaloy | G72: -0.8 | J72: 1 | L72: 0 | M72: 0 | P72: 0 | Q72: 0 | R72: 0 | S72: 0 | T72: 0 | U72: 0 | V72: 0.5 | W72: =Таблица32[[#This Row],[Столбец7]]*Таблица32[[#This Row],[Ishga kelish nazoratchi2]]% -> 0 | X72: =Таблица32[[#This Row],[Столбец7]]*Таблица32[[#This Row],[Ishga vaqtida kelish ketish]]% -> -1600 | Y72: =Таблица32[[#This Row],[Столбец7]]*Таблица32[[#This Row],[Ishga kelish bank klient]]% -> 0 | Z72: =Таблица32[[#This Row],[Столбец7]]*Таблица32[[#This Row],[Gruppa buxgalter]]% -> 2000 | AA72: =Таблица32[[#This Row],[Столбец7]]*Таблица32[[#This Row],[Gruppa bank klient ]]% -> 0 | AB72: =Таблица32[[#This Row],[1c]]*Таблица32[[#This Row],[Столбец7]]/100 -> 0 | AC72: =SUM(Таблица32[[#This Row],[Didox]:[ мехнат]],Таблица32[[#This Row],[Avtokameral]])*Таблица32[[#This Row],[Столбец7]]/100 -> 0 | AD72: =SUM(Таблица32[[#This Row],[Pul oqimlari]:[Foyda va zarar]])*Таблица32[[#This Row],[Столбец7]]/100 -> 0 | AE72: =Таблица32[[#This Row],[Столбец7]]*Таблица32[[#This Row],[Nazoratchi]]% -> 1000 | AF72: =Таблица32[[#This Row],[Ishga vaqtida kelish nazoratchi]]+Таблица32[[#This Row],[Nazoratchi2]] -> 1000 | AG72: =Таблица32[[#This Row],[Ishga vaqtida kelish ketish2]]+Таблица32[[#This Row],[Gruppa buxgalter4]]+Таблица32[[#This Row],[1C baza3]]+Таблица32[[#This Row],[xatlar4]]+Таблица32[[#This Row],[Belgilangan otchetlar5]] -> 400 | AH72: =Таблица32[[#This Row],[Ishga kelish bank klient3]]+Таблица32[[#This Row],[Gruppa bank klient 2]] -> 0
A73: 71 | B73: RIZO MULK MCHJ | C73: Abrorbek | E73: 1000000 | F73: Go'zaloy | J73: -1 | L73: 0.25 | M73: 0.25 | P73: -0.25 | Q73: 0 | R73: 0.2 | S73: 0.2 | T73: -0.2 | U73: 0.2 | V73: -1 | W73: =Таблица32[[#This Row],[Столбец7]]*Таблица32[[#This Row],[Ishga kelish nazoratchi2]]% -> 0 | X73: =Таблица32[[#This Row],[Столбец7]]*Таблица32[[#This Row],[Ishga vaqtida kelish ketish]]% -> 0 | Y73: =Таблица32[[#This Row],[Столбец7]]*Таблица32[[#This Row],[Ishga kelish bank klient]]% -> 0 | Z73: =Таблица32[[#This Row],[Столбец7]]*Таблица32[[#This Row],[Gruppa buxgalter]]% -> -10000 | AB73: =Таблица32[[#This Row],[1c]]*Таблица32[[#This Row],[Столбец7]]/100 -> 0 | AC73: =SUM(Таблица32[[#This Row],[Didox]:[ мехнат]],Таблица32[[#This Row],[Avtokameral]])*Таблица32[[#This Row],[Столбец7]]/100 -> 2500 | AD73: =SUM(Таблица32[[#This Row],[Pul oqimlari]:[Foyda va zarar]])*Таблица32[[#This Row],[Столбец7]]/100 -> 4000 | AE73: =Таблица32[[#This Row],[Столбец7]]*Таблица32[[#This Row],[Nazoratchi]]% -> -10000 | AF73: =Таблица32[[#This Row],[Ishga vaqtida kelish nazoratchi]]+Таблица32[[#This Row],[Nazoratchi2]] -> -10000 | AG73: =Таблица32[[#This Row],[Ishga vaqtida kelish ketish2]]+Таблица32[[#This Row],[Gruppa buxgalter4]]+Таблица32[[#This Row],[1C baza3]]+Таблица32[[#This Row],[xatlar4]]+Таблица32[[#This Row],[Belgilangan otchetlar5]] -> -3500 | AH73: =Таблица32[[#This Row],[Ishga kelish bank klient3]]+Таблица32[[#This Row],[Gruppa bank klient 2]] -> 0
A74: 72 | B74: ENGLIFY | C74: Axmadjon | D74: Ruslan | E74: 11000000 | F74: Muslimbek | H74: 1 | J74: 1 | K74: 1 | L74: 0.25 | M74: 0.25 | P74: 0.25 | Q74: 0.2 | R74: -0.2 | S74: 0 | T74: -0.2 | U74: -0.2 | V74: 0.5 | W74: =Таблица32[[#This Row],[Столбец7]]*Таблица32[[#This Row],[Ishga kelish nazoratchi2]]% -> 0 | X74: =Таблица32[[#This Row],[Столбец7]]*Таблица32[[#This Row],[Ishga vaqtida kelish ketish]]% -> 0 | Y74: =Таблица32[[#This Row],[Столбец7]]*Таблица32[[#This Row],[Ishga kelish bank klient]]% -> 110000 | Z74: =Таблица32[[#This Row],[Столбец7]]*Таблица32[[#This Row],[Gruppa buxgalter]]% -> 110000 | AA74: =Таблица32[[#This Row],[Столбец7]]*Таблица32[[#This Row],[Gruppa bank klient ]]% -> 110000 | AB74: =Таблица32[[#This Row],[1c]]*Таблица32[[#This Row],[Столбец7]]/100 -> 0 | AC74: =SUM(Таблица32[[#This Row],[Didox]:[ мехнат]],Таблица32[[#This Row],[Avtokameral]])*Таблица32[[#This Row],[Столбец7]]/100 -> 82500 | AD74: =SUM(Таблица32[[#This Row],[Pul oqimlari]:[Foyda va zarar]])*Таблица32[[#This Row],[Столбец7]]/100 -> -44000 | AE74: =Таблица32[[#This Row],[Столбец7]]*Таблица32[[#This Row],[Nazoratchi]]% -> 55000 | AF74: =Таблица32[[#This Row],[Ishga vaqtida kelish nazoratchi]]+Таблица32[[#This Row],[Nazoratchi2]] -> 55000 | AG74: =Таблица32[[#This Row],[Ishga vaqtida kelish ketish2]]+Таблица32[[#This Row],[Gruppa buxgalter4]]+Таблица32[[#This Row],[1C baza3]]+Таблица32[[#This Row],[xatlar4]]+Таблица32[[#This Row],[Belgilangan otchetlar5]] -> 148500 | AH74: =Таблица32[[#This Row],[Ishga kelish bank klient3]]+Таблица32[[#This Row],[Gruppa bank klient 2]] -> 220000
A75: 73 | B75: J-R GROUP | C75: Mirabbos | D75: Azizbek | E75: 1000000 | F75: Muslimbek | H75: 1 | J75: 1 | K75: 1 | L75: -0.25 | M75: -0.25 | P75: 0.25 | Q75: -0.2 | R75: -0.2 | S75: -0.2 | T75: -0.2 | U75: -0.2 | V75: 0.5 | W75: =Таблица32[[#This Row],[Столбец7]]*Таблица32[[#This Row],[Ishga kelish nazoratchi2]]% -> 0 | X75: =Таблица32[[#This Row],[Столбец7]]*Таблица32[[#This Row],[Ishga vaqtida kelish ketish]]% -> 0 | Y75: =Таблица32[[#This Row],[Столбец7]]*Таблица32[[#This Row],[Ishga kelish bank klient]]% -> 10000 | Z75: =Таблица32[[#This Row],[Столбец7]]*Таблица32[[#This Row],[Gruppa buxgalter]]% -> 10000 | AA75: =Таблица32[[#This Row],[Столбец7]]*Таблица32[[#This Row],[Gruppa bank klient ]]% -> 10000 | AB75: =Таблица32[[#This Row],[1c]]*Таблица32[[#This Row],[Столбец7]]/100 -> 0 | AC75: =SUM(Таблица32[[#This Row],[Didox]:[ мехнат]],Таблица32[[#This Row],[Avtokameral]])*Таблица32[[#This Row],[Столбец7]]/100 -> -2500 | AD75: =SUM(Таблица32[[#This Row],[Pul oqimlari]:[Foyda va zarar]])*Таблица32[[#This Row],[Столбец7]]/100 -> -10000 | AE75: =Таблица32[[#This Row],[Столбец7]]*Таблица32[[#This Row],[Nazoratchi]]% -> 5000 | AF75: =Таблица32[[#This Row],[Ishga vaqtida kelish nazoratchi]]+Таблица32[[#This Row],[Nazoratchi2]] -> 5000 | AG75: =Таблица32[[#This Row],[Ishga vaqtida kelish ketish2]]+Таблица32[[#This Row],[Gruppa buxgalter4]]+Таблица32[[#This Row],[1C baza3]]+Таблица32[[#This Row],[xatlar4]]+Таблица32[[#This Row],[Belgilangan otchetlar5]] -> -2500 | AH75: =Таблица32[[#This Row],[Ishga kelish bank klient3]]+Таблица32[[#This Row],[Gruppa bank klient 2]] -> 20000
A76: 74 | B76: BADEX LIFE | C76: Muslimbek | D76: Ruslan | E76: 2500000 | F76: Go'zaloy | G76: -0.8 | H76: 1 | J76: -1 | K76: 1 | L76: 0.25 | M76: 0.25 | N76: 0.25 | P76: 0.25 | Q76: 0.2 | R76: 0.2 | S76: 0.2 | T76: 0.2 | U76: 0.2 | V76: -1 | W76: =Таблица32[[#This Row],[Столбец7]]*Таблица32[[#This Row],[Ishga kelish nazoratchi2]]% -> 0 | X76: =Таблица32[[#This Row],[Столбец7]]*Таблица32[[#This Row],[Ishga vaqtida kelish ketish]]% -> -20000 | Y76: =Таблица32[[#This Row],[Столбец7]]*Таблица32[[#This Row],[Ishga kelish bank klient]]% -> 25000 | Z76: =Таблица32[[#This Row],[Столбец7]]*Таблица32[[#This Row],[Gruppa buxgalter]]% -> -25000 | AA76: =Таблица32[[#This Row],[Столбец7]]*Таблица32[[#This Row],[Gruppa bank klient ]]% -> 25000 | AB76: =Таблица32[[#This Row],[1c]]*Таблица32[[#This Row],[Столбец7]]/100 -> 0 | AC76: =SUM(Таблица32[[#This Row],[Didox]:[ мехнат]],Таблица32[[#This Row],[Avtokameral]])*Таблица32[[#This Row],[Столбец7]]/100 -> 25000 | AD76: =SUM(Таблица32[[#This Row],[Pul oqimlari]:[Foyda va zarar]])*Таблица32[[#This Row],[Столбец7]]/100 -> 25000 | AE76: =Таблица32[[#This Row],[Столбец7]]*Таблица32[[#This Row],[Nazoratchi]]% -> -25000 | AF76: =Таблица32[[#This Row],[Ishga vaqtida kelish nazoratchi]]+Таблица32[[#This Row],[Nazoratchi2]] -> -25000 | AG76: =Таблица32[[#This Row],[Ishga vaqtida kelish ketish2]]+Таблица32[[#This Row],[Gruppa buxgalter4]]+Таблица32[[#This Row],[1C baza3]]+Таблица32[[#This Row],[xatlar4]]+Таблица32[[#This Row],[Belgilangan otchetlar5]] -> 5000 | AH76: =Таблица32[[#This Row],[Ishga kelish bank klient3]]+Таблица32[[#This Row],[Gruppa bank klient 2]] -> 50000
A77: 75 | B77: RONICS ENGINEERING TEAM | C77: Muslimbek | D77: Azizbek | E77: 700000 | F77: Go'zaloy | G77: -0.8 | H77: 1 | J77: 1 | K77: 1 | L77: 0.25 | M77: 0.25 | P77: 0.25 | Q77: 0 | R77: 0.2 | S77: 0.2 | T77: 0 | U77: 0 | V77: 0.5 | W77: =Таблица32[[#This Row],[Столбец7]]*Таблица32[[#This Row],[Ishga kelish nazoratchi2]]% -> 0 | X77: =Таблица32[[#This Row],[Столбец7]]*Таблица32[[#This Row],[Ishga vaqtida kelish ketish]]% -> -5600 | Y77: =Таблица32[[#This Row],[Столбец7]]*Таблица32[[#This Row],[Ishga kelish bank klient]]% -> 7000 | Z77: =Таблица32[[#This Row],[Столбец7]]*Таблица32[[#This Row],[Gruppa buxgalter]]% -> 7000 | AA77: =Таблица32[[#This Row],[Столбец7]]*Таблица32[[#This Row],[Gruppa bank klient ]]% -> 7000 | AB77: =Таблица32[[#This Row],[1c]]*Таблица32[[#This Row],[Столбец7]]/100 -> 0 | AC77: =SUM(Таблица32[[#This Row],[Didox]:[ мехнат]],Таблица32[[#This Row],[Avtokameral]])*Таблица32[[#This Row],[Столбец7]]/100 -> 5250 | AD77: =SUM(Таблица32[[#This Row],[Pul oqimlari]:[Foyda va zarar]])*Таблица32[[#This Row],[Столбец7]]/100 -> 2800 | AE77: =Таблица32[[#This Row],[Столбец7]]*Таблица32[[#This Row],[Nazoratchi]]% -> 3500 | AF77: =Таблица32[[#This Row],[Ishga vaqtida kelish nazoratchi]]+Таблица32[[#This Row],[Nazoratchi2]] -> 3500 | AG77: =Таблица32[[#This Row],[Ishga vaqtida kelish ketish2]]+Таблица32[[#This Row],[Gruppa buxgalter4]]+Таблица32[[#This Row],[1C baza3]]+Таблица32[[#This Row],[xatlar4]]+Таблица32[[#This Row],[Belgilangan otchetlar5]] -> 9450 | AH77: =Таблица32[[#This Row],[Ishga kelish bank klient3]]+Таблица32[[#This Row],[Gruppa bank klient 2]] -> 14000
A78: 76 | B78: Raximjonova Dilnoza YATT | C78: Go'zaloy | E78: 170000 | F78: Muslimbek | G78: 0.05 | J78: 1 | L78: 0 | M78: 0 | P78: 0 | Q78: 0 | R78: 0 | S78: 0 | T78: 0 | U78: 0 | V78: 0.5 | W78: =Таблица32[[#This Row],[Столбец7]]*Таблица32[[#This Row],[Ishga kelish nazoratchi2]]% -> 0 | X78: =Таблица32[[#This Row],[Столбец7]]*Таблица32[[#This Row],[Ishga vaqtida kelish ketish]]% -> 85 | Y78: =Таблица32[[#This Row],[Столбец7]]*Таблица32[[#This Row],[Ishga kelish bank klient]]% -> 0 | Z78: =Таблица32[[#This Row],[Столбец7]]*Таблица32[[#This Row],[Gruppa buxgalter]]% -> 1700 | AA78: =Таблица32[[#This Row],[Столбец7]]*Таблица32[[#This Row],[Gruppa bank klient ]]% -> 0 | AB78: =Таблица32[[#This Row],[1c]]*Таблица32[[#This Row],[Столбец7]]/100 -> 0 | AC78: =SUM(Таблица32[[#This Row],[Didox]:[ мехнат]],Таблица32[[#This Row],[Avtokameral]])*Таблица32[[#This Row],[Столбец7]]/100 -> 0 | AD78: =SUM(Таблица32[[#This Row],[Pul oqimlari]:[Foyda va zarar]])*Таблица32[[#This Row],[Столбец7]]/100 -> 0 | AE78: =Таблица32[[#This Row],[Столбец7]]*Таблица32[[#This Row],[Nazoratchi]]% -> 850 | AF78: =Таблица32[[#This Row],[Ishga vaqtida kelish nazoratchi]]+Таблица32[[#This Row],[Nazoratchi2]] -> 850 | AG78: =Таблица32[[#This Row],[Ishga vaqtida kelish ketish2]]+Таблица32[[#This Row],[Gruppa buxgalter4]]+Таблица32[[#This Row],[1C baza3]]+Таблица32[[#This Row],[xatlar4]]+Таблица32[[#This Row],[Belgilangan otchetlar5]] -> 1785 | AH78: =Таблица32[[#This Row],[Ishga kelish bank klient3]]+Таблица32[[#This Row],[Gruppa bank klient 2]] -> 0
A79: 77 | B79: HI UNIT | C79: Humora | D79: Azizbek | E79: 1000000 | F79: Go'zaloy | G79: -0.35 | H79: 1 | J79: 1 | K79: 1 | L79: 0.25 | M79: -0.25 | O79: 1 | P79: 0.25 | Q79: 0.2 | R79: 0.2 | S79: 0.2 | T79: 0.2 | U79: 0.2 | V79: 0.5 | W79: =Таблица32[[#This Row],[Столбец7]]*Таблица32[[#This Row],[Ishga kelish nazoratchi2]]% -> 0 | X79: =Таблица32[[#This Row],[Столбец7]]*Таблица32[[#This Row],[Ishga vaqtida kelish ketish]]% -> -3500 | Y79: =Таблица32[[#This Row],[Столбец7]]*Таблица32[[#This Row],[Ishga kelish bank klient]]% -> 10000 | Z79: =Таблица32[[#This Row],[Столбец7]]*Таблица32[[#This Row],[Gruppa buxgalter]]% -> 10000 | AA79: =Таблица32[[#This Row],[Столбец7]]*Таблица32[[#This Row],[Gruppa bank klient ]]% -> 10000 | AB79: =Таблица32[[#This Row],[1c]]*Таблица32[[#This Row],[Столбец7]]/100 -> 10000 | AC79: =SUM(Таблица32[[#This Row],[Didox]:[ мехнат]],Таблица32[[#This Row],[Avtokameral]])*Таблица32[[#This Row],[Столбец7]]/100 -> 2500 | AD79: =SUM(Таблица32[[#This Row],[Pul oqimlari]:[Foyda va zarar]])*Таблица32[[#This Row],[Столбец7]]/100 -> 10000 | AE79: =Таблица32[[#This Row],[Столбец7]]*Таблица32[[#This Row],[Nazoratchi]]% -> 5000 | AF79: =Таблица32[[#This Row],[Ishga vaqtida kelish nazoratchi]]+Таблица32[[#This Row],[Nazoratchi2]] -> 5000 | AG79: =Таблица32[[#This Row],[Ishga vaqtida kelish ketish2]]+Таблица32[[#This Row],[Gruppa buxgalter4]]+Таблица32[[#This Row],[1C baza3]]+Таблица32[[#This Row],[xatlar4]]+Таблица32[[#This Row],[Belgilangan otchetlar5]] -> 29000 | AH79: =Таблица32[[#This Row],[Ishga kelish bank klient3]]+Таблица32[[#This Row],[Gruppa bank klient 2]] -> 20000
A80: 78 | B80: BRAND NEW HOUSES | C80: Humora | E80: 10000000 | F80: Go'zaloy | G80: -0.35 | J80: 1 | L80: 0 | M80: -0.25 | N80: 0 | O80: 1 | P80: 0.25 | Q80: 0.2 | R80: 0 | S80: 0 | T80: 0.2 | U80: 0.2 | V80: 0.5 | W80: =Таблица32[[#This Row],[Столбец7]]*Таблица32[[#This Row],[Ishga kelish nazoratchi2]]% -> 0 | X80: =Таблица32[[#This Row],[Столбец7]]*Таблица32[[#This Row],[Ishga vaqtida kelish ketish]]% -> -35000 | Y80: =Таблица32[[#This Row],[Столбец7]]*Таблица32[[#This Row],[Ishga kelish bank klient]]% -> 0 | Z80: =Таблица32[[#This Row],[Столбец7]]*Таблица32[[#This Row],[Gruppa buxgalter]]% -> 100000 | AA80: =Таблица32[[#This Row],[Столбец7]]*Таблица32[[#This Row],[Gruppa bank klient ]]% -> 0 | AB80: =Таблица32[[#This Row],[1c]]*Таблица32[[#This Row],[Столбец7]]/100 -> 100000 | AC80: =SUM(Таблица32[[#This Row],[Didox]:[ мехнат]],Таблица32[[#This Row],[Avtokameral]])*Таблица32[[#This Row],[Столбец7]]/100 -> 0 | AD80: =SUM(Таблица32[[#This Row],[Pul oqimlari]:[Foyda va zarar]])*Таблица32[[#This Row],[Столбец7]]/100 -> 60000 | AE80: =Таблица32[[#This Row],[Столбец7]]*Таблица32[[#This Row],[Nazoratchi]]% -> 50000 | AF80: =Таблица32[[#This Row],[Ishga vaqtida kelish nazoratchi]]+Таблица32[[#This Row],[Nazoratchi2]] -> 50000 | AG80: =Таблица32[[#This Row],[Ishga vaqtida kelish ketish2]]+Таблица32[[#This Row],[Gruppa buxgalter4]]+Таблица32[[#This Row],[1C baza3]]+Таблица32[[#This Row],[xatlar4]]+Таблица32[[#This Row],[Belgilangan otchetlar5]] -> 225000 | AH80: =Таблица32[[#This Row],[Ishga kelish bank klient3]]+Таблица32[[#This Row],[Gruppa bank klient 2]] -> 0
A81: 79 | B81: MARGARET | C81: Otabek | E81: 500000 | F81: Muslimbek | J81: 1 | L81: 0.25 | M81: 0.25 | P81: 0.25 | Q81: 0 | R81: 0 | S81: 0 | T81: 0 | U81: 0 | V81: 0.5 | W81: =Таблица32[[#This Row],[Столбец7]]*Таблица32[[#This Row],[Ishga kelish nazoratchi2]]% -> 0 | X81: =Таблица32[[#This Row],[Столбец7]]*Таблица32[[#This Row],[Ishga vaqtida kelish ketish]]% -> 0 | Y81: =Таблица32[[#This Row],[Столбец7]]*Таблица32[[#This Row],[Ishga kelish bank klient]]% -> 0 | Z81: =Таблица32[[#This Row],[Столбец7]]*Таблица32[[#This Row],[Gruppa buxgalter]]% -> 5000 | AA81: =Таблица32[[#This Row],[Столбец7]]*Таблица32[[#This Row],[Gruppa bank klient ]]% -> 0 | AB81: 0 | AC81: =SUM(Таблица32[[#This Row],[Didox]:[ мехнат]],Таблица32[[#This Row],[Avtokameral]])*Таблица32[[#This Row],[Столбец7]]/100 -> 3750 | AD81: =SUM(Таблица32[[#This Row],[Pul oqimlari]:[Foyda va zarar]])*Таблица32[[#This Row],[Столбец7]]/100 -> 0 | AE81: =Таблица32[[#This Row],[Столбец7]]*Таблица32[[#This Row],[Nazoratchi]]% -> 2500 | AF81: =Таблица32[[#This Row],[Ishga vaqtida kelish nazoratchi]]+Таблица32[[#This Row],[Nazoratchi2]] -> 2500 | AG81: =Таблица32[[#This Row],[Ishga vaqtida kelish ketish2]]+Таблица32[[#This Row],[Gruppa buxgalter4]]+Таблица32[[#This Row],[1C baza3]]+Таблица32[[#This Row],[xatlar4]]+Таблица32[[#This Row],[Belgilangan otchetlar5]] -> 8750 | AH81: =Таблица32[[#This Row],[Ishga kelish bank klient3]]+Таблица32[[#This Row],[Gruppa bank klient 2]] -> 0
A82: 80 | B82: IT-INTEGRATOR | C82: Muslimbek | D82: Azizbek | E82: 1500000 | F82: Go'zaloy | G82: -0.8 | H82: 1 | J82: -0.5 | K82: 1 | L82: 0.25 | M82: 0.25 | N82: 0.25 | O82: 1 | P82: 0.25 | Q82: 0.2 | R82: 0.2 | S82: 0.2 | T82: 0.2 | U82: 0.2 | V82: -0.5 | W82: =Таблица32[[#This Row],[Столбец7]]*Таблица32[[#This Row],[Ishga kelish nazoratchi2]]% -> 0 | X82: =Таблица32[[#This Row],[Столбец7]]*Таблица32[[#This Row],[Ishga vaqtida kelish ketish]]% -> -12000 | Y82: =Таблица32[[#This Row],[Столбец7]]*Таблица32[[#This Row],[Ishga kelish bank klient]]% -> 15000 | Z82: =Таблица32[[#This Row],[Столбец7]]*Таблица32[[#This Row],[Gruppa buxgalter]]% -> -7500 | AA82: =Таблица32[[#This Row],[Столбец7]]*Таблица32[[#This Row],[Gruppa bank klient ]]% -> 15000 | AB82: =Таблица32[[#This Row],[1c]]*Таблица32[[#This Row],[Столбец7]]/100 -> 15000 | AC82: =SUM(Таблица32[[#This Row],[Didox]:[ мехнат]],Таблица32[[#This Row],[Avtokameral]])*Таблица32[[#This Row],[Столбец7]]/100 -> 15000 | AD82: =SUM(Таблица32[[#This Row],[Pul oqimlari]:[Foyda va zarar]])*Таблица32[[#This Row],[Столбец7]]/100 -> 15000 | AE82: =Таблица32[[#This Row],[Столбец7]]*Таблица32[[#This Row],[Nazoratchi]]% -> -7500 | AF82: =Таблица32[[#This Row],[Ishga vaqtida kelish nazoratchi]]+Таблица32[[#This Row],[Nazoratchi2]] -> -7500 | AG82: =Таблица32[[#This Row],[Ishga vaqtida kelish ketish2]]+Таблица32[[#This Row],[Gruppa buxgalter4]]+Таблица32[[#This Row],[1C baza3]]+Таблица32[[#This Row],[xatlar4]]+Таблица32[[#This Row],[Belgilangan otchetlar5]] -> 25500 | AH82: =Таблица32[[#This Row],[Ishga kelish bank klient3]]+Таблица32[[#This Row],[Gruppa bank klient 2]] -> 30000
A83: 81 | B83: UNI GLOBAL | C83: Humora | D83: Azizbek | E83: 0 | F83: Go'zaloy | G83: -0.35 | H83: 1 | J83: 1 | K83: 1 | L83: 0.25 | M83: 0.25 | P83: 0.25 | Q83: 0.2 | R83: 0.2 | S83: 0.2 | T83: 0.2 | U83: 0.2 | V83: 0.5 | W83: =Таблица32[[#This Row],[Столбец7]]*Таблица32[[#This Row],[Ishga kelish nazoratchi2]]% -> 0 | X83: =Таблица32[[#This Row],[Столбец7]]*Таблица32[[#This Row],[Ishga vaqtida kelish ketish]]% -> 0 | Y83: =Таблица32[[#This Row],[Столбец7]]*Таблица32[[#This Row],[Ishga kelish bank klient]]% -> 0 | Z83: =Таблица32[[#This Row],[Столбец7]]*Таблица32[[#This Row],[Gruppa buxgalter]]% -> 0 | AA83: =Таблица32[[#This Row],[Столбец7]]*Таблица32[[#This Row],[Gruppa bank klient ]]% -> 0 | AB83: =Таблица32[[#This Row],[1c]]*Таблица32[[#This Row],[Столбец7]]/100 -> 0 | AC83: =SUM(Таблица32[[#This Row],[Didox]:[ мехнат]],Таблица32[[#This Row],[Avtokameral]])*Таблица32[[#This Row],[Столбец7]]/100 -> 0 | AD83: =SUM(Таблица32[[#This Row],[Pul oqimlari]:[Foyda va zarar]])*Таблица32[[#This Row],[Столбец7]]/100 -> 0 | AE83: =Таблица32[[#This Row],[Столбец7]]*Таблица32[[#This Row],[Nazoratchi]]% -> 0 | AF83: =Таблица32[[#This Row],[Ishga vaqtida kelish nazoratchi]]+Таблица32[[#This Row],[Nazoratchi2]] -> 0 | AG83: =Таблица32[[#This Row],[Ishga vaqtida kelish ketish2]]+Таблица32[[#This Row],[Gruppa buxgalter4]]+Таблица32[[#This Row],[1C baza3]]+Таблица32[[#This Row],[xatlar4]]+Таблица32[[#This Row],[Belgilangan otchetlar5]] -> 0 | AH83: =Таблица32[[#This Row],[Ishga kelish bank klient3]]+Таблица32[[#This Row],[Gruppa bank klient 2]] -> 0
A84: 82 | B84: NOEL TRIP | C84: Javohir | D84: Azizbek | E84: 800000 | F84: Muslimbek | G84: -0.05 | H84: 1 | J84: -0.5 | K84: 1 | L84: 0.25 | M84: 0.25 | P84: 0.25 | Q84: -0.2 | R84: 0.2 | S84: -0.2 | T84: -0.2 | U84: -0.2 | V84: -0.5 | W84: =Таблица32[[#This Row],[Столбец7]]*Таблица32[[#This Row],[Ishga kelish nazoratchi2]]% -> 0 | X84: =Таблица32[[#This Row],[Столбец7]]*Таблица32[[#This Row],[Ishga vaqtida kelish ketish]]% -> -400 | Y84: =Таблица32[[#This Row],[Столбец7]]*Таблица32[[#This Row],[Ishga kelish bank klient]]% -> 8000 | Z84: =Таблица32[[#This Row],[Столбец7]]*Таблица32[[#This Row],[Gruppa buxgalter]]% -> -4000 | AA84: =Таблица32[[#This Row],[Столбец7]]*Таблица32[[#This Row],[Gruppa bank klient ]]% -> 8000 | AB84: =Таблица32[[#This Row],[1c]]*Таблица32[[#This Row],[Столбец7]]/100 -> 0 | AC84: =SUM(Таблица32[[#This Row],[Didox]:[ мехнат]],Таблица32[[#This Row],[Avtokameral]])*Таблица32[[#This Row],[Столбец7]]/100 -> 6000 | AD84: =SUM(Таблица32[[#This Row],[Pul oqimlari]:[Foyda va zarar]])*Таблица32[[#This Row],[Столбец7]]/100 -> -4800 | AE84: =Таблица32[[#This Row],[Столбец7]]*Таблица32[[#This Row],[Nazoratchi]]% -> -4000 | AF84: =Таблица32[[#This Row],[Ishga vaqtida kelish nazoratchi]]+Таблица32[[#This Row],[Nazoratchi2]] -> -4000 | AG84: =Таблица32[[#This Row],[Ishga vaqtida kelish ketish2]]+Таблица32[[#This Row],[Gruppa buxgalter4]]+Таблица32[[#This Row],[1C baza3]]+Таблица32[[#This Row],[xatlar4]]+Таблица32[[#This Row],[Belgilangan otchetlar5]] -> -3200 | AH84: =Таблица32[[#This Row],[Ishga kelish bank klient3]]+Таблица32[[#This Row],[Gruppa bank klient 2]] -> 16000
A85: 83 | B85: KOLBERG MEDICAL | C85: Ilhom | D85: Bekzod | E85: 15000000 | F85: Go'zaloy | L85: 0 | M85: 0 | P85: 0 | Q85: 0 | R85: 0 | S85: 0 | T85: 0 | U85: 0 | W85: =Таблица32[[#This Row],[Столбец7]]*Таблица32[[#This Row],[Ishga kelish nazoratchi2]]% -> 0 | X85: =Таблица32[[#This Row],[Столбец7]]*Таблица32[[#This Row],[Ishga vaqtida kelish ketish]]% -> 0 | Y85: =Таблица32[[#This Row],[Столбец7]]*Таблица32[[#This Row],[Ishga kelish bank klient]]% -> 0 | Z85: =Таблица32[[#This Row],[Столбец7]]*Таблица32[[#This Row],[Gruppa buxgalter]]% -> 0 | AA85: =Таблица32[[#This Row],[Столбец7]]*Таблица32[[#This Row],[Gruppa bank klient ]]% -> 0 | AB85: =Таблица32[[#This Row],[1c]]*Таблица32[[#This Row],[Столбец7]]/100 -> 0 | AC85: =SUM(Таблица32[[#This Row],[Didox]:[ мехнат]],Таблица32[[#This Row],[Avtokameral]])*Таблица32[[#This Row],[Столбец7]]/100 -> 0 | AD85: =SUM(Таблица32[[#This Row],[Pul oqimlari]:[Foyda va zarar]])*Таблица32[[#This Row],[Столбец7]]/100 -> 0 | AE85: =Таблица32[[#This Row],[Столбец7]]*Таблица32[[#This Row],[Nazoratchi]]% -> 0 | AF85: =Таблица32[[#This Row],[Ishga vaqtida kelish nazoratchi]]+Таблица32[[#This Row],[Nazoratchi2]] -> 0 | AG85: =Таблица32[[#This Row],[Ishga vaqtida kelish ketish2]]+Таблица32[[#This Row],[Gruppa buxgalter4]]+Таблица32[[#This Row],[1C baza3]]+Таблица32[[#This Row],[xatlar4]]+Таблица32[[#This Row],[Belgilangan otchetlar5]] -> 0 | AH85: =Таблица32[[#This Row],[Ishga kelish bank klient3]]+Таблица32[[#This Row],[Gruppa bank klient 2]] -> 0
A86: 84 | B86: TULYAGANOV FX | C86: Mirabbos | D86: Azizbek | E86: 1000000 | F86: Muslimbek | H86: 1 | J86: 1 | K86: 1 | L86: -0.25 | M86: -0.25 | P86: -0.25 | Q86: -0.2 | R86: -0.2 | S86: -0.2 | T86: -0.2 | U86: -0.2 | V86: 0.5 | W86: =Таблица32[[#This Row],[Столбец7]]*Таблица32[[#This Row],[Ishga kelish nazoratchi2]]% -> 0 | X86: =Таблица32[[#This Row],[Столбец7]]*Таблица32[[#This Row],[Ishga vaqtida kelish ketish]]% -> 0 | Y86: =Таблица32[[#This Row],[Столбец7]]*Таблица32[[#This Row],[Ishga kelish bank klient]]% -> 10000 | Z86: =Таблица32[[#This Row],[Столбец7]]*Таблица32[[#This Row],[Gruppa buxgalter]]% -> 10000 | AA86: =Таблица32[[#This Row],[Столбец7]]*Таблица32[[#This Row],[Gruppa bank klient ]]% -> 10000 | AB86: =Таблица32[[#This Row],[1c]]*Таблица32[[#This Row],[Столбец7]]/100 -> 0 | AC86: =SUM(Таблица32[[#This Row],[Didox]:[ мехнат]],Таблица32[[#This Row],[Avtokameral]])*Таблица32[[#This Row],[Столбец7]]/100 -> -7500 | AD86: =SUM(Таблица32[[#This Row],[Pul oqimlari]:[Foyda va zarar]])*Таблица32[[#This Row],[Столбец7]]/100 -> -10000 | AE86: =Таблица32[[#This Row],[Столбец7]]*Таблица32[[#This Row],[Nazoratchi]]% -> 5000 | AF86: =Таблица32[[#This Row],[Ishga vaqtida kelish nazoratchi]]+Таблица32[[#This Row],[Nazoratchi2]] -> 5000 | AG86: =Таблица32[[#This Row],[Ishga vaqtida kelish ketish2]]+Таблица32[[#This Row],[Gruppa buxgalter4]]+Таблица32[[#This Row],[1C baza3]]+Таблица32[[#This Row],[xatlar4]]+Таблица32[[#This Row],[Belgilangan otchetlar5]] -> -7500 | AH86: =Таблица32[[#This Row],[Ishga kelish bank klient3]]+Таблица32[[#This Row],[Gruppa bank klient 2]] -> 20000
A87: 85 | B87: SOFI TEAM | C87: Ruslan | D87: Ruslan | E87: 700000 | F87: Go'zaloy | H87: 1 | K87: 1 | L87: 0.25 | M87: 0.25 | P87: 0.25 | Q87: 0 | R87: 0 | S87: 0 | T87: 0 | U87: 0 | W87: =Таблица32[[#This Row],[Столбец7]]*Таблица32[[#This Row],[Ishga kelish nazoratchi2]]% -> 0 | X87: =Таблица32[[#This Row],[Столбец7]]*Таблица32[[#This Row],[Ishga vaqtida kelish ketish]]% -> 0 | Y87: =Таблица32[[#This Row],[Столбец7]]*Таблица32[[#This Row],[Ishga kelish bank klient]]% -> 7000 | Z87: =Таблица32[[#This Row],[Столбец7]]*Таблица32[[#This Row],[Gruppa buxgalter]]% -> 0 | AA87: =Таблица32[[#This Row],[Столбец7]]*Таблица32[[#This Row],[Gruppa bank klient ]]% -> 7000 | AB87: =Таблица32[[#This Row],[1c]]*Таблица32[[#This Row],[Столбец7]]/100 -> 0 | AC87: =SUM(Таблица32[[#This Row],[Didox]:[ мехнат]],Таблица32[[#This Row],[Avtokameral]])*Таблица32[[#This Row],[Столбец7]]/100 -> 5250 | AD87: =SUM(Таблица32[[#This Row],[Pul oqimlari]:[Foyda va zarar]])*Таблица32[[#This Row],[Столбец7]]/100 -> 0 | AE87: =Таблица32[[#This Row],[Столбец7]]*Таблица32[[#This Row],[Nazoratchi]]% -> 0 | AF87: =Таблица32[[#This Row],[Ishga vaqtida kelish nazoratchi]]+Таблица32[[#This Row],[Nazoratchi2]] -> 0 | AG87: =Таблица32[[#This Row],[Ishga vaqtida kelish ketish2]]+Таблица32[[#This Row],[Gruppa buxgalter4]]+Таблица32[[#This Row],[1C baza3]]+Таблица32[[#This Row],[xatlar4]]+Таблица32[[#This Row],[Belgilangan otchetlar5]] -> 5250 | AH87: =Таблица32[[#This Row],[Ishga kelish bank klient3]]+Таблица32[[#This Row],[Gruppa bank klient 2]] -> 14000
A88: 86 | B88: RM MUROD BIZNES | C88: Abrorbek | D88: Ruslan | E88: 1000000 | F88: Go'zaloy | H88: 1 | J88: 1 | K88: 1 | L88: 0.25 | M88: -0.25 | P88: 0.25 | Q88: 0 | R88: 0.2 | S88: 0 | T88: 0 | U88: 0 | V88: 0.5 | W88: =Таблица32[[#This Row],[Столбец7]]*Таблица32[[#This Row],[Ishga kelish nazoratchi2]]% -> 0 | X88: =Таблица32[[#This Row],[Столбец7]]*Таблица32[[#This Row],[Ishga vaqtida kelish ketish]]% -> 0 | Y88: =Таблица32[[#This Row],[Столбец7]]*Таблица32[[#This Row],[Ishga kelish bank klient]]% -> 10000 | Z88: =Таблица32[[#This Row],[Столбец7]]*Таблица32[[#This Row],[Gruppa buxgalter]]% -> 10000 | AA88: =Таблица32[[#This Row],[Столбец7]]*Таблица32[[#This Row],[Gruppa bank klient ]]% -> 10000 | AB88: =Таблица32[[#This Row],[1c]]*Таблица32[[#This Row],[Столбец7]]/100 -> 0 | AC88: =SUM(Таблица32[[#This Row],[Didox]:[ мехнат]],Таблица32[[#This Row],[Avtokameral]])*Таблица32[[#This Row],[Столбец7]]/100 -> 2500 | AD88: =SUM(Таблица32[[#This Row],[Pul oqimlari]:[Foyda va zarar]])*Таблица32[[#This Row],[Столбец7]]/100 -> 2000 | AE88: =Таблица32[[#This Row],[Столбец7]]*Таблица32[[#This Row],[Nazoratchi]]% -> 5000 | AF88: =Таблица32[[#This Row],[Ishga vaqtida kelish nazoratchi]]+Таблица32[[#This Row],[Nazoratchi2]] -> 5000 | AG88: =Таблица32[[#This Row],[Ishga vaqtida kelish ketish2]]+Таблица32[[#This Row],[Gruppa buxgalter4]]+Таблица32[[#This Row],[1C baza3]]+Таблица32[[#This Row],[xatlar4]]+Таблица32[[#This Row],[Belgilangan otchetlar5]] -> 14500 | AH88: =Таблица32[[#This Row],[Ishga kelish bank klient3]]+Таблица32[[#This Row],[Gruppa bank klient 2]] -> 20000
A89: 87 | B89: BAROKAT TEAM | C89: Ruslan | D89: Ruslan | E89: 700000 | F89: Go'zaloy | H89: 1 | K89: 1 | L89: 0.25 | M89: 0.25 | N89: 0.25 | P89: 0.25 | Q89: 0 | R89: 0 | S89: 0 | T89: 0 | U89: 0 | W89: =Таблица32[[#This Row],[Столбец7]]*Таблица32[[#This Row],[Ishga kelish nazoratchi2]]% -> 0 | X89: =Таблица32[[#This Row],[Столбец7]]*Таблица32[[#This Row],[Ishga vaqtida kelish ketish]]% -> 0 | Y89: =Таблица32[[#This Row],[Столбец7]]*Таблица32[[#This Row],[Ishga kelish bank klient]]% -> 7000 | Z89: =Таблица32[[#This Row],[Столбец7]]*Таблица32[[#This Row],[Gruppa buxgalter]]% -> 0 | AA89: =Таблица32[[#This Row],[Столбец7]]*Таблица32[[#This Row],[Gruppa bank klient ]]% -> 7000 | AB89: =Таблица32[[#This Row],[1c]]*Таблица32[[#This Row],[Столбец7]]/100 -> 0 | AC89: =SUM(Таблица32[[#This Row],[Didox]:[ мехнат]],Таблица32[[#This Row],[Avtokameral]])*Таблица32[[#This Row],[Столбец7]]/100 -> 7000 | AD89: =SUM(Таблица32[[#This Row],[Pul oqimlari]:[Foyda va zarar]])*Таблица32[[#This Row],[Столбец7]]/100 -> 0 | AE89: =Таблица32[[#This Row],[Столбец7]]*Таблица32[[#This Row],[Nazoratchi]]% -> 0 | AF89: =Таблица32[[#This Row],[Ishga vaqtida kelish nazoratchi]]+Таблица32[[#This Row],[Nazoratchi2]] -> 0 | AG89: =Таблица32[[#This Row],[Ishga vaqtida kelish ketish2]]+Таблица32[[#This Row],[Gruppa buxgalter4]]+Таблица32[[#This Row],[1C baza3]]+Таблица32[[#This Row],[xatlar4]]+Таблица32[[#This Row],[Belgilangan otchetlar5]] -> 7000 | AH89: =Таблица32[[#This Row],[Ishga kelish bank klient3]]+Таблица32[[#This Row],[Gruppa bank klient 2]] -> 14000
A90: 88 | B90: UZART GROUP PROJEKT | C90: Abrorbek | D90: Azizbek | E90: 3000000 | F90: Go'zaloy | H90: 1 | J90: 1 | K90: 1 | L90: 0.25 | M90: 0.25 | P90: 0.25 | Q90: 0 | R90: 0 | S90: 0 | T90: 0.2 | U90: 0 | V90: 0.5 | W90: =Таблица32[[#This Row],[Столбец7]]*Таблица32[[#This Row],[Ishga kelish nazoratchi2]]% -> 0 | X90: =Таблица32[[#This Row],[Столбец7]]*Таблица32[[#This Row],[Ishga vaqtida kelish ketish]]% -> 0 | Y90: =Таблица32[[#This Row],[Столбец7]]*Таблица32[[#This Row],[Ishga kelish bank klient]]% -> 30000 | Z90: =Таблица32[[#This Row],[Столбец7]]*Таблица32[[#This Row],[Gruppa buxgalter]]% -> 30000 | AA90: =Таблица32[[#This Row],[Столбец7]]*Таблица32[[#This Row],[Gruppa bank klient ]]% -> 30000 | AB90: =Таблица32[[#This Row],[1c]]*Таблица32[[#This Row],[Столбец7]]/100 -> 0 | AC90: =SUM(Таблица32[[#This Row],[Didox]:[ мехнат]],Таблица32[[#This Row],[Avtokameral]])*Таблица32[[#This Row],[Столбец7]]/100 -> 22500 | AD90: =SUM(Таблица32[[#This Row],[Pul oqimlari]:[Foyda va zarar]])*Таблица32[[#This Row],[Столбец7]]/100 -> 6000 | AE90: =Таблица32[[#This Row],[Столбец7]]*Таблица32[[#This Row],[Nazoratchi]]% -> 15000 | AF90: =Таблица32[[#This Row],[Ishga vaqtida kelish nazoratchi]]+Таблица32[[#This Row],[Nazoratchi2]] -> 15000 | AG90: =Таблица32[[#This Row],[Ishga vaqtida kelish ketish2]]+Таблица32[[#This Row],[Gruppa buxgalter4]]+Таблица32[[#This Row],[1C baza3]]+Таблица32[[#This Row],[xatlar4]]+Таблица32[[#This Row],[Belgilangan otchetlar5]] -> 58500 | AH90: =Таблица32[[#This Row],[Ishga kelish bank klient3]]+Таблица32[[#This Row],[Gruppa bank klient 2]] -> 60000
A91: 89 | B91: KORBAZAAR | C91: Abdugani | D91: Ruslan | E91: 3000000 | F91: Go'zaloy | G91: -0.8 | H91: 1 | J91: 1 | K91: 1 | L91: 0 | M91: 0.25 | N91: 0.25 | P91: -0.25 | Q91: 0.2 | R91: 0.2 | S91: 0.2 | T91: -0.2 | U91: -0.2 | V91: 0.5 | W91: =Таблица32[[#This Row],[Столбец7]]*Таблица32[[#This Row],[Ishga kelish nazoratchi2]]% -> 0 | X91: =Таблица32[[#This Row],[Столбец7]]*Таблица32[[#This Row],[Ishga vaqtida kelish ketish]]% -> -24000 | Y91: =Таблица32[[#This Row],[Столбец7]]*Таблица32[[#This Row],[Ishga kelish bank klient]]% -> 30000 | Z91: =Таблица32[[#This Row],[Столбец7]]*Таблица32[[#This Row],[Gruppa buxgalter]]% -> 30000 | AA91: =Таблица32[[#This Row],[Столбец7]]*Таблица32[[#This Row],[Gruppa bank klient ]]% -> 30000 | AB91: =Таблица32[[#This Row],[1c]]*Таблица32[[#This Row],[Столбец7]]/100 -> 0 | AC91: =SUM(Таблица32[[#This Row],[Didox]:[ мехнат]],Таблица32[[#This Row],[Avtokameral]])*Таблица32[[#This Row],[Столбец7]]/100 -> 7500 | AD91: =SUM(Таблица32[[#This Row],[Pul oqimlari]:[Foyda va zarar]])*Таблица32[[#This Row],[Столбец7]]/100 -> 6000 | AE91: =Таблица32[[#This Row],[Столбец7]]*Таблица32[[#This Row],[Nazoratchi]]% -> 15000 | AF91: =Таблица32[[#This Row],[Ishga vaqtida kelish nazoratchi]]+Таблица32[[#This Row],[Nazoratchi2]] -> 15000 | AG91: =Таблица32[[#This Row],[Ishga vaqtida kelish ketish2]]+Таблица32[[#This Row],[Gruppa buxgalter4]]+Таблица32[[#This Row],[1C baza3]]+Таблица32[[#This Row],[xatlar4]]+Таблица32[[#This Row],[Belgilangan otchetlar5]] -> 19500 | AH91: =Таблица32[[#This Row],[Ishga kelish bank klient3]]+Таблица32[[#This Row],[Gruppa bank klient 2]] -> 60000
A92: 90 | B92: NURDEVAI | C92: Otabek | D92: Ruslan | E92: 500000 | F92: Muslimbek | H92: 1 | J92: 1 | K92: 1 | L92: 0.25 | M92: 0.25 | P92: 0.25 | Q92: 0 | R92: 0 | S92: 0 | T92: 0 | U92: 0 | V92: 0.5 | W92: =Таблица32[[#This Row],[Столбец7]]*Таблица32[[#This Row],[Ishga kelish nazoratchi2]]% -> 0 | X92: =Таблица32[[#This Row],[Столбец7]]*Таблица32[[#This Row],[Ishga vaqtida kelish ketish]]% -> 0 | Y92: =Таблица32[[#This Row],[Столбец7]]*Таблица32[[#This Row],[Ishga kelish bank klient]]% -> 5000 | Z92: =Таблица32[[#This Row],[Столбец7]]*Таблица32[[#This Row],[Gruppa buxgalter]]% -> 5000 | AA92: =Таблица32[[#This Row],[Столбец7]]*Таблица32[[#This Row],[Gruppa bank klient ]]% -> 5000 | AB92: =Таблица32[[#This Row],[1c]]*Таблица32[[#This Row],[Столбец7]]/100 -> 0 | AC92: =SUM(Таблица32[[#This Row],[Didox]:[ мехнат]],Таблица32[[#This Row],[Avtokameral]])*Таблица32[[#This Row],[Столбец7]]/100 -> 3750 | AD92: =SUM(Таблица32[[#This Row],[Pul oqimlari]:[Foyda va zarar]])*Таблица32[[#This Row],[Столбец7]]/100 -> 0 | AE92: =Таблица32[[#This Row],[Столбец7]]*Таблица32[[#This Row],[Nazoratchi]]% -> 2500 | AF92: =Таблица32[[#This Row],[Ishga vaqtida kelish nazoratchi]]+Таблица32[[#This Row],[Nazoratchi2]] -> 2500 | AG92: =Таблица32[[#This Row],[Ishga vaqtida kelish ketish2]]+Таблица32[[#This Row],[Gruppa buxgalter4]]+Таблица32[[#This Row],[1C baza3]]+Таблица32[[#This Row],[xatlar4]]+Таблица32[[#This Row],[Belgilangan otchetlar5]] -> 8750 | AH92: =Таблица32[[#This Row],[Ishga kelish bank klient3]]+Таблица32[[#This Row],[Gruppa bank klient 2]] -> 10000
A93: 91 | B93: MEDICAL GM | C93: Musobek | E93: 2500000 | F93: Go'zaloy | G93: 0.9 | J93: -0.5 | L93: -0.25 | M93: 0.25 | P93: 0.25 | Q93: 0.2 | R93: 0.2 | S93: 0.2 | T93: 0.2 | U93: -0.2 | V93: -0.5 | W93: =Таблица32[[#This Row],[Столбец7]]*Таблица32[[#This Row],[Ishga kelish nazoratchi2]]% -> 0 | X93: =Таблица32[[#This Row],[Столбец7]]*Таблица32[[#This Row],[Ishga vaqtida kelish ketish]]% -> 22500 | Y93: =Таблица32[[#This Row],[Столбец7]]*Таблица32[[#This Row],[Ishga kelish bank klient]]% -> 0 | Z93: =Таблица32[[#This Row],[Столбец7]]*Таблица32[[#This Row],[Gruppa buxgalter]]% -> -12500 | AA93: =Таблица32[[#This Row],[Столбец7]]*Таблица32[[#This Row],[Gruppa bank klient ]]% -> 0 | AB93: =Таблица32[[#This Row],[1c]]*Таблица32[[#This Row],[Столбец7]]/100 -> 0 | AC93: =SUM(Таблица32[[#This Row],[Didox]:[ мехнат]],Таблица32[[#This Row],[Avtokameral]])*Таблица32[[#This Row],[Столбец7]]/100 -> 6250 | AD93: =SUM(Таблица32[[#This Row],[Pul oqimlari]:[Foyda va zarar]])*Таблица32[[#This Row],[Столбец7]]/100 -> 15000 | AE93: =Таблица32[[#This Row],[Столбец7]]*Таблица32[[#This Row],[Nazoratchi]]% -> -12500 | AF93: =Таблица32[[#This Row],[Ishga vaqtida kelish nazoratchi]]+Таблица32[[#This Row],[Nazoratchi2]] -> -12500 | AG93: =Таблица32[[#This Row],[Ishga vaqtida kelish ketish2]]+Таблица32[[#This Row],[Gruppa buxgalter4]]+Таблица32[[#This Row],[1C baza3]]+Таблица32[[#This Row],[xatlar4]]+Таблица32[[#This Row],[Belgilangan otchetlar5]] -> 31250 | AH93: =Таблица32[[#This Row],[Ishga kelish bank klient3]]+Таблица32[[#This Row],[Gruppa bank klient 2]] -> 0
A94: 92 | B94: LUNA CATERING TEAM | C94: Humora | D94: Azizbek | E94: 0 | F94: Go'zaloy | G94: -0.35 | H94: 1 | J94: 1 | K94: 1 | L94: 0.25 | M94: -0.25 | P94: 0.25 | Q94: 0.2 | R94: 0.2 | S94: 0.2 | T94: 0.2 | U94: 0.2 | V94: 0.5 | W94: =Таблица32[[#This Row],[Столбец7]]*Таблица32[[#This Row],[Ishga kelish nazoratchi2]]% -> 0 | X94: =Таблица32[[#This Row],[Столбец7]]*Таблица32[[#This Row],[Ishga vaqtida kelish ketish]]% -> 0 | Y94: =Таблица32[[#This Row],[Столбец7]]*Таблица32[[#This Row],[Ishga kelish bank klient]]% -> 0 | Z94: =Таблица32[[#This Row],[Столбец7]]*Таблица32[[#This Row],[Gruppa buxgalter]]% -> 0 | AA94: =Таблица32[[#This Row],[Столбец7]]*Таблица32[[#This Row],[Gruppa bank klient ]]% -> 0 | AB94: =Таблица32[[#This Row],[1c]]*Таблица32[[#This Row],[Столбец7]]/100 -> 0 | AC94: =SUM(Таблица32[[#This Row],[Didox]:[ мехнат]],Таблица32[[#This Row],[Avtokameral]])*Таблица32[[#This Row],[Столбец7]]/100 -> 0 | AD94: =SUM(Таблица32[[#This Row],[Pul oqimlari]:[Foyda va zarar]])*Таблица32[[#This Row],[Столбец7]]/100 -> 0 | AE94: =Таблица32[[#This Row],[Столбец7]]*Таблица32[[#This Row],[Nazoratchi]]% -> 0 | AF94: =Таблица32[[#This Row],[Ishga vaqtida kelish nazoratchi]]+Таблица32[[#This Row],[Nazoratchi2]] -> 0 | AG94: =Таблица32[[#This Row],[Ishga vaqtida kelish ketish2]]+Таблица32[[#This Row],[Gruppa buxgalter4]]+Таблица32[[#This Row],[1C baza3]]+Таблица32[[#This Row],[xatlar4]]+Таблица32[[#This Row],[Belgilangan otchetlar5]] -> 0 | AH94: =Таблица32[[#This Row],[Ishga kelish bank klient3]]+Таблица32[[#This Row],[Gruppa bank klient 2]] -> 0
A95: 93 | B95: IE ASILBEKOVA ZULFIYA | C95: Dilhush | D95: Azizbek | E95: 700000 | F95: Go'zaloy | H95: 1 | J95: 1 | K95: 1 | L95: 0.25 | M95: 0.25 | O95: 1 | P95: 0.25 | Q95: 0 | R95: 0.2 | S95: 0.2 | T95: 0 | U95: 0 | V95: 0.5 | W95: =Таблица32[[#This Row],[Столбец7]]*Таблица32[[#This Row],[Ishga kelish nazoratchi2]]% -> 0 | X95: =Таблица32[[#This Row],[Столбец7]]*Таблица32[[#This Row],[Ishga vaqtida kelish ketish]]% -> 0 | Y95: =Таблица32[[#This Row],[Столбец7]]*Таблица32[[#This Row],[Ishga kelish bank klient]]% -> 7000 | Z95: =Таблица32[[#This Row],[Столбец7]]*Таблица32[[#This Row],[Gruppa buxgalter]]% -> 7000 | AA95: =Таблица32[[#This Row],[Столбец7]]*Таблица32[[#This Row],[Gruppa bank klient ]]% -> 7000 | AB95: =Таблица32[[#This Row],[1c]]*Таблица32[[#This Row],[Столбец7]]/100 -> 7000 | AC95: =SUM(Таблица32[[#This Row],[Didox]:[ мехнат]],Таблица32[[#This Row],[Avtokameral]])*Таблица32[[#This Row],[Столбец7]]/100 -> 5250 | AD95: =SUM(Таблица32[[#This Row],[Pul oqimlari]:[Foyda va zarar]])*Таблица32[[#This Row],[Столбец7]]/100 -> 2800 | AE95: =Таблица32[[#This Row],[Столбец7]]*Таблица32[[#This Row],[Nazoratchi]]% -> 3500 | AF95: =Таблица32[[#This Row],[Ishga vaqtida kelish nazoratchi]]+Таблица32[[#This Row],[Nazoratchi2]] -> 3500 | AG95: =Таблица32[[#This Row],[Ishga vaqtida kelish ketish2]]+Таблица32[[#This Row],[Gruppa buxgalter4]]+Таблица32[[#This Row],[1C baza3]]+Таблица32[[#This Row],[xatlar4]]+Таблица32[[#This Row],[Belgilangan otchetlar5]] -> 22050 | AH95: =Таблица32[[#This Row],[Ishga kelish bank klient3]]+Таблица32[[#This Row],[Gruppa bank klient 2]] -> 14000
A96: 94 | B96: QUDRATILLA ILA | C96: Otabek | D96: Ruslan | E96: 700000 | F96: Muslimbek | H96: 1 | J96: 1 | K96: 1 | L96: 0.25 | M96: 0.25 | O96: 1 | P96: 0.25 | Q96: 0.2 | R96: 0.2 | S96: 0.2 | T96: 0.2 | U96: 0.2 | V96: 0.5 | W96: =Таблица32[[#This Row],[Столбец7]]*Таблица32[[#This Row],[Ishga kelish nazoratchi2]]% -> 0 | X96: =Таблица32[[#This Row],[Столбец7]]*Таблица32[[#This Row],[Ishga vaqtida kelish ketish]]% -> 0 | Y96: =Таблица32[[#This Row],[Столбец7]]*Таблица32[[#This Row],[Ishga kelish bank klient]]% -> 7000 | Z96: =Таблица32[[#This Row],[Столбец7]]*Таблица32[[#This Row],[Gruppa buxgalter]]% -> 7000 | AA96: =Таблица32[[#This Row],[Столбец7]]*Таблица32[[#This Row],[Gruppa bank klient ]]% -> 7000 | AB96: =Таблица32[[#This Row],[1c]]*Таблица32[[#This Row],[Столбец7]]/100 -> 7000 | AC96: =SUM(Таблица32[[#This Row],[Didox]:[ мехнат]],Таблица32[[#This Row],[Avtokameral]])*Таблица32[[#This Row],[Столбец7]]/100 -> 5250 | AD96: =SUM(Таблица32[[#This Row],[Pul oqimlari]:[Foyda va zarar]])*Таблица32[[#This Row],[Столбец7]]/100 -> 7000 | AE96: =Таблица32[[#This Row],[Столбец7]]*Таблица32[[#This Row],[Nazoratchi]]% -> 3500 | AF96: =Таблица32[[#This Row],[Ishga vaqtida kelish nazoratchi]]+Таблица32[[#This Row],[Nazoratchi2]] -> 3500 | AG96: =Таблица32[[#This Row],[Ishga vaqtida kelish ketish2]]+Таблица32[[#This Row],[Gruppa buxgalter4]]+Таблица32[[#This Row],[1C baza3]]+Таблица32[[#This Row],[xatlar4]]+Таблица32[[#This Row],[Belgilangan otchetlar5]] -> 26250 | AH96: =Таблица32[[#This Row],[Ishga kelish bank klient3]]+Таблица32[[#This Row],[Gruppa bank klient 2]] -> 14000
A97: 95 | B97: MG BUSINESS BROKERS | C97: Otabek | E97: 500000 | F97: Muslimbek | J97: 1 | L97: 0.25 | M97: 0.25 | P97: 0.25 | Q97: 0 | R97: 0 | S97: 0 | T97: 0 | U97: 0 | V97: 0.5 | W97: =Таблица32[[#This Row],[Столбец7]]*Таблица32[[#This Row],[Ishga kelish nazoratchi2]]% -> 0 | X97: =Таблица32[[#This Row],[Столбец7]]*Таблица32[[#This Row],[Ishga vaqtida kelish ketish]]% -> 0 | Y97: =Таблица32[[#This Row],[Столбец7]]*Таблица32[[#This Row],[Ishga kelish bank klient]]% -> 0 | Z97: =Таблица32[[#This Row],[Столбец7]]*Таблица32[[#This Row],[Gruppa buxgalter]]% -> 5000 | AA97: =Таблица32[[#This Row],[Столбец7]]*Таблица32[[#This Row],[Gruppa bank klient ]]% -> 0 | AB97: =Таблица32[[#This Row],[1c]]*Таблица32[[#This Row],[Столбец7]]/100 -> 0 | AC97: =SUM(Таблица32[[#This Row],[Didox]:[ мехнат]],Таблица32[[#This Row],[Avtokameral]])*Таблица32[[#This Row],[Столбец7]]/100 -> 3750 | AD97: =SUM(Таблица32[[#This Row],[Pul oqimlari]:[Foyda va zarar]])*Таблица32[[#This Row],[Столбец7]]/100 -> 0 | AE97: =Таблица32[[#This Row],[Столбец7]]*Таблица32[[#This Row],[Nazoratchi]]% -> 2500 | AF97: =Таблица32[[#This Row],[Ishga vaqtida kelish nazoratchi]]+Таблица32[[#This Row],[Nazoratchi2]] -> 2500 | AG97: =Таблица32[[#This Row],[Ishga vaqtida kelish ketish2]]+Таблица32[[#This Row],[Gruppa buxgalter4]]+Таблица32[[#This Row],[1C baza3]]+Таблица32[[#This Row],[xatlar4]]+Таблица32[[#This Row],[Belgilangan otchetlar5]] -> 8750 | AH97: =Таблица32[[#This Row],[Ishga kelish bank klient3]]+Таблица32[[#This Row],[Gruppa bank klient 2]] -> 0
A98: 96 | B98: FIDELITY SERVISE | C98: Humora | D98: Azizbek | E98: 1000000 | F98: Go'zaloy | G98: -0.35 | H98: 1 | J98: 1 | K98: 1 | L98: 0.25 | M98: 0.25 | O98: 1 | P98: 0.25 | Q98: 0.2 | R98: 0.2 | S98: 0.2 | T98: 0.2 | U98: 0.2 | V98: 0.5 | W98: =Таблица32[[#This Row],[Столбец7]]*Таблица32[[#This Row],[Ishga kelish nazoratchi2]]% -> 0 | X98: =Таблица32[[#This Row],[Столбец7]]*Таблица32[[#This Row],[Ishga vaqtida kelish ketish]]% -> -3500 | Y98: =Таблица32[[#This Row],[Столбец7]]*Таблица32[[#This Row],[Ishga kelish bank klient]]% -> 10000 | Z98: =Таблица32[[#This Row],[Столбец7]]*Таблица32[[#This Row],[Gruppa buxgalter]]% -> 10000 | AA98: =Таблица32[[#This Row],[Столбец7]]*Таблица32[[#This Row],[Gruppa bank klient ]]% -> 10000 | AB98: =Таблица32[[#This Row],[1c]]*Таблица32[[#This Row],[Столбец7]]/100 -> 10000 | AC98: =SUM(Таблица32[[#This Row],[Didox]:[ мехнат]],Таблица32[[#This Row],[Avtokameral]])*Таблица32[[#This Row],[Столбец7]]/100 -> 7500 | AD98: =SUM(Таблица32[[#This Row],[Pul oqimlari]:[Foyda va zarar]])*Таблица32[[#This Row],[Столбец7]]/100 -> 10000 | AE98: =Таблица32[[#This Row],[Столбец7]]*Таблица32[[#This Row],[Nazoratchi]]% -> 5000 | AF98: =Таблица32[[#This Row],[Ishga vaqtida kelish nazoratchi]]+Таблица32[[#This Row],[Nazoratchi2]] -> 5000 | AG98: =Таблица32[[#This Row],[Ishga vaqtida kelish ketish2]]+Таблица32[[#This Row],[Gruppa buxgalter4]]+Таблица32[[#This Row],[1C baza3]]+Таблица32[[#This Row],[xatlar4]]+Таблица32[[#This Row],[Belgilangan otchetlar5]] -> 34000 | AH98: =Таблица32[[#This Row],[Ishga kelish bank klient3]]+Таблица32[[#This Row],[Gruppa bank klient 2]] -> 20000
A99: 97 | B99: EASTREX | C99: Dilhush | D99: Azizbek | E99: 700000 | F99: Go'zaloy | H99: 1 | J99: 1 | K99: 1 | L99: 0.25 | M99: 0.25 | O99: 1 | P99: 0.25 | Q99: 0 | R99: 0.2 | S99: 0.2 | T99: 0 | U99: 0 | V99: 0.5 | W99: =Таблица32[[#This Row],[Столбец7]]*Таблица32[[#This Row],[Ishga kelish nazoratchi2]]% -> 0 | X99: =Таблица32[[#This Row],[Столбец7]]*Таблица32[[#This Row],[Ishga vaqtida kelish ketish]]% -> 0 | Y99: =Таблица32[[#This Row],[Столбец7]]*Таблица32[[#This Row],[Ishga kelish bank klient]]% -> 7000 | Z99: =Таблица32[[#This Row],[Столбец7]]*Таблица32[[#This Row],[Gruppa buxgalter]]% -> 7000 | AA99: =Таблица32[[#This Row],[Столбец7]]*Таблица32[[#This Row],[Gruppa bank klient ]]% -> 7000 | AB99: =Таблица32[[#This Row],[1c]]*Таблица32[[#This Row],[Столбец7]]/100 -> 7000 | AC99: =SUM(Таблица32[[#This Row],[Didox]:[ мехнат]],Таблица32[[#This Row],[Avtokameral]])*Таблица32[[#This Row],[Столбец7]]/100 -> 5250 | AD99: =SUM(Таблица32[[#This Row],[Pul oqimlari]:[Foyda va zarar]])*Таблица32[[#This Row],[Столбец7]]/100 -> 2800 | AE99: =Таблица32[[#This Row],[Столбец7]]*Таблица32[[#This Row],[Nazoratchi]]% -> 3500 | AF99: =Таблица32[[#This Row],[Ishga vaqtida kelish nazoratchi]]+Таблица32[[#This Row],[Nazoratchi2]] -> 3500 | AG99: =Таблица32[[#This Row],[Ishga vaqtida kelish ketish2]]+Таблица32[[#This Row],[Gruppa buxgalter4]]+Таблица32[[#This Row],[1C baza3]]+Таблица32[[#This Row],[xatlar4]]+Таблица32[[#This Row],[Belgilangan otchetlar5]] -> 22050 | AH99: =Таблица32[[#This Row],[Ishga kelish bank klient3]]+Таблица32[[#This Row],[Gruppa bank klient 2]] -> 14000
A100: 98 | B100: XURSHID AVTO | C100: Otabek | D100: Ruslan | E100: 750000 | F100: Muslimbek | H100: 1 | J100: 1 | K100: 1 | L100: 0.25 | M100: 0.25 | O100: 1 | P100: 0.25 | Q100: 0.2 | R100: 0.2 | S100: 0.2 | T100: 0.2 | U100: 0.2 | V100: 0.5 | W100: =Таблица32[[#This Row],[Столбец7]]*Таблица32[[#This Row],[Ishga kelish nazoratchi2]]% -> 0 | X100: =Таблица32[[#This Row],[Столбец7]]*Таблица32[[#This Row],[Ishga vaqtida kelish ketish]]% -> 0 | Y100: =Таблица32[[#This Row],[Столбец7]]*Таблица32[[#This Row],[Ishga kelish bank klient]]% -> 7500 | Z100: =Таблица32[[#This Row],[Столбец7]]*Таблица32[[#This Row],[Gruppa buxgalter]]% -> 7500 | AA100: =Таблица32[[#This Row],[Столбец7]]*Таблица32[[#This Row],[Gruppa bank klient ]]% -> 7500 | AB100: =Таблица32[[#This Row],[1c]]*Таблица32[[#This Row],[Столбец7]]/100 -> 7500 | AC100: =SUM(Таблица32[[#This Row],[Didox]:[ мехнат]],Таблица32[[#This Row],[Avtokameral]])*Таблица32[[#This Row],[Столбец7]]/100 -> 5625 | AD100: =SUM(Таблица32[[#This Row],[Pul oqimlari]:[Foyda va zarar]])*Таблица32[[#This Row],[Столбец7]]/100 -> 7500 | AE100: =Таблица32[[#This Row],[Столбец7]]*Таблица32[[#This Row],[Nazoratchi]]% -> 3750 | AF100: =Таблица32[[#This Row],[Ishga vaqtida kelish nazoratchi]]+Таблица32[[#This Row],[Nazoratchi2]] -> 3750 | AG100: =Таблица32[[#This Row],[Ishga vaqtida kelish ketish2]]+Таблица32[[#This Row],[Gruppa buxgalter4]]+Таблица32[[#This Row],[1C baza3]]+Таблица32[[#This Row],[xatlar4]]+Таблица32[[#This Row],[Belgilangan otchetlar5]] -> 28125 | AH100: =Таблица32[[#This Row],[Ishga kelish bank klient3]]+Таблица32[[#This Row],[Gruppa bank klient 2]] -> 15000
A101: 99 | B101: VIKTORIYA TIBBIY KORIK | C101: Musobek | D101: Azizbek | E101: 700000 | F101: Go'zaloy | G101: 0.9 | H101: 1 | J101: 1 | K101: 1 | L101: 0.25 | M101: 0.25 | P101: -0.25 | Q101: 0.2 | R101: 0.2 | S101: 0.2 | T101: 0.2 | U101: 0.2 | W101: =Таблица32[[#This Row],[Столбец7]]*Таблица32[[#This Row],[Ishga kelish nazoratchi2]]% -> 0 | X101: =Таблица32[[#This Row],[Столбец7]]*Таблица32[[#This Row],[Ishga vaqtida kelish ketish]]% -> 6300 | Y101: =Таблица32[[#This Row],[Столбец7]]*Таблица32[[#This Row],[Ishga kelish bank klient]]% -> 7000 | Z101: =Таблица32[[#This Row],[Столбец7]]*Таблица32[[#This Row],[Gruppa buxgalter]]% -> 7000 | AA101: =Таблица32[[#This Row],[Столбец7]]*Таблица32[[#This Row],[Gruppa bank klient ]]% -> 7000 | AB101: =Таблица32[[#This Row],[1c]]*Таблица32[[#This Row],[Столбец7]]/100 -> 0 | AC101: =SUM(Таблица32[[#This Row],[Didox]:[ мехнат]],Таблица32[[#This Row],[Avtokameral]])*Таблица32[[#This Row],[Столбец7]]/100 -> 1750 | AD101: =SUM(Таблица32[[#This Row],[Pul oqimlari]:[Foyda va zarar]])*Таблица32[[#This Row],[Столбец7]]/100 -> 7000 | AE101: =Таблица32[[#This Row],[Столбец7]]*Таблица32[[#This Row],[Nazoratchi]]% -> 0 | AF101: =Таблица32[[#This Row],[Ishga vaqtida kelish nazoratchi]]+Таблица32[[#This Row],[Nazoratchi2]] -> 0 | AG101: =Таблица32[[#This Row],[Ishga vaqtida kelish ketish2]]+Таблица32[[#This Row],[Gruppa buxgalter4]]+Таблица32[[#This Row],[1C baza3]]+Таблица32[[#This Row],[xatlar4]]+Таблица32[[#This Row],[Belgilangan otchetlar5]] -> 22050 | AH101: =Таблица32[[#This Row],[Ishga kelish bank klient3]]+Таблица32[[#This Row],[Gruppa bank klient 2]] -> 14000
...

Sheet vast
B1: Jami tolanishi kerak | C1: Tolandi | D1: Qoldi
A2: Belstore vostanavleniya
A3: Doniyor | B3: 4000000 | C3: 4000000 | D3: =B3-C3 -> 0
A4: Diyorbek | B4: 3000000 | C4: 3000000 | D4: =B4-C4 -> 0
A5: Musobek | B5: 4500000 | C5: 4500000 | D5: =B5-C5 -> 0
A6: Shahzoda | B6: 1000000 | C6: 1000000 | D6: =B6-C6 -> 0
A7: Yorqinoy | B7: 11500000 | C7: 11500000 | D7: =B7-C7 -> 0
A8: Jami | B8: 24000000 | C8: 24000000 | D8: =B8-C8 -> 0
A9: Buyuk turon
A10: Maxmuda | B10: 3000000 | C10: 3000000 | D10: 0
A11: Yorqinoy | B11: 6000000 | C11: =B11 -> 6000000 | D11: 0
A12: Jami | B12: 9000000 | C12: 9000000 | D12: =B12-C12 -> 0
A13: Universal nutrition
A14: Gulrux | B14: 2500000 | C14: 2500000 | D14: =B14-C14 -> 0
A15: Yorqinoy | B15: 2500000 | C15: 2500000 | D15: =B15-C15 -> 0
A16: Jami | B16: =B14+B15 -> 5000000 | C16: =C14+C15 -> 5000000 | D16: =B16-C16 -> 0
A17: Sardor firmalari
A18: Jamshid | B18: 2500000 | C18: 2500000 | D18: =B18-C18 -> 0
A19: Yorqinoy | B19: 2500000 | C19: 2500000 | D19: =B19-C19 -> 0
A20: Jami | B20: 5000000 | D20: =D18+D19 -> 0
A21: Living stone
A22: Maxmuda | B22: 7000000 | C22: 7000000 | D22: =B22-C22 -> 0
A23: Gozaloy | B23: 3000000 | C23: 3000000 | D23: =B23-C23 -> 0
A24: Yorqinoy | B24: 10000000 | C24: 10000000 | D24: =B24-C24 -> 0
A25: Jami | B25: =SUM(B22:B24) -> 20000000 | C25: =SUM(C22:C24) -> 20000000 | D25: =SUM(D22:D24) -> 0
A26: Unity
A27: Axmadjon | B27: 6000000 | C27: 6000000 | D27: =B27-C27 -> 0
A28: Gozaloy | B28: 8000000 | C28: =B28 -> 8000000 | D28: =B28-C28 -> 0
A29: Maxmuda | B29: 2000000 | C29: =B29 -> 2000000 | D29: =B29-C29 -> 0
A30: Yorqinoy | B30: 9000000 | C30: 9000000 | D30: =B30-C30 -> 0
A31: Jami | B31: =SUM(B27:B30) -> 25000000 | D31: =SUM(D27:D30) -> 0
A32: Safety
A33: Humora | B33: 1400000 | C33: 1400000 | D33: =B33-C33 -> 0
A34: Yorqinoy | B34: 1400000 | C34: 1400000 | D34: =B34-C34 -> 0
A35: Jami | B35: =SUM(B33:B34) -> 2800000 | C35: =SUM(C33:C34) -> 2800000 | D35: =SUM(D33:D34) -> 0
A36: Divan
A37: Musobek | B37: 2500000 | C37: 2500000 | D37: =B37-C37 -> 0
A38: Yorqinoy | B38: 2500000 | C38: 2500000 | D38: =B38-C38 -> 0
A39: Jami | B39: =SUM(B37:B38) -> 5000000 | C39: =SUM(C37:C38) -> 5000000 | D39: =SUM(D37:D38) -> 0
A40: Anvar farm
A41: Musobek | B41: 12000000 | C41: =6000000+6000000 -> 12000000 | D41: =B41-C41 -> 0
A42: Dilhush | B42: 12000000 | C42: =2000000+6000000+4000000 -> 12000000 | D42: =B42-C42 -> 0
A43: Yorqinoy | B43: 24000000 | C43: 24000000 | D43: =B43-C43 -> 0
A44: Jami | B44: =B41+B42+B43 -> 48000000 | C44: =C41+C42+C43 -> 48000000 | D44: =D41+D42+D43 -> 0
A45: Shifo Xasan
A46: Yorqinoy | B46: 7500000 | C46: 7500000 | D46: 0
A47: Jami | B47: =B46 -> 7500000 | C47: =C46 -> 7500000 | D47: 0
A48: Tim building
A49: Yorqinoy | B49: 3000000 | C49: 3000000
A50: Javoxir | B50: 2000000 | C50: 2000000
A51: Jami | B51: =B49+B50 -> 5000000
A52: Madina farm
